Workbook
Name AsOfDate: 'Instructions & Assumptions'!$B$4
Name ATNW_Active: 'Instructions & Assumptions'!$B$28
Name Bajaj_TL_Maturity: 'Instructions & Assumptions'!$B$52
Name Bajaj_TL_PrincOS: 'Repayment Schedule'!$D$63
Name Bajaj_TL_PrincRepaid: 'Repayment Schedule'!$C$63
Name Bajaj_TL_SNo: 'Instructions & Assumptions'!$B$57
Name BFRR_Bajaj: 'Instructions & Assumptions'!$B$16
Name BMK_12M_MCLR_SIB: 'Instructions & Assumptions'!$C$18
Name BMK_1Y_MCLR_RBL: 'Instructions & Assumptions'!$C$15
Name BMK_3M_MCLR_YBL: 'Instructions & Assumptions'!$C$16
Name BMK_3M_TBILL: 'Instructions & Assumptions'!$C$13
Name BMK_6M_IMCLR_ICICI: 'Instructions & Assumptions'!$C$17
Name BMK_BFRR: 'Instructions & Assumptions'!$C$19
Name BMK_FD_RATE: 'Instructions & Assumptions'!$C$21
Name BMK_REPO: 'Instructions & Assumptions'!$C$14
Name BMK_TERM_SOFR: 'Instructions & Assumptions'!$C$20
Name Bucket1_DebtTotal: 'Lender Summary'!$D$10
Name Bucket1_Interest: 'Interest Schedule'!$I$40
Name Bucket1_TL_Total: 'Lender Summary'!$B$10
Name CA_Active: 'Instructions & Assumptions'!$B$29
Name CL_Active: 'Instructions & Assumptions'!$B$30
Name CovenantBreached: 'Covenant Tracker'!$B$33
Name CovenantCompliant: 'Covenant Tracker'!$B$31
Name CovenantCount: 'Covenant Tracker'!$B$30
Name CovenantNearBreach: 'Covenant Tracker'!$B$32
Name CovenantPending: 'Covenant Tracker'!$B$34
Name DaysInYear: 'Instructions & Assumptions'!$B$7
Name EBITDA_Active: 'Instructions & Assumptions'!$B$24
Name FA_Active: 'Instructions & Assumptions'!$B$33
Name FBMainsTotal: 'Lender Summary'!$B$10
Name FD_Rate_RBL: 'Instructions & Assumptions'!$B$20
Name FDBackedTotal: 'Lender Summary'!$D$30
Name FIN_ATNW: 'Instructions & Assumptions'!$C$29
Name FIN_CA: 'Instructions & Assumptions'!$C$30
Name FIN_CL: 'Instructions & Assumptions'!$C$31
Name FIN_EBITDA: 'Instructions & Assumptions'!$C$25
Name FIN_FA_NET: 'Instructions & Assumptions'!$C$34
Name FIN_INT_EXP: 'Instructions & Assumptions'!$C$33
Name FIN_PRINC_REP: 'Instructions & Assumptions'!$C$38
Name FIN_PROM_SHARE: 'Instructions & Assumptions'!$C$37
Name FIN_RATING: 'Instructions & Assumptions'!$C$36
Name FIN_SCHED_REPAY: 'Instructions & Assumptions'!$C$40
Name FIN_SEC_DEBT: 'Instructions & Assumptions'!$C$35
Name FIN_TAX_PAID: 'Instructions & Assumptions'!$C$39
Name FIN_TERM_DEBT: 'Instructions & Assumptions'!$C$27
Name FIN_TNW: 'Instructions & Assumptions'!$C$28
Name FIN_TOL: 'Instructions & Assumptions'!$C$32
Name FIN_TOTAL_DEBT: 'Instructions & Assumptions'!$C$26
Name FinancialBasis: 'Instructions & Assumptions'!$C$10
Name FinBasis: 'Instructions & Assumptions'!$B$8
Name FX_USD_INR: 'Instructions & Assumptions'!$B$5
Name HedgeNotionalTotal: 'Lender Summary'!$C$37
Name IMCLR_ICICI_6M: 'Instructions & Assumptions'!$B$14
Name IntExp_Active: 'Instructions & Assumptions'!$B$32
Name LenderFilter: Dashboard!$H$5
Name MCLR_RBL_1Y: 'Instructions & Assumptions'!$B$12
Name MCLR_SIB_12M: 'Instructions & Assumptions'!$B$15
Name MCLR_YBL_3M: 'Instructions & Assumptions'!$B$13
Name NFBContingent: 'Lender Summary'!$D$20
Name NFBMainsTotal: 'Lender Summary'!$C$10

Sheet Cover Page
A1: JINDAL COKE LIMITED
A2: Debt Monitoring Model
A4: ="As of: " & TEXT(AsOfDate,"dd-mmm-yyyy") -> As of: 31-Mar-2026
B6: Active Lenders | D6: {=ROUND(SUMPRODUCT(1/COUNTIF('Facility Master'!B5:B38,'Facility Master'!B5:B38&"")),0)} -> 5
B7: Total Facility Lines (incl. sub-limits) | D7: =COUNTIF('Facility Master'!A5:A38,">0") -> 34
B8: Sanctioned Debt (₹ Cr) | D8: =SanctionedDebt -> 1320.7
B9: NFB Contingent (₹ Cr) | D9: =NFBContingent -> 815
B10: As-of Date | D10: =AsOfDate -> 46112
B11: FD-Backed Separate Lines (₹ Cr) | D11: =FDBackedTotal -> 100
B12: Prepared by | D12: Divyanshu Vatsa · Treasury
A13: WORKBOOK TAB GUIDE
A14: Tab | C14: Description
A15: Cover Page | C15: This page — model summary and tab map.
A16: Notes | C16: Methodology and reading guide for first-time viewers.
A17: Dashboard | C17: Senior management one-pager — KPI tiles, covenant status, lender concentration, narratives.
A18: Instructions & Assumptions | C18: Core inputs, benchmark rates, financial assumptions, sanction-letter caps.
A19: Facility Master | C19: Single source of truth — all 34 facilities with structural, pricing, and tenor data.
A20: Lender Summary | C20: Three-bucket aggregation: Sanctioned Debt, NFB Contingent, Separate Lines, by lender.
A21: Working Capital Facilities | C21: Operational view of all WC fund-based lines with cap-basis aggregation.
A22: Term Loans | C22: Detailed view of the three term loans with parameters and totals.
A23: Non-Fund Based Facilities | C23: LCs, SBLCs, BGs, Capex LCs, and hedge notional facilities.
A24: Repayment Schedule | C24: 53-period quarterly schedule for the three TLs and consolidated.
A25: Interest Schedule | C25: Annual interest and commission cost by facility; weighted-average debt cost.
... A32: Validation Engine | C32: 51-check internal validation engine — PPT-referenced Master Status (PASS/FAIL/Critical).

Sheet Notes
A1: MODEL NOTES & METHODOLOGY — Path B (Optimized)
A2: Prepared by Divyanshu Vatsa · Treasury · Last revised: 8 May 2026
A4: 1. BUCKET DECISION TREE
A5: Q1. | B5: Is the facility a sub-limit of another facility already in the model? Either (a) labelled in the sanction letter, or (b) sharing a binding cap with an umbrella facility such that drawing it reduces the umbrella's available capacity. If YES → BUCKET 0 (excluded from totals).
A6: Q2. | B6: Is the facility FD-backed (collateralised by 100% Fixed Deposit)? If YES → BUCKET 3 (Separate Lines). Currently only RBL FDOD ₹100 Cr.
A7: Q3. | B7: Is the facility fund-based (FB, FB-Term, FB-FCY)? If YES → BUCKET 1 (FB Mains). Currently 4 facilities: YBL TL ₹320.7 + Bajaj TL ₹150 + ICICI CC ₹50 + RBL TL Main ₹200 = ₹720.7 Cr.
A8: Q4. | B8: Is the facility non-fund-based (NFB)? If YES → BUCKET 2 (NFB Mains). Currently 4 facilities: YBL LC ₹200 + ICICI LC ₹150 + SIB LC ₹150 + RBL LC Main ₹100 = ₹600 Cr.
A9: Memo. | B9: Hedge notional limits (RBL LER ₹20 + SIB Forward ₹3) are derivative caps, not credit facilities. Tracked in Lender Summary Memo line, not in any bucket.
A11: 2. KPI DEFINITIONS
A12: • | B12: Sanctioned Debt: = Bucket 1 + Bucket 2 = ₹1,320.7 Cr. Sum of all FB and NFB main parent facilities at sanction face value, excluding FD-backed lines. Industry-standard 'total credit sanctioned at parent level' view used in CRILC reporting, rating agency analyses, and bank credit memos. Distinct from drawn debt. Reconciles to sanction-letter caps: YBL TL 320.7 + YBL LC 200 + Bajaj TL 150 + ICICI Total 200 + SIB LC 150 + RBL TL 200 + RBL LC 100 = 1,320.7.
A13: • | B13: FB Economic Debt: = Bucket 1 alone = ₹720.7 Cr. The fund-based parent facilities at sanction face. Used as cost basis for weighted-average debt cost calculation (interest sits only on FB facilities).
A14: • | B14: NFB Mains: = Bucket 2 alone = ₹600 Cr. Pure NFB parent facilities, before adding sub-limit overlays.
A15: • | B15: NFB Contingent: = Bucket 2 + NFB sub-limits whose parent is a FB Main = ₹815 Cr. The two FB-Main NFB sub-limits counted are RBL SBLC for Buyer's Credit ₹190 Cr and RBL Capex LC ₹25 Cr (both sub of TL Main ₹200). Both create distinct third-party contingent exposure even though they consume TL Main capacity. The Lender Summary Bucket 2 column shows pure NFB Mains; the NFB Contingent KPI adds the in-FB-umbrella contingents.
A16: • | B16: FD-Backed (Separate Lines): = Bucket 3 = ₹100 Cr. RBL FDOD only — self-collateralised by 100% FD; explicitly excluded from RBL's ₹300 Cr Overall Borrower exposure cap per 31-Dec-2025 letter.
A17: • | B17: Hedge Notional (Memo): = ₹23 Cr (RBL LER 20 + SIB Forward 3). Derivative limits, not credit facilities. Out of all buckets; informational only.
A19: 3. SANCTION LETTER SOURCES
A20: • | B20: YES Bank: TL ₹320.7 Cr per Sanction Letter dated 16-Dec-2024 (Ref YBL/DEL/FI/1500/2024-25); pricing addendum 28-Mar-2025 changed spread T-Bill 3M + 2.45% → +2.52%. WC umbrella ₹200 Cr cap (incl ₹25 Cr treasury) per latest Renewal cum Addendum dated 19-Mar-2026 (Ref YBL/DEL/LC/FI/06790/03/2026). LC parent ₹200 Cr per original 9-May-2023 letter; Financial BG/SBLC ₹200 sub of LC; PIF ₹100, WCDL ₹50, CC ₹25 share the ₹200 WC cap → all sub-limits.
A21: • | B21: RBL Bank: Three Main Limits per 31-Dec-2025 Renewal cum Modification letter (Ref CAD/DEL/1093/2025-26): LC Main ₹100, TL Main ₹200, FDOD ₹100. Overall Borrower exposure capped ₹300 Cr (excl FD). Sub-limits explicitly labelled in letter: BG ₹25, PID ₹100, SBLC ₹100, LCBD ₹100, CC ₹100, WCDL ₹100, LER ₹20 (all sub of LC); SBLC for BC ₹190, Capex LC ₹25 (sub of TL); LC backed by FD ₹50 (sub of FDOD). Earlier letters dated 13-Mar-2025 (BC WC USD 11M / ₹100 Cr) and 27-Mar-2025 (BC CAPEX USD 20M / ₹172 Cr) consolidated into 31-Dec-2025 structure: 'Extension of availability period till December 2026 for the conversion o/s SBLCs/Buyers Credit to term loan' — therefore treated as sub-limits of TL Main.
A22: • | B22: Bajaj Finance: TL ₹150 Cr per 18-Aug-2025 sole letter. Pricing 8.60% (BFRR 8.50% + 10 bps). 8-yr tenor incl 12-mo moratorium. 28 quarterly instalments. 1st pari-passu on FA at Khurunti Coke Plant; MSC 1.25x.
A23: • | B23: ICICI Bank: FB ₹50 (CC, with WCDL ₹50 as interchangeable sub-limit) + NFB ₹150 (LC parent, with SBLC ₹150 + BG-Performance ₹25 + BG-Financial ₹5 nested inside) per CAL dated 16-Sep-2025 (issued 31-Oct-2025) and Addendum 11-Nov-2025. Total A+B = ₹200 Cr per Annexure I. LC to JSL Global Commodities Pte Ltd capped INR 25 Cr.
A24: • | B24: South Indian Bank: LC ₹150 Cr cap per 21-Jun-2025 Renewal letter; cap explicit: 'Total LC limit (including Capex LC) shall not exceed Rs.150.0 Crores'. Capex LC ₹50 → shared-cap sub-limit of LC. SBLC ₹150 (sub of LC), CCOL ₹50 (sub of LC), WCDL ₹50 (sub of CCOL). Forward Contract ₹3 Cr → hedge notional memo.
A26: 4. KEY TREATMENT DECISIONS
A27: • | B27: RBL Term Loan repayment schedule excluded from quarterly schedule. Drawdown pending — existing BC instruments converting to TL by Dec-2026 per latest letter. Sanction face ₹200 Cr remains in Bucket 1 / Sanctioned Debt; only the repayment schedule defers until drawdown completes.
A28: • | B28: RBL BC GIFT WC ₹100 Cr (per 13-Mar-2025 letter) and BC CAPEX ₹172 Cr (per 27-Mar-2025 letter) are superseded by the 31-Dec-2025 consolidated structure. Both reclassified to Bucket 0 (sub-limits of TL Main). Avoids ~₹272 Cr of double-counting that existed in prior version.
A29: • | B29: YBL PIF, WCDL, CC, BG/SBLC and Treasury limits all share the ₹200 Cr WC umbrella cap. Reclassified to Bucket 0 (shared-cap sub-limits of LC umbrella). LC ₹200 alone represents the umbrella in Bucket 2.
A30: • | B30: SIB Capex LC ₹50 Cr shares ₹150 Cr cap with main LC per letter wording. Reclassified to Bucket 0. SIB LC ₹150 represents the umbrella in Bucket 2.
A31: • | B31: RBL SBLC for BC ₹190 (sub of TL) and RBL Capex LC ₹25 (sub of TL) are NFB sub-limits of an FB-Main parent. Sit in Bucket 0 for sub-limit deduplication purposes, but flagged via 'NFB Contingent Flag' column AG in Facility Master to surface in NFB Contingent KPI (₹815 = Bucket 2 ₹600 + these two ₹215).
A32: • | B32: Hedge notional limits (RBL LER ₹20 sub of LC, SIB Forward ₹3 standalone) excluded from all buckets. LER → Bucket 0 (Q1 hits before Q2 since LER is sub-of-LC). SIB Forward → no parent, but it's a derivative cap not credit. Tracked in Memo section of Lender Summary.
A34: 5. WORKBOOK ARCHITECTURE
A35: • | B35: Facility Master is the single source of truth. All other sheets aggregate via SUMIFS on FM columns.
A36: • | B36: Named ranges (Excel Name Manager): SanctionedDebt, NFBContingent, FDBackedTotal, FBMainsTotal, NFBMainsTotal, HedgeNotionalTotal — point to Lender Summary anchor cells. Use these in formulas instead of cell references for portability.
A37: • | B37: NFB Contingent computed via column AG flag in Facility Master (TRUE for facilities contributing to NFB Contingent KPI). Lender Summary aggregates via SUMIFS on this flag plus H=2.
A38: • | B38: Repayment Schedule consolidated columns S-V (Total Prin, Total Int, Total DS, Combined O/S) sum YBL + Bajaj only; RBL excluded. Dashboard's 'Term Loan Maturity Profile' reads from these consolidated columns and inherits the exclusion.
A39: • | B39: Validation Engine has 51 checks (VVE-01 through VVE-51). Master Status at row 69 shows ✓ PASS only when zero critical fails.

Sheet Dashboard
A1: JCL DEBT MONITORING DASHBOARD
A2: ="As of: " & TEXT(AsOfDate,"dd-mmm-yyyy") & " • Financial Basis: " & FinBasis & " • All figures in INR Crores" -> As of: 31-Mar-2026 • Financial Basis: Projected • All figures in INR Crores
A4: Sanctioned Debt (₹ Cr) | D4: FB Mains — Bucket 1 (₹ Cr) | G4: NFB Mains — Bucket 2 (₹ Cr) | J4: NFB Contingent (₹ Cr)
A5: =SanctionedDebt -> 1320.7 | D5: =FBMainsTotal -> 720.7 | G5: =NFBMainsTotal -> 600 | J5: =NFBContingent -> 815
A6: B1 + B2; main parents only | D6: TLs + ICICI CC (parent FB) | G6: Parent NFB at all 4 lenders | J6: B2 + NFB sub of FB-Main
A8: FD-Backed Lines (₹ Cr) | D8: Bucket 1 Outstanding (₹ Cr) | G8: Wt. Avg Cost of FB Economic Debt | J8: Annual Interest + Comm.
A9: =FDBackedTotal -> 100 | D9: =IFERROR(SUMIFS('Facility Master'!M:M,'Facility Master'!H:H,1),0) -> 495.9612 | G9: =WtAvgDebtCost -> 0.080780538 | J9: =TotalIntComm -> 49.039012
A10: Self-collateralised; excl. RBL ₹300 cap | D10: Drawn Bucket-1 (effective O/S) | G10: Bucket 1 (FB) cost basis only — interest accrues on FB | J10: Total run-rate (interest + commission)
A12: Active Facilities | D12: TL Earliest Maturity | G12: TL Farthest Maturity | J12: Avg Debt Utilisation
A13: =IFERROR(34-COUNTIF('Facility Master'!F:F,TRUE()),0) -> 10 | D13: =IFERROR(_xlfn.MINIFS('Facility Master'!Z:Z,'Facility Master'!D:D,"FB-Term",'Facility Master'!H:H,1),"") -> 47208 | G13: =IFERROR(_xlfn.MAXIFS('Facility Master'!Z:Z,'Facility Master'!D:D,"FB-Term",'Facility Master'!H:H,1),"") -> 49948 | J13: =IFERROR(SUMIFS('Facility Master'!M:M,'Facility Master'!H:H,1)/SUMIFS('Facility Master'!K:K,'Facility Master'!H:H,1),0) -> 0.68816595
A14: Excludes sub-limits | D14: First TL maturing | G14: Last TL maturing | J14: Eff. outstanding / sanctioned (Bucket 1)
A16: Covenant Compliance
A17: Total | B17: Compliant | C17: Near Breach | D17: Breached | E17: Pending | F17: Compliance %
A18: =CovenantCount -> 24 | B18: =CovenantCompliant -> 24 | C18: =CovenantNearBreach -> 0 | D18: =CovenantBreached -> 0 | E18: =CovenantPending -> 0 | F18: =PortfolioCompliancePct -> 1
A20: ="Portfolio Compliance: " & TEXT(PortfolioCompliancePct,"0.0%") & " (" & CovenantCompliant & " of " & CovenantCount & " covenants Compliant). " & CovenantNearBreach & " Near Breach. " & CovenantBreached & " Breached. " & CovenantPending & " Pending Input." -> Portfolio Compliance: 100.0% (24 of 24 covenants Compliant). 0 Near Breach. 0 Breached. 0 Pending Input.
A23: Lender Concentration — Sanctioned Debt
A24: Lender | B24: Sanctioned Debt (₹ Cr) | C24: % of Sanctioned Debt | L24: Relative Share ▶
A25: YES Bank | B25: ='Lender Summary'!D6 -> 520.7 | C25: =IFERROR(B25/SanctionedDebt,0) -> 0.39426062 | E25: =REPT("█", ROUND(C25*40,0)) -> ████████████████
A26: RBL Bank | B26: ='Lender Summary'!D5 -> 300 | C26: =IFERROR(B26/SanctionedDebt,0) -> 0.22715227 | E26: =REPT("█", ROUND(C26*40,0)) -> █████████
A27: ICICI Bank | B27: ='Lender Summary'!D8 -> 200 | C27: =IFERROR(B27/SanctionedDebt,0) -> 0.15143485 | E27: =REPT("█", ROUND(C27*40,0)) -> ██████
A28: Bajaj Finance | B28: ='Lender Summary'!D7 -> 150 | C28: =IFERROR(B28/SanctionedDebt,0) -> 0.11357613 | E28: =REPT("█", ROUND(C28*40,0)) -> █████
A29: South Indian Bank | B29: ='Lender Summary'!D9 -> 150 | C29: =IFERROR(B29/SanctionedDebt,0) -> 0.11357613 | E29: =REPT("█", ROUND(C29*40,0)) -> █████
A32: Term Loan Maturity Profile by Fiscal Year
A33: FY | B33: Period Start | C33: Period End | D33: Total Principal Due (₹ Cr) | E33: Cumulative | F33: Annual Bar ▶
A34: FY24 | B34: =DATE(2023,4,1) -> 45017 | C34: =DATE(2024,3,31) -> 45382 | D34: =IFERROR(SUMIFS('Repayment Schedule'!S:S,'Repayment Schedule'!B:B,">="&B34,'Repayment Schedule'!B:B,"<="&C34),0) -> 0 | E34: =D34 -> 0 | F34: =IFERROR(REPT("█",ROUND(D34/48.72*30,0)),"")
A35: FY25 | B35: =DATE(2024,4,1) -> 45383 | C35: =DATE(2025,3,31) -> 45747 | D35: =IFERROR(SUMIFS('Repayment Schedule'!S:S,'Repayment Schedule'!B:B,">="&B35,'Repayment Schedule'!B:B,"<="&C35),0) -> 0 | E35: =E34+D35 -> 0 | F35: =IFERROR(REPT("█",ROUND(D35/48.72*30,0)),"")
A36: FY26 | B36: =DATE(2025,4,1) -> 45748 | C36: =DATE(2026,3,31) -> 46112 | D36: =IFERROR(SUMIFS('Repayment Schedule'!S:S,'Repayment Schedule'!B:B,">="&B36,'Repayment Schedule'!B:B,"<="&C36),0) -> 24.7388 | E36: =E35+D36 -> 24.7388 | F36: =IFERROR(REPT("█",ROUND(D36/48.72*30,0)),"") -> ███████████████
A37: FY27 | B37: =DATE(2026,4,1) -> 46113 | C37: =DATE(2027,3,31) -> 46477 | D37: =IFERROR(SUMIFS('Repayment Schedule'!S:S,'Repayment Schedule'!B:B,">="&B37,'Repayment Schedule'!B:B,"<="&C37),0) -> 35.453086 | E37: =E36+D37 -> 60.191886 | F37: =IFERROR(REPT("█",ROUND(D37/48.72*30,0)),"") -> ██████████████████████
A38: FY28 | B38: =DATE(2027,4,1) -> 46478 | C38: =DATE(2028,3,31) -> 46843 | D38: =IFERROR(SUMIFS('Repayment Schedule'!S:S,'Repayment Schedule'!B:B,">="&B38,'Repayment Schedule'!B:B,"<="&C38),0) -> 46.167372 | E38: =E37+D38 -> 106.35926 | F38: =IFERROR(REPT("█",ROUND(D38/48.72*30,0)),"") -> ████████████████████████████
A39: FY29 | B39: =DATE(2028,4,1) -> 46844 | C39: =DATE(2029,3,31) -> 47208 | D39: =IFERROR(SUMIFS('Repayment Schedule'!S:S,'Repayment Schedule'!B:B,">="&B39,'Repayment Schedule'!B:B,"<="&C39),0) -> 46.427772 | E39: =E38+D39 -> 152.78703 | F39: =IFERROR(REPT("█",ROUND(D39/48.72*30,0)),"") -> █████████████████████████████
A40: FY30 | B40: =DATE(2029,4,1) -> 47209 | C40: =DATE(2030,3,31) -> 47573 | D40: =IFERROR(SUMIFS('Repayment Schedule'!S:S,'Repayment Schedule'!B:B,">="&B40,'Repayment Schedule'!B:B,"<="&C40),0) -> 47.956972 | E40: =E39+D40 -> 200.744 | F40: =IFERROR(REPT("█",ROUND(D40/48.72*30,0)),"") -> ██████████████████████████████
A41: FY31 | B41: =DATE(2030,4,1) -> 47574 | C41: =DATE(2031,3,31) -> 47938 | D41: =IFERROR(SUMIFS('Repayment Schedule'!S:S,'Repayment Schedule'!B:B,">="&B41,'Repayment Schedule'!B:B,"<="&C41),0) -> 50.317372 | E41: =E40+D41 -> 251.06137 | F41: =IFERROR(REPT("█",ROUND(D41/48.72*30,0)),"") -> ███████████████████████████████
A42: FY32 | B42: =DATE(2031,4,1) -> 47939 | C42: =DATE(2032,3,31) -> 48304 | D42: =IFERROR(SUMIFS('Repayment Schedule'!S:S,'Repayment Schedule'!B:B,">="&B42,'Repayment Schedule'!B:B,"<="&C42),0) -> 52.400572 | E42: =E41+D42 -> 303.46194 | F42: =IFERROR(REPT("█",ROUND(D42/48.72*30,0)),"") -> ████████████████████████████████
A43: FY33 | B43: =DATE(2032,4,1) -> 48305 | C43: =DATE(2033,3,31) -> 48669 | D43: =IFERROR(SUMIFS('Repayment Schedule'!S:S,'Repayment Schedule'!B:B,">="&B43,'Repayment Schedule'!B:B,"<="&C43),0) -> 52.400572 | E43: =E42+D43 -> 355.86252 | F43: =IFERROR(REPT("█",ROUND(D43/48.72*30,0)),"") -> ████████████████████████████████
A44: FY34 | B44: =DATE(2033,4,1) -> 48670 | C44: =DATE(2034,3,31) -> 49034 | D44: =IFERROR(SUMIFS('Repayment Schedule'!S:S,'Repayment Schedule'!B:B,">="&B44,'Repayment Schedule'!B:B,"<="&C44),0) -> 41.686285 | E44: =E43+D44 -> 397.5488 | F44: =IFERROR(REPT("█",ROUND(D44/48.72*30,0)),"") -> ██████████████████████████
A45: FY35 | B45: =DATE(2034,4,1) -> 49035 | C45: =DATE(2035,3,31) -> 49399 | D45: =IFERROR(SUMIFS('Repayment Schedule'!S:S,'Repayment Schedule'!B:B,">="&B45,'Repayment Schedule'!B:B,"<="&C45),0) -> 32.2228 | E45: =E44+D45 -> 429.7716 | F45: =IFERROR(REPT("█",ROUND(D45/48.72*30,0)),"") -> ████████████████████
A46: FY36 | B46: =DATE(2035,4,1) -> 49400 | C46: =DATE(2036,3,31) -> 49765 | D46: =IFERROR(SUMIFS('Repayment Schedule'!S:S,'Repayment Schedule'!B:B,">="&B46,'Repayment Schedule'!B:B,"<="&C46),0) -> 36.112 | E46: =E45+D46 -> 465.8836 | F46: =IFERROR(REPT("█",ROUND(D46/48.72*30,0)),"") -> ██████████████████████
A47: FY37 | B47: =DATE(2036,4,1) -> 49766 | C47: =DATE(2037,3,31) -> 50130 | D47: =IFERROR(SUMIFS('Repayment Schedule'!S:S,'Repayment Schedule'!B:B,">="&B47,'Repayment Schedule'!B:B,"<="&C47),0) -> 4.8164 | E47: =E46+D47 -> 470.7 | F47: =IFERROR(REPT("█",ROUND(D47/48.72*30,0)),"") -> ███
A50: Facility Type Mix
A51: Bucket | B51: Amount (₹ Cr) | C51: % of Sanctioned | D51: Visual
A52: Sanctioned Debt (B1+B2) | B52: =SanctionedDebt -> 1320.7 | C52: =IFERROR(B52/SanctionedDebt,"") -> 1 | D52: =IFERROR(REPT("█",ROUND(B52/SanctionedDebt*40,0)),"") -> ████████████████████████████████████████
A53: NFB Contingent | B53: =NFBContingent -> 815 | C53: =IFERROR(B53/SanctionedDebt,"") -> 0.61709699 | D53: =IFERROR(REPT("█",ROUND(B53/SanctionedDebt*40,0)),"") -> █████████████████████████
A54: FD-Backed (Separate Lines) | B54: =FDBackedTotal -> 100 | C54: =IFERROR(B54/SanctionedDebt,"") -> 0.075717423 | D54: =IFERROR(REPT("█",ROUND(B54/SanctionedDebt*40,0)),"") -> ███
A55: Memo: Hedge Notional | B55: =HedgeNotionalTotal -> 23 | C55: =IFERROR(B55/SanctionedDebt,"") -> 0.017415007 | D55: =IFERROR(REPT("█",ROUND(B55/SanctionedDebt*40,0)),"") -> █
A57: Key Findings & Watch Items
A58: • | B58: Sanctioned Debt of ₹1,320.7 Cr = sum of FB & NFB main parent facilities at sanction-letter caps. Industry-standard credit-relationship view.
A59: • | B59: NFB Contingent of ₹815.0 Cr = NFB Main parents (₹600) + NFB sub-limits of FB-Main parents (₹190 RBL SBLC for BC + ₹25 RBL Capex LC). Off-balance-sheet face value.
A60: • | B60: FD-Backed Separate Line: RBL FDOD ₹100 Cr only — self-collateralised, excluded from RBL's ₹300 Cr Overall Borrower exposure cap.
A61: • | B61: Lender concentration: YBL 39.4% + RBL 22.7% = 62.1% of Sanctioned Debt. ICICI/Bajaj/SIB each 11-15%.
A62: • | B62: RBL Term Loan ₹200 Cr Main: drawdown pending; existing BC instruments converting to TL by Dec-2026 per 31-Dec-2025 letter. Repayment schedule excluded until drawdown completes.
A63: • | B63: All 24 covenants Compliant at FY26E base case. Tightest is TOL/TNW with ample headroom.
A65: Model Integrity
B66: Bucket totals reconcile | D66: TL schedules tie out | F66: Covenants populated | H66: Inputs set | J66: Facilities bucketed
B67: =IFERROR(IF(COUNTIFS('Validation Engine'!G13:G63,"Bucket",'Validation Engine'!E13:E63,"FAIL")=0,IF(COUNTIFS('Validation Engine'!G13:G63,"Bucket")>0,"✓","—"),"—"),"—") -> ✓ | D67: =IFERROR(IF(COUNTIFS('Validation Engine'!G13:G63,"TL",'Validation Engine'!E13:E63,"FAIL")=0,IF(COUNTIFS('Validation Engine'!G13:G63,"TL")>0,"✓","—"),"—"),"—") -> ✓ | F67: =IFERROR(IF(COUNTIFS('Validation Engine'!G13:G63,"Cov",'Validation Engine'!E13:E63,"FAIL")=0,IF(COUNTIFS('Validation Engine'!G13:G63,"Cov")>0,"✓","—"),"—"),"—") -> ✓ | H67: =IFERROR(IF(COUNTIFS('Validation Engine'!G13:G63,"Inputs",'Validation Engine'!E13:E63,"FAIL")=0,IF(COUNTIFS('Validation Engine'!G13:G63,"Inputs")>0,"✓","—"),"—"),"—") -> ✓ | J67: =IFERROR(IF(COUNTIFS('Validation Engine'!G13:G63,"FM",'Validation Engine'!E13:E63,"FAIL")=0,IF(COUNTIFS('Validation Engine'!G13:G63,"FM")>0,"✓","—"),"—"),"—") -> ✓
A69: Prepared by Divyanshu Vatsa · Treasury · Methodology: Path B (Optimized) — Sanctioned Debt = sum of all FB & NFB main parents; sub-limits → Bucket 0; FD-backed segregated; hedge notional in memo. See Notes tab for full bucket logic.

Sheet Instructions & Assumptions
A1: INSTRUCTIONS & ASSUMPTIONS
A3: A. Core Model Parameters | B3: Value | C3: Unit | D3: Notes
A4: As-of Date | B4: =DATE(2026,3,31) -> 46112 | C4: date | D4: Drives remaining-tenor and covenant-period calculations.
A5: USD / INR FX Rate | B5: 92.98 | C5: ₹/USD | D5: Drives INR equivalents of USD-denominated facilities subject to sanction-letter caps.
A6: Use Full Utilisation = Sanctioned? | B6: =TRUE() -> TRUE | C6: TRUE/FALSE | D6: If TRUE, Effective Outstanding = Sanctioned. If FALSE, uses Current Outstanding from Facility Master Col N.
A7: Days in Year | B7: 365 | C7: days | D7: Day-count convention for interest computation.
A8: Financial Basis (Actual / Projected) | B8: Projected | C8: Basis | D8: Toggle drives Section C 'Active' column which feeds the Covenant Tracker.
A11: B. Benchmark Rates | B11: Current Rate | D11: Source / Notes
A12: 1Y MCLR (RBL Bank) | B12: 0.09 | D12: RBL Bank 1Y MCLR (Apr-2026).
A13: 3M MCLR (YBL) | B13: 0.09 | D13: YES Bank 3M MCLR (Apr-2026).
A14: 6M I-MCLR (ICICI) | B14: 0.083 | D14: ICICI 6M I-MCLR effective 22-Jan-2026.
A15: 12M MCLR (SIB) | B15: 0.0975 | D15: SIB 12M MCLR per sanction letter dated 21-Jun-2025.
A16: Bajaj Floating Reference Rate (BFRR) | B16: 0.085 | D16: Per Bajaj sanction letter dated 18-Aug-2025.
A17: Term SOFR (USD) 3M | B17: 0.043 | D17: Term SOFR 3M, Apr-2026.
A18: 3M T-Bill | B18: 0.0518 | D18: India 3M T-Bill yield, Apr-2026.
A19: Repo Rate | B19: 0.0525 | D19: RBI Policy Repo Rate, Apr-2026.
A20: FD rate (RBL FDOD) | B20: 0.07 | D20: Customer-specific FD rate backing the RBL FDOD facility.
A22: C. Management Financials (INR Cr) | B22: Active (toggle) | C22: FY24A | D22: FY26E
A24: EBITDA | B24: {=IFERROR(IF(FinBasis="Actual",C24,D24),0)} -> 383.96 | C24: 173.37 | D24: 383.96
A25: Total Debt (Gross) | B25: {=IFERROR(IF(FinBasis="Actual",C25,D25),0)} -> 613.03 | C25: 471.82 | D25: 613.03
A26: Term Debt | B26: {=IFERROR(IF(FinBasis="Actual",C26,D26),0)} -> 431.28 | C26: 324.01 | D26: 431.28
A27: Tangible Net Worth (TNW) | B27: {=IFERROR(IF(FinBasis="Actual",C27,D27),0)} -> 740.13 | C27: 720.11 | D27: 740.13
A28: Adjusted TNW (ATNW) | B28: {=IFERROR(IF(FinBasis="Actual",C28,D28),0)} -> 720.76 | C28: 588.29 | D28: 720.76
A29: Current Assets | B29: {=IFERROR(IF(FinBasis="Actual",C29,D29),0)} -> 755.02 | C29: 711.3 | D29: 755.02
A30: Current Liabilities | B30: {=IFERROR(IF(FinBasis="Actual",C30,D30),0)} -> 544.79 | C30: 513.82 | D30: 544.79
A31: Total Outside Liabilities (TOL) | B31: {=IFERROR(IF(FinBasis="Actual",C31,D31),0)} -> 1143.49 | C31: 1143.77 | D31: 1143.49
A32: Interest Expense (TTM) | B32: {=IFERROR(IF(FinBasis="Actual",C32,D32),0)} -> 49.08 | C32: 39.87 | D32: 49.08
A33: Fixed Assets (net block) | B33: {=IFERROR(IF(FinBasis="Actual",C33,D33),0)} -> 937.69 | C33: 449.34 | D33: 937.69
A34: Secured Debt (outstanding) | B34: {=IFERROR(IF(FinBasis="Actual",C34,D34),0)} -> 431.28 | C34: 324.01 | D34: 431.28
A35: External Rating | B35: {=IFERROR(IF(FinBasis="Actual",C35,D35),0)} -> CARE A+; Stable / A1 | C35: CARE A+; Stable / A1 | D35: CARE A+; Stable / A1
A36: Promoter Shareholding % | B36: {=IFERROR(IF(FinBasis="Actual",C36,D36),0)} -> 1 | C36: 1 | D36: 1
A37: Principal Repayment (TTM) | B37: {=IFERROR(IF(FinBasis="Actual",C37,D37),0)} -> 170.07 | C37: 18.76 | D37: 170.07
A38: Tax Paid (TTM) | B38: {=IFERROR(IF(FinBasis="Actual",C38,D38),0)} -> 69.36 | C38: 0 | D38: 69.36
A39: Scheduled TL Repayment (next 12M) | B39: {=IFERROR(IF(FinBasis="Actual",C39,D39),0)} -> 41.09 | C39: 0 | D39: 41.09
A41: D. Sanction-Letter Binding Caps (INR Cr) | B41: Value
A42: RBL — INR WC Umbrella Cap | B42: 100
A43: RBL — GIFT City BC Working Capital Cap | B43: 100
A44: RBL — GIFT City BC CAPEX Cap | B44: 172
A45: ICICI — Fund-Based Cap | B45: 50
A46: SIB — CCOL Cap | B46: 50
A48: E. Term Loan Date Overrides | B48: Date
A49: RBL TL Maturity | B49: =DATE(2029,3,31) -> 47208
A50: YBL TL Repayment Start | B50: =DATE(2025,6,30) -> 45838
A51: YBL TL Maturity | B51: =DATE(2036,9,30) -> 49948
A52: Bajaj TL Maturity | B52: =DATE(2033,8,25) -> 48816
A54: F. Term Loan S.No References | B54: S.No
A55: RBL TL S.No | B55: 9
A56: YBL TL S.No | B56: 21
A57: Bajaj TL S.No | B57: 22
A59: G. Rating-Tier Ordinal Map (higher = better)
A60: Rating Token | B60: Ordinal | C60: Notes
A61: AAA | B61: 21 | C61: Investment grade — highest
A62: AA+ | B62: 20
A63: AA | B63: 19
A64: AA- | B64: 18
A65: A+ | B65: 17 | C65: JCL current rating: CARE A+
A66: A | B66: 16
A67: A- | B67: 15 | C67: Common minimum rating covenant
A68: BBB+ | B68: 14 | C68: RBL TL minimum
A69: BBB | B69: 13
A70: BBB- | B70: 12
A71: BB+ | B71: 11 | C71: Below investment grade
A72: BB or below | B72: 10

Sheet Facility Master
A1: FACILITY MASTER
A3: Identification | G3: Flags | I3: Financial Structure | P3: Pricing | U3: Repayment | Y3: Dates | AE3: Reference & Notes
A4: S.No | B4: Lender | C4: Facility | D4: Category | E4: Nature | F4: Sub-Limit Flag | G4: FD-Backed | H4: Bucket | I4: Currency | J4: Sanc Orig Ccy | K4: Sanc INR Cr | L4: Current O/S | M4: Eff Current O/S | N4: Util % | O4: Headroom | P4: Benchmark | Q4: Spread | R4: Eff Rate p.a. | S4: Rate Type | T4: Moratorium Mths | U4: Rep Frequency | V4: Tenor Mths | W4: No of Instalments | X4: Drawdown Date | Y4: Rep Start Date | Z4: Maturity Date | AA4: Sanction Date | AB4: Validity Date | AC4: Purpose | AD4: Security Summary | AE4: Sanction Reference | AF4: Remarks | AG4: NFB Contingent Flag
A5: 1 | B5: RBL Bank | C5: Letter of Credit - Main Limit | D5: NFB | E5: Revolving | F5: =FALSE() -> FALSE | G5: =FALSE() -> FALSE | H5: 2 | I5: INR | J5: 100 | K5: =IFERROR(J5,0) -> 100 | M5: =IFERROR(IF(D5="FB-Term",IF(A5=RBL_TL_SNo,RBL_TL_PrincOS,IF(A5=YBL_TL_SNo,YBL_TL_PrincOS,IF(A5=Bajaj_TL_SNo,Bajaj_TL_PrincOS,0))),IF(L5<>"",L5,IF(UseFullUtil,K5,0))),0) -> 100 | N5: =IFERROR(M5/K5,0) -> 1 | O5: =IFERROR(K5-M5,0) -> 0 | P5: Fixed commission | Q5: 0 | R5: {=IFERROR(_xlfn.SWITCH(P5,"1Y MCLR (RBL Bank)",MCLR_RBL_1Y+Q5,"3M MCLR (YBL)",MCLR_YBL_3M+Q5,"6M I-MCLR (ICICI)",IMCLR_ICICI_6M+Q5,"12M MCLR (SIB)",MCLR_SIB_12M+Q5,"Bajaj Floating Reference Rate (BFRR)",BFRR_Bajaj+Q5,"Term SOFR (USD)",SOFR_3M+Q5,"3M T-Bill",TBill_3M+Q5,"Repo Rate",RepoRate+Q5,"FD rate",IFERROR(FD_Rate_RBL,0)+Q5,Q5),0)} -> 0 | S5: Fixed | T5: 0 | U5: On Maturity | V5: 6 | W5: 0 | X5: 46022 | Y5: =IFERROR(EDATE(X5,T5),"") -> 46022 | Z5: =IFERROR(EDATE(X5,V5),"") -> 46203 | AA5: 46022 | AB5: 46356 | AC5: Working capital incl. service LC issuance | AD5: 1st p-p on current assets; 2nd p-p on FA; Personal guarantee | AE5: RBL Renewal Letter dated 31-Dec-2025 | AF5: Pricing 0.45% effective 31-Dec-2025. | AG5: =TRUE() -> TRUE
A6: 2 | B6: RBL Bank | C6: Bank Guarantee | D6: NFB | E6: Revolving | F6: =TRUE() -> TRUE | G6: =FALSE() -> FALSE | H6: 0 | I6: INR | J6: 25 | K6: =IFERROR(J6,0) -> 25 | M6: =IFERROR(IF(D6="FB-Term",IF(A6=RBL_TL_SNo,RBL_TL_PrincOS,IF(A6=YBL_TL_SNo,YBL_TL_PrincOS,IF(A6=Bajaj_TL_SNo,Bajaj_TL_PrincOS,0))),IF(L6<>"",L6,IF(UseFullUtil,K6,0))),0) -> 25 | N6: =IFERROR(M6/K6,0) -> 1 | O6: =IFERROR(K6-M6,0) -> 0 | P6: Fixed commission | Q6: 0 | R6: {=IFERROR(_xlfn.SWITCH(P6,"1Y MCLR (RBL Bank)",MCLR_RBL_1Y+Q6,"3M MCLR (YBL)",MCLR_YBL_3M+Q6,"6M I-MCLR (ICICI)",IMCLR_ICICI_6M+Q6,"12M MCLR (SIB)",MCLR_SIB_12M+Q6,"Bajaj Floating Reference Rate (BFRR)",BFRR_Bajaj+Q6,"Term SOFR (USD)",SOFR_3M+Q6,"3M T-Bill",TBill_3M+Q6,"Repo Rate",RepoRate+Q6,"FD rate",IFERROR(FD_Rate_RBL,0)+Q6,Q6),0)} -> 0 | S6: Fixed | T6: 0 | U6: On Demand | V6: 12 | W6: 0 | X6: 46022 | Y6: =IFERROR(EDATE(X6,T6),"") -> 46022 | Z6: =IFERROR(EDATE(X6,V6),"") -> 46387 | AA6: 46022 | AB6: 46356 | AC6: PBG, Bid Bond, Govt/Semi-Govt guarantees | AD6: 1st p-p on current assets; 2nd p-p on FA; Personal guarantee | AE6: RBL Renewal Letter dated 31-Dec-2025 | AF6: BG commission 0.50% per 28-Feb-2025 pricing table. | AG6: =FALSE() -> FALSE
A7: 3 | B7: RBL Bank | C7: Invoice Discounting (PID) | D7: FB | E7: Revolving | F7: =TRUE() -> TRUE | G7: =FALSE() -> FALSE | H7: 0 | I7: INR | J7: 100 | K7: =IFERROR(J7,0) -> 100 | M7: =IFERROR(IF(D7="FB-Term",IF(A7=RBL_TL_SNo,RBL_TL_PrincOS,IF(A7=YBL_TL_SNo,YBL_TL_PrincOS,IF(A7=Bajaj_TL_SNo,Bajaj_TL_PrincOS,0))),IF(L7<>"",L7,IF(UseFullUtil,K7,0))),0) -> 100 | N7: =IFERROR(M7/K7,0) -> 1 | O7: =IFERROR(K7-M7,0) -> 0 | P7: 1Y MCLR (RBL Bank) | Q7: 0.005 | R7: {=IFERROR(_xlfn.SWITCH(P7,"1Y MCLR (RBL Bank)",MCLR_RBL_1Y+Q7,"3M MCLR (YBL)",MCLR_YBL_3M+Q7,"6M I-MCLR (ICICI)",IMCLR_ICICI_6M+Q7,"12M MCLR (SIB)",MCLR_SIB_12M+Q7,"Bajaj Floating Reference Rate (BFRR)",BFRR_Bajaj+Q7,"Term SOFR (USD)",SOFR_3M+Q7,"3M T-Bill",TBill_3M+Q7,"Repo Rate",RepoRate+Q7,"FD rate",IFERROR(FD_Rate_RBL,0)+Q7,Q7),0)} -> 0.095 | S7: Floating (Indicative) | T7: 0 | U7: On Maturity | V7: 1 | W7: 0 | X7: 46022 | Y7: =IFERROR(EDATE(X7,T7),"") -> 46022 | Z7: =IFERROR(EDATE(X7,V7),"") -> 46053 | AA7: 46022 | AB7: 46356 | AC7: Working capital | AD7: 1st p-p on current assets; 2nd p-p on FA; Personal guarantee | AE7: RBL Renewal Letter dated 31-Dec-2025 | AF7: Rate set at availment. Spread of 50 bps over 1Y MCLR is illustrative; rate confirmed at each availment per sanction letter. | AG7: =FALSE() -> FALSE
A8: 4 | B8: RBL Bank | C8: SBLC | D8: NFB | E8: Revolving | F8: =TRUE() -> TRUE | G8: =FALSE() -> FALSE | H8: 0 | I8: INR | J8: 100 | K8: =IFERROR(J8,0) -> 100 | M8: =IFERROR(IF(D8="FB-Term",IF(A8=RBL_TL_SNo,RBL_TL_PrincOS,IF(A8=YBL_TL_SNo,YBL_TL_PrincOS,IF(A8=Bajaj_TL_SNo,Bajaj_TL_PrincOS,0))),IF(L8<>"",L8,IF(UseFullUtil,K8,0))),0) -> 100 | N8: =IFERROR(M8/K8,0) -> 1 | O8: =IFERROR(K8-M8,0) -> 0 | P8: To be decided | Q8: 0.005 | R8: {=IFERROR(_xlfn.SWITCH(P8,"1Y MCLR (RBL Bank)",MCLR_RBL_1Y+Q8,"3M MCLR (YBL)",MCLR_YBL_3M+Q8,"6M I-MCLR (ICICI)",IMCLR_ICICI_6M+Q8,"12M MCLR (SIB)",MCLR_SIB_12M+Q8,"Bajaj Floating Reference Rate (BFRR)",BFRR_Bajaj+Q8,"Term SOFR (USD)",SOFR_3M+Q8,"3M T-Bill",TBill_3M+Q8,"Repo Rate",RepoRate+Q8,"FD rate",IFERROR(FD_Rate_RBL,0)+Q8,Q8),0)} -> 0.005 | S8: TBD | T8: 0 | U8: On Maturity | V8: 6 | W8: 0 | X8: 45729 | Y8: =IFERROR(EDATE(X8,T8),"") -> 45729 | Z8: =IFERROR(EDATE(X8,V8),"") -> 45913 | AA8: 45729 | AB8: 46356 | AC8: Buyer's Credit from RBL GIFT City / other banks | AD8: Same as LC | AE8: RBL Modification Letter dated 13-Mar-2025 | AF8: Sub-limit of LC (Main). | AG8: =FALSE() -> FALSE
A9: 5 | B9: RBL Bank | C9: Pre-Acceptance LCBD | D9: FB | E9: Revolving | F9: =TRUE() -> TRUE | G9: =FALSE() -> FALSE | H9: 0 | I9: INR | J9: 100 | K9: =IFERROR(J9,0) -> 100 | M9: =IFERROR(IF(D9="FB-Term",IF(A9=RBL_TL_SNo,RBL_TL_PrincOS,IF(A9=YBL_TL_SNo,YBL_TL_PrincOS,IF(A9=Bajaj_TL_SNo,Bajaj_TL_PrincOS,0))),IF(L9<>"",L9,IF(UseFullUtil,K9,0))),0) -> 100 | N9: =IFERROR(M9/K9,0) -> 1 | O9: =IFERROR(K9-M9,0) -> 0 | P9: 1Y MCLR (RBL Bank) | Q9: 0.0075 | R9: {=IFERROR(_xlfn.SWITCH(P9,"1Y MCLR (RBL Bank)",MCLR_RBL_1Y+Q9,"3M MCLR (YBL)",MCLR_YBL_3M+Q9,"6M I-MCLR (ICICI)",IMCLR_ICICI_6M+Q9,"12M MCLR (SIB)",MCLR_SIB_12M+Q9,"Bajaj Floating Reference Rate (BFRR)",BFRR_Bajaj+Q9,"Term SOFR (USD)",SOFR_3M+Q9,"3M T-Bill",TBill_3M+Q9,"Repo Rate",RepoRate+Q9,"FD rate",IFERROR(FD_Rate_RBL,0)+Q9,Q9),0)} -> 0.0975 | S9: Floating (Indicative) | T9: 0 | U9: On Maturity | V9: 0 | W9: 0 | X9: 46022 | Y9: =IFERROR(EDATE(X9,T9),"") -> 46022 | Z9: =IFERROR(EDATE(X9,V9),"") -> 46022 | AA9: 46022 | AB9: 46356 | AC9: Working capital | AD9: 1st p-p on current assets; 2nd p-p on FA; Personal guarantee | AE9: RBL Renewal Letter dated 31-Dec-2025 | AF9: Rate set at availment. Spread of 75 bps over 1Y MCLR is illustrative; rate confirmed at each availment per sanction letter. | AG9: =FALSE() -> FALSE
A10: 6 | B10: RBL Bank | C10: Cash Credit | D10: FB | E10: Revolving | F10: =TRUE() -> TRUE | G10: =FALSE() -> FALSE | H10: 0 | I10: INR | J10: 100 | K10: =IFERROR(J10,0) -> 100 | M10: =IFERROR(IF(D10="FB-Term",IF(A10=RBL_TL_SNo,RBL_TL_PrincOS,IF(A10=YBL_TL_SNo,YBL_TL_PrincOS,IF(A10=Bajaj_TL_SNo,Bajaj_TL_PrincOS,0))),IF(L10<>"",L10,IF(UseFullUtil,K10,0))),0) -> 100 | N10: =IFERROR(M10/K10,0) -> 1 | O10: =IFERROR(K10-M10,0) -> 0 | P10: 1Y MCLR (RBL Bank) | Q10: 0.0005 | R10: {=IFERROR(_xlfn.SWITCH(P10,"1Y MCLR (RBL Bank)",MCLR_RBL_1Y+Q10,"3M MCLR (YBL)",MCLR_YBL_3M+Q10,"6M I-MCLR (ICICI)",IMCLR_ICICI_6M+Q10,"12M MCLR (SIB)",MCLR_SIB_12M+Q10,"Bajaj Floating Reference Rate (BFRR)",BFRR_Bajaj+Q10,"Term SOFR (USD)",SOFR_3M+Q10,"3M T-Bill",TBill_3M+Q10,"Repo Rate",RepoRate+Q10,"FD rate",IFERROR(FD_Rate_RBL,0)+Q10,Q10),0)} -> 0.0905 | S10: Floating | T10: 0 | U10: On Demand | V10: 0 | W10: 0 | X10: 45716 | Y10: =IFERROR(EDATE(X10,T10),"") -> 45716 | Z10: =IFERROR(EDATE(X10,V10),"") -> 45716 | AA10: 45716 | AB10: 46356 | AC10: Working capital | AD10: 1st p-p on current assets; 2nd p-p on FA; Personal guarantee | AE10: RBL Renewal cum Modification dated 28-Feb-2025 | AF10: 1Y MCLR + 5 bps. | AG10: =FALSE() -> FALSE
A11: 7 | B11: RBL Bank | C11: Working Capital Demand Loan (WCDL) | D11: FB | E11: Revolving | F11: =TRUE() -> TRUE | G11: =FALSE() -> FALSE | H11: 0 | I11: INR | J11: 100 | K11: =IFERROR(J11,0) -> 100 | M11: =IFERROR(IF(D11="FB-Term",IF(A11=RBL_TL_SNo,RBL_TL_PrincOS,IF(A11=YBL_TL_SNo,YBL_TL_PrincOS,IF(A11=Bajaj_TL_SNo,Bajaj_TL_PrincOS,0))),IF(L11<>"",L11,IF(UseFullUtil,K11,0))),0) -> 100 | N11: =IFERROR(M11/K11,0) -> 1 | O11: =IFERROR(K11-M11,0) -> 0 | P11: To be decided | Q11: 0 | R11: {=IFERROR(_xlfn.SWITCH(P11,"1Y MCLR (RBL Bank)",MCLR_RBL_1Y+Q11,"3M MCLR (YBL)",MCLR_YBL_3M+Q11,"6M I-MCLR (ICICI)",IMCLR_ICICI_6M+Q11,"12M MCLR (SIB)",MCLR_SIB_12M+Q11,"Bajaj Floating Reference Rate (BFRR)",BFRR_Bajaj+Q11,"Term SOFR (USD)",SOFR_3M+Q11,"3M T-Bill",TBill_3M+Q11,"Repo Rate",RepoRate+Q11,"FD rate",IFERROR(FD_Rate_RBL,0)+Q11,Q11),0)} -> 0 | S11: TBD | T11: 0 | U11: On Demand | V11: 4 | W11: 0 | X11: 46022 | Y11: =IFERROR(EDATE(X11,T11),"") -> 46022 | Z11: =IFERROR(EDATE(X11,V11),"") -> 46142 | AA11: 46022 | AB11: 46356 | AC11: Working capital | AD11: 1st p-p on current assets; 2nd p-p on FA; Personal guarantee | AE11: RBL Renewal Letter dated 31-Dec-2025 | AF11: Rate set at drawdown. | AG11: =FALSE() -> FALSE
A12: 8 | B12: RBL Bank | C12: Loan Equivalent Risk (LER) | D12: Hedge | E12: Revolving | F12: =TRUE() -> TRUE | G12: =FALSE() -> FALSE | H12: 0 | I12: INR | J12: 20 | K12: =IFERROR(J12,0) -> 20 | M12: =IFERROR(IF(D12="FB-Term",IF(A12=RBL_TL_SNo,RBL_TL_PrincOS,IF(A12=YBL_TL_SNo,YBL_TL_PrincOS,IF(A12=Bajaj_TL_SNo,Bajaj_TL_PrincOS,0))),IF(L12<>"",L12,IF(UseFullUtil,K12,0))),0) -> 20 | N12: =IFERROR(M12/K12,0) -> 1 | O12: =IFERROR(K12-M12,0) -> 0 | P12: Bank treasury | Q12: 0 | R12: {=IFERROR(_xlfn.SWITCH(P12,"1Y MCLR (RBL Bank)",MCLR_RBL_1Y+Q12,"3M MCLR (YBL)",MCLR_YBL_3M+Q12,"6M I-MCLR (ICICI)",IMCLR_ICICI_6M+Q12,"12M MCLR (SIB)",MCLR_SIB_12M+Q12,"Bajaj Floating Reference Rate (BFRR)",BFRR_Bajaj+Q12,"Term SOFR (USD)",SOFR_3M+Q12,"3M T-Bill",TBill_3M+Q12,"Repo Rate",RepoRate+Q12,"FD rate",IFERROR(FD_Rate_RBL,0)+Q12,Q12),0)} -> 0 | S12: Fixed | T12: 0 | U12: On Settlement | V12: 12 | W12: 0 | X12: 46022 | Y12: =IFERROR(EDATE(X12,T12),"") -> 46022 | Z12: =IFERROR(EDATE(X12,V12),"") -> 46387 | AA12: 46022 | AB12: 46356 | AC12: Forex hedging (MTM cap 75%) | AD12: Unsecured | AE12: RBL Renewal Letter dated 31-Dec-2025 | AF12: Notional limit; 75% MTM trigger. | AG12: =FALSE() -> FALSE
A13: 9 | B13: RBL Bank | C13: Term Loan | D13: FB-Term | E13: Non-Revolving | F13: =FALSE() -> FALSE | G13: =FALSE() -> FALSE | H13: 1 | I13: INR | J13: 200 | K13: =IFERROR(J13,0) -> 200 | M13: =IFERROR(IF(D13="FB-Term",IF(A13=RBL_TL_SNo,RBL_TL_PrincOS,IF(A13=YBL_TL_SNo,YBL_TL_PrincOS,IF(A13=Bajaj_TL_SNo,Bajaj_TL_PrincOS,0))),IF(L13<>"",L13,IF(UseFullUtil,K13,0))),0) -> 0 | N13: =IFERROR(M13/K13,0) -> 0 | O13: =IFERROR(K13-M13,0) -> 200 | P13: 1Y MCLR (RBL Bank) | Q13: 0.0075 | R13: {=IFERROR(_xlfn.SWITCH(P13,"1Y MCLR (RBL Bank)",MCLR_RBL_1Y+Q13,"3M MCLR (YBL)",MCLR_YBL_3M+Q13,"6M I-MCLR (ICICI)",IMCLR_ICICI_6M+Q13,"12M MCLR (SIB)",MCLR_SIB_12M+Q13,"Bajaj Floating Reference Rate (BFRR)",BFRR_Bajaj+Q13,"Term SOFR (USD)",SOFR_3M+Q13,"3M T-Bill",TBill_3M+Q13,"Repo Rate",RepoRate+Q13,"FD rate",IFERROR(FD_Rate_RBL,0)+Q13,Q13),0)} -> 0.0975 | S13: Floating (Indicative) | T13: 24 | U13: Quarterly | V13: 60 | W13: 12 | X13: 45315 | Y13: =IFERROR(EDATE(X13,T13),"") -> 46046 | Z13: =RBL_TL_Maturity -> 47208 | AA13: 45315 | AB13: 46387 | AC13: Repayment of existing SBLC/BC + fresh capex | AD13: 1st p-p on FA; 1st p-p mortgage on immovable; 2nd p-p on CA | AE13: RBL TL Sanction | AF13: Indicative 9.75% (1Y MCLR + 75 bps); confirm with RBL at drawdown. | AG13: =FALSE() -> FALSE
A14: 10 | B14: RBL Bank | C14: SBLC for Buyer's Credit (GIFT City) | D14: NFB | E14: Revolving | F14: =TRUE() -> TRUE | G14: =FALSE() -> FALSE | H14: 0 | I14: INR | J14: 190 | K14: =IFERROR(J14,0) -> 190 | M14: =IFERROR(IF(D14="FB-Term",IF(A14=RBL_TL_SNo,RBL_TL_PrincOS,IF(A14=YBL_TL_SNo,YBL_TL_PrincOS,IF(A14=Bajaj_TL_SNo,Bajaj_TL_PrincOS,0))),IF(L14<>"",L14,IF(UseFullUtil,K14,0))),0) -> 190 | N14: =IFERROR(M14/K14,0) -> 1 | O14: =IFERROR(K14-M14,0) -> 0 | P14: Fixed commission | Q14: 0.005 | R14: {=IFERROR(_xlfn.SWITCH(P14,"1Y MCLR (RBL Bank)",MCLR_RBL_1Y+Q14,"3M MCLR (YBL)",MCLR_YBL_3M+Q14,"6M I-MCLR (ICICI)",IMCLR_ICICI_6M+Q14,"12M MCLR (SIB)",MCLR_SIB_12M+Q14,"Bajaj Floating Reference Rate (BFRR)",BFRR_Bajaj+Q14,"Term SOFR (USD)",SOFR_3M+Q14,"3M T-Bill",TBill_3M+Q14,"Repo Rate",RepoRate+Q14,"FD rate",IFERROR(FD_Rate_RBL,0)+Q14,Q14),0)} -> 0.005 | S14: Fixed | T14: 0 | U14: On Maturity | V14: 36 | W14: 0 | X14: 46022 | Y14: =IFERROR(EDATE(X14,T14),"") -> 46022 | Z14: =IFERROR(EDATE(X14,V14),"") -> 47118 | AA14: 46022 | AB14: 46356 | AC14: Buyer's credit through RBL GIFT City or other banks | AD14: 1st p-p on FA; 1st p-p mortgage on immovable; 2nd p-p on CA | AE14: RBL Renewal Letter dated 31-Dec-2025 | AF14: Limit increased 172 → 190 Cr on 31-Dec-2025. | AG14: =TRUE() -> TRUE
A15: 11 | B15: RBL Bank | C15: Capex LC | D15: NFB | E15: Revolving | F15: =TRUE() -> TRUE | G15: =FALSE() -> FALSE | H15: 0 | I15: INR | J15: 25 | K15: =IFERROR(J15,0) -> 25 | M15: =IFERROR(IF(D15="FB-Term",IF(A15=RBL_TL_SNo,RBL_TL_PrincOS,IF(A15=YBL_TL_SNo,YBL_TL_PrincOS,IF(A15=Bajaj_TL_SNo,Bajaj_TL_PrincOS,0))),IF(L15<>"",L15,IF(UseFullUtil,K15,0))),0) -> 25 | N15: =IFERROR(M15/K15,0) -> 1 | O15: =IFERROR(K15-M15,0) -> 0 | P15: Fixed commission | Q15: 0.005 | R15: {=IFERROR(_xlfn.SWITCH(P15,"1Y MCLR (RBL Bank)",MCLR_RBL_1Y+Q15,"3M MCLR (YBL)",MCLR_YBL_3M+Q15,"6M I-MCLR (ICICI)",IMCLR_ICICI_6M+Q15,"12M MCLR (SIB)",MCLR_SIB_12M+Q15,"Bajaj Floating Reference Rate (BFRR)",BFRR_Bajaj+Q15,"Term SOFR (USD)",SOFR_3M+Q15,"3M T-Bill",TBill_3M+Q15,"Repo Rate",RepoRate+Q15,"FD rate",IFERROR(FD_Rate_RBL,0)+Q15,Q15),0)} -> 0.005 | S15: Fixed | T15: 0 | U15: On Maturity | V15: 36 | W15: 0 | X15: 46022 | Y15: =IFERROR(EDATE(X15,T15),"") -> 46022 | Z15: =IFERROR(EDATE(X15,V15),"") -> 47118 | AA15: 46022 | AB15: 46356 | AC15: Purchase of capital goods | AD15: 1st p-p on FA; 1st p-p mortgage on immovable; 2nd p-p on CA | AE15: RBL Renewal Letter dated 31-Dec-2025 | AF15: Originally 24-Jan-2024; converted revolving 28-Feb-2025. | AG15: =TRUE() -> TRUE
A16: 12 | B16: RBL Bank | C16: Overdraft backed by 100% FD (FDOD) | D16: FB-FDbacked | E16: Revolving | F16: =FALSE() -> FALSE | G16: =TRUE() -> TRUE | H16: 3 | I16: INR | J16: 100 | K16: =IFERROR(J16,0) -> 100 | M16: =IFERROR(IF(D16="FB-Term",IF(A16=RBL_TL_SNo,RBL_TL_PrincOS,IF(A16=YBL_TL_SNo,YBL_TL_PrincOS,IF(A16=Bajaj_TL_SNo,Bajaj_TL_PrincOS,0))),IF(L16<>"",L16,IF(UseFullUtil,K16,0))),0) -> 100 | N16: =IFERROR(M16/K16,0) -> 1 | O16: =IFERROR(K16-M16,0) -> 0 | P16: FD rate | Q16: 0.0025 | R16: {=IFERROR(_xlfn.SWITCH(P16,"1Y MCLR (RBL Bank)",MCLR_RBL_1Y+Q16,"3M MCLR (YBL)",MCLR_YBL_3M+Q16,"6M I-MCLR (ICICI)",IMCLR_ICICI_6M+Q16,"12M MCLR (SIB)",MCLR_SIB_12M+Q16,"Bajaj Floating Reference Rate (BFRR)",BFRR_Bajaj+Q16,"Term SOFR (USD)",SOFR_3M+Q16,"3M T-Bill",TBill_3M+Q16,"Repo Rate",RepoRate+Q16,"FD rate",IFERROR(FD_Rate_RBL,0)+Q16,Q16),0)} -> 0.0725 | S16: Floating | T16: 0 | U16: On Demand | V16: 12 | W16: 0 | X16: 45315 | Y16: =IFERROR(EDATE(X16,T16),"") -> 45315 | Z16: =IFERROR(EDATE(X16,V16),"") -> 45681 | AA16: 45315 | AB16: 46356 | AC16: Cash flow mismatches | AD16: Exclusive charge on FD = 100% of facility | AE16: RBL Renewal cum Enhancement dated 24-Jan-2024 | AF16: Excluded from INR 300 Cr overall cap. | AG16: =FALSE() -> FALSE
A17: 13 | B17: RBL Bank | C17: LC backed by 100% FD | D17: NFB-FDbacked | E17: Revolving | F17: =TRUE() -> TRUE | G17: =TRUE() -> TRUE | H17: 0 | I17: INR | J17: 50 | K17: =IFERROR(J17,0) -> 50 | M17: =IFERROR(IF(D17="FB-Term",IF(A17=RBL_TL_SNo,RBL_TL_PrincOS,IF(A17=YBL_TL_SNo,YBL_TL_PrincOS,IF(A17=Bajaj_TL_SNo,Bajaj_TL_PrincOS,0))),IF(L17<>"",L17,IF(UseFullUtil,K17,0))),0) -> 50 | N17: =IFERROR(M17/K17,0) -> 1 | O17: =IFERROR(K17-M17,0) -> 0 | P17: To be decided | Q17: 0 | R17: {=IFERROR(_xlfn.SWITCH(P17,"1Y MCLR (RBL Bank)",MCLR_RBL_1Y+Q17,"3M MCLR (YBL)",MCLR_YBL_3M+Q17,"6M I-MCLR (ICICI)",IMCLR_ICICI_6M+Q17,"12M MCLR (SIB)",MCLR_SIB_12M+Q17,"Bajaj Floating Reference Rate (BFRR)",BFRR_Bajaj+Q17,"Term SOFR (USD)",SOFR_3M+Q17,"3M T-Bill",TBill_3M+Q17,"Repo Rate",RepoRate+Q17,"FD rate",IFERROR(FD_Rate_RBL,0)+Q17,Q17),0)} -> 0 | S17: TBD | T17: 0 | U17: On Maturity | V17: 12 | W17: 0 | X17: 45315 | Y17: =IFERROR(EDATE(X17,T17),"") -> 45315 | Z17: =IFERROR(EDATE(X17,V17),"") -> 45681 | AA17: 45315 | AB17: 46356 | AC17: WC - import/purchase of raw materials | AD17: Exclusive charge on FD = 100% of facility | AE17: RBL Renewal cum Enhancement dated 24-Jan-2024 | AF17: Sub-limit of FDOD. | AG17: =FALSE() -> FALSE
A18: 14 | B18: RBL Bank | C18: Buyer's Credit from GIFT City - WC | D18: FB-FCY | E18: Revolving | F18: =TRUE() -> TRUE | G18: =FALSE() -> FALSE | H18: 0 | I18: USD | J18: 11 | K18: 100 | M18: =IFERROR(IF(D18="FB-Term",IF(A18=RBL_TL_SNo,RBL_TL_PrincOS,IF(A18=YBL_TL_SNo,YBL_TL_PrincOS,IF(A18=Bajaj_TL_SNo,Bajaj_TL_PrincOS,0))),IF(L18<>"",L18,IF(UseFullUtil,K18,0))),0) -> 100 | N18: =IFERROR(M18/K18,0) -> 1 | O18: =IFERROR(K18-M18,0) -> 0 | P18: Term SOFR (USD) | Q18: 0 | R18: {=IFERROR(_xlfn.SWITCH(P18,"1Y MCLR (RBL Bank)",MCLR_RBL_1Y+Q18,"3M MCLR (YBL)",MCLR_YBL_3M+Q18,"6M I-MCLR (ICICI)",IMCLR_ICICI_6M+Q18,"12M MCLR (SIB)",MCLR_SIB_12M+Q18,"Bajaj Floating Reference Rate (BFRR)",BFRR_Bajaj+Q18,"Term SOFR (USD)",SOFR_3M+Q18,"3M T-Bill",TBill_3M+Q18,"Repo Rate",RepoRate+Q18,"FD rate",IFERROR(FD_Rate_RBL,0)+Q18,Q18),0)} -> 0.043 | S18: Floating | T18: 0 | U18: Bullet | V18: 6 | W18: 1 | X18: 45729 | Y18: =IFERROR(EDATE(X18,T18),"") -> 45729 | Z18: =IFERROR(EDATE(X18,V18),"") -> 45913 | AA18: 45729 | AB18: 46356 | AC18: Working capital | AD18: RBL-issued BG/SBLC | AE18: RBL Buyer's Credit WC Sanction dated 13-Mar-2025 | AF18: INR-capped at ₹100 Cr. | AG18: =FALSE() -> FALSE
A19: 15 | B19: RBL Bank | C19: Buyer's Credit from GIFT City - CAPEX | D19: FB-FCY | E19: Revolving | F19: =TRUE() -> TRUE | G19: =FALSE() -> FALSE | H19: 0 | I19: USD | J19: 20 | K19: 172 | M19: =IFERROR(IF(D19="FB-Term",IF(A19=RBL_TL_SNo,RBL_TL_PrincOS,IF(A19=YBL_TL_SNo,YBL_TL_PrincOS,IF(A19=Bajaj_TL_SNo,Bajaj_TL_PrincOS,0))),IF(L19<>"",L19,IF(UseFullUtil,K19,0))),0) -> 172 | N19: =IFERROR(M19/K19,0) -> 1 | O19: =IFERROR(K19-M19,0) -> 0 | P19: Term SOFR (USD) | Q19: 0 | R19: {=IFERROR(_xlfn.SWITCH(P19,"1Y MCLR (RBL Bank)",MCLR_RBL_1Y+Q19,"3M MCLR (YBL)",MCLR_YBL_3M+Q19,"6M I-MCLR (ICICI)",IMCLR_ICICI_6M+Q19,"12M MCLR (SIB)",MCLR_SIB_12M+Q19,"Bajaj Floating Reference Rate (BFRR)",BFRR_Bajaj+Q19,"Term SOFR (USD)",SOFR_3M+Q19,"3M T-Bill",TBill_3M+Q19,"Repo Rate",RepoRate+Q19,"FD rate",IFERROR(FD_Rate_RBL,0)+Q19,Q19),0)} -> 0.043 | S19: Floating | T19: 0 | U19: Bullet | V19: 36 | W19: 1 | X19: 45743 | Y19: =IFERROR(EDATE(X19,T19),"") -> 45743 | Z19: =IFERROR(EDATE(X19,V19),"") -> 46839 | AA19: 45743 | AB19: 46356 | AC19: CAPEX funding | AD19: RBL-issued BG/SBLC | AE19: RBL Buyer's Credit CAPEX Sanction dated 27-Mar-2025 | AF19: INR-capped at ₹172 Cr. | AG19: =FALSE() -> FALSE
A20: 16 | B20: YES Bank | C20: Purchase Invoice Financing | D20: FB | E20: Revolving | F20: =TRUE() -> TRUE | G20: =FALSE() -> FALSE | H20: 0 | I20: INR | J20: 100 | K20: =IFERROR(J20,0) -> 100 | M20: =IFERROR(IF(D20="FB-Term",IF(A20=RBL_TL_SNo,RBL_TL_PrincOS,IF(A20=YBL_TL_SNo,YBL_TL_PrincOS,IF(A20=Bajaj_TL_SNo,Bajaj_TL_PrincOS,0))),IF(L20<>"",L20,IF(UseFullUtil,K20,0))),0) -> 100 | N20: =IFERROR(M20/K20,0) -> 1 | O20: =IFERROR(K20-M20,0) -> 0 | P20: 3M MCLR (YBL) | Q20: 0.005 | R20: {=IFERROR(_xlfn.SWITCH(P20,"1Y MCLR (RBL Bank)",MCLR_RBL_1Y+Q20,"3M MCLR (YBL)",MCLR_YBL_3M+Q20,"6M I-MCLR (ICICI)",IMCLR_ICICI_6M+Q20,"12M MCLR (SIB)",MCLR_SIB_12M+Q20,"Bajaj Floating Reference Rate (BFRR)",BFRR_Bajaj+Q20,"Term SOFR (USD)",SOFR_3M+Q20,"3M T-Bill",TBill_3M+Q20,"Repo Rate",RepoRate+Q20,"FD rate",IFERROR(FD_Rate_RBL,0)+Q20,Q20),0)} -> 0.095 | S20: TBD | T20: 0 | U20: On Maturity | V20: 3 | W20: 0 | X20: 46100 | Y20: =IFERROR(EDATE(X20,T20),"") -> 46100 | Z20: =IFERROR(EDATE(X20,V20),"") -> 46192 | AA20: 46100 | AB20: 46142 | AC20: Working capital | AD20: 1st p-p hypothecation over current assets | AE20: YBL Renewal cum Addendum dated 19-Mar-2026 | AF20: New facility; interest payable upfront. | AG20: =FALSE() -> FALSE
A21: 17 | B21: YES Bank | C21: Cash Credit | D21: FB | E21: Revolving | F21: =TRUE() -> TRUE | G21: =FALSE() -> FALSE | H21: 0 | I21: INR | J21: 25 | K21: =IFERROR(J21,0) -> 25 | M21: =IFERROR(IF(D21="FB-Term",IF(A21=RBL_TL_SNo,RBL_TL_PrincOS,IF(A21=YBL_TL_SNo,YBL_TL_PrincOS,IF(A21=Bajaj_TL_SNo,Bajaj_TL_PrincOS,0))),IF(L21<>"",L21,IF(UseFullUtil,K21,0))),0) -> 25 | N21: =IFERROR(M21/K21,0) -> 1 | O21: =IFERROR(K21-M21,0) -> 0 | P21: 3M MCLR (YBL) | Q21: 0.0007 | R21: {=IFERROR(_xlfn.SWITCH(P21,"1Y MCLR (RBL Bank)",MCLR_RBL_1Y+Q21,"3M MCLR (YBL)",MCLR_YBL_3M+Q21,"6M I-MCLR (ICICI)",IMCLR_ICICI_6M+Q21,"12M MCLR (SIB)",MCLR_SIB_12M+Q21,"Bajaj Floating Reference Rate (BFRR)",BFRR_Bajaj+Q21,"Term SOFR (USD)",SOFR_3M+Q21,"3M T-Bill",TBill_3M+Q21,"Repo Rate",RepoRate+Q21,"FD rate",IFERROR(FD_Rate_RBL,0)+Q21,Q21),0)} -> 0.0907 | S21: Floating | T21: 0 | U21: On Demand | V21: 12 | W21: 0 | X21: 46100 | Y21: =IFERROR(EDATE(X21,T21),"") -> 46100 | Z21: =IFERROR(EDATE(X21,V21),"") -> 46465 | AA21: 46100 | AB21: 46490 | AC21: Working capital | AD21: 1st p-p on CA; mortgage on Faridabad property; 2nd p-p on FA; Personal Guarantee | AE21: YBL Renewal cum Addendum dated 19-Mar-2026 | AF21: Pricing moved to 3M MCLR + 7 bps on 19-Mar-2026. | AG21: =FALSE() -> FALSE
A22: 18 | B22: YES Bank | C22: Letter of Credit | D22: NFB | E22: Revolving | F22: =FALSE() -> FALSE | G22: =FALSE() -> FALSE | H22: 2 | I22: INR | J22: 200 | K22: =IFERROR(J22,0) -> 200 | M22: =IFERROR(IF(D22="FB-Term",IF(A22=RBL_TL_SNo,RBL_TL_PrincOS,IF(A22=YBL_TL_SNo,YBL_TL_PrincOS,IF(A22=Bajaj_TL_SNo,Bajaj_TL_PrincOS,0))),IF(L22<>"",L22,IF(UseFullUtil,K22,0))),0) -> 200 | N22: =IFERROR(M22/K22,0) -> 1 | O22: =IFERROR(K22-M22,0) -> 0 | P22: Fixed commission | Q22: 0 | R22: {=IFERROR(_xlfn.SWITCH(P22,"1Y MCLR (RBL Bank)",MCLR_RBL_1Y+Q22,"3M MCLR (YBL)",MCLR_YBL_3M+Q22,"6M I-MCLR (ICICI)",IMCLR_ICICI_6M+Q22,"12M MCLR (SIB)",MCLR_SIB_12M+Q22,"Bajaj Floating Reference Rate (BFRR)",BFRR_Bajaj+Q22,"Term SOFR (USD)",SOFR_3M+Q22,"3M T-Bill",TBill_3M+Q22,"Repo Rate",RepoRate+Q22,"FD rate",IFERROR(FD_Rate_RBL,0)+Q22,Q22),0)} -> 0 | S22: Fixed | T22: 0 | U22: On Maturity | V22: 7 | W22: 0 | X22: 46100 | Y22: =IFERROR(EDATE(X22,T22),"") -> 46100 | Z22: =IFERROR(EDATE(X22,V22),"") -> 46314 | AA22: 46100 | AB22: 46472 | AC22: Procurement of raw materials | AD22: 1st p-p on CA; mortgage on Faridabad property; 2nd p-p on FA; Personal Guarantee | AE22: YBL Renewal cum Addendum dated 19-Mar-2026 | AF22: Overall WC cap INR 200 Cr net of receivable finance. | AG22: =TRUE() -> TRUE
A23: 19 | B23: YES Bank | C23: Financial BG / SBLC | D23: NFB | E23: Revolving | F23: =TRUE() -> TRUE | G23: =FALSE() -> FALSE | H23: 0 | I23: INR | J23: 200 | K23: =IFERROR(J23,0) -> 200 | M23: =IFERROR(IF(D23="FB-Term",IF(A23=RBL_TL_SNo,RBL_TL_PrincOS,IF(A23=YBL_TL_SNo,YBL_TL_PrincOS,IF(A23=Bajaj_TL_SNo,Bajaj_TL_PrincOS,0))),IF(L23<>"",L23,IF(UseFullUtil,K23,0))),0) -> 200 | N23: =IFERROR(M23/K23,0) -> 1 | O23: =IFERROR(K23-M23,0) -> 0 | P23: Fixed commission | Q23: 0.005 | R23: {=IFERROR(_xlfn.SWITCH(P23,"1Y MCLR (RBL Bank)",MCLR_RBL_1Y+Q23,"3M MCLR (YBL)",MCLR_YBL_3M+Q23,"6M I-MCLR (ICICI)",IMCLR_ICICI_6M+Q23,"12M MCLR (SIB)",MCLR_SIB_12M+Q23,"Bajaj Floating Reference Rate (BFRR)",BFRR_Bajaj+Q23,"Term SOFR (USD)",SOFR_3M+Q23,"3M T-Bill",TBill_3M+Q23,"Repo Rate",RepoRate+Q23,"FD rate",IFERROR(FD_Rate_RBL,0)+Q23,Q23),0)} -> 0.005 | S23: Fixed | T23: 0 | U23: On Maturity | V23: 6 | W23: 0 | X23: 46100 | Y23: =IFERROR(EDATE(X23,T23),"") -> 46100 | Z23: =IFERROR(EDATE(X23,V23),"") -> 46284 | AA23: 46100 | AB23: 46490 | AC23: Securing payment for raw materials / paper | AD23: 1st p-p on CA; mortgage on Faridabad property; 2nd p-p on FA; Personal Guarantee | AE23: YBL Renewal cum Addendum dated 19-Mar-2026 | AF23: Sub-limit of LC (Main). | AG23: =FALSE() -> FALSE
A24: 20 | B24: YES Bank | C24: Working Capital Demand Loan (WCDL) | D24: FB | E24: Revolving | F24: =TRUE() -> TRUE | G24: =FALSE() -> FALSE | H24: 0 | I24: INR | J24: 50 | K24: =IFERROR(J24,0) -> 50 | M24: =IFERROR(IF(D24="FB-Term",IF(A24=RBL_TL_SNo,RBL_TL_PrincOS,IF(A24=YBL_TL_SNo,YBL_TL_PrincOS,IF(A24=Bajaj_TL_SNo,Bajaj_TL_PrincOS,0))),IF(L24<>"",L24,IF(UseFullUtil,K24,0))),0) -> 50 | N24: =IFERROR(M24/K24,0) -> 1 | O24: =IFERROR(K24-M24,0) -> 0 | P24: To be decided | Q24: 0 | R24: {=IFERROR(_xlfn.SWITCH(P24,"1Y MCLR (RBL Bank)",MCLR_RBL_1Y+Q24,"3M MCLR (YBL)",MCLR_YBL_3M+Q24,"6M I-MCLR (ICICI)",IMCLR_ICICI_6M+Q24,"12M MCLR (SIB)",MCLR_SIB_12M+Q24,"Bajaj Floating Reference Rate (BFRR)",BFRR_Bajaj+Q24,"Term SOFR (USD)",SOFR_3M+Q24,"3M T-Bill",TBill_3M+Q24,"Repo Rate",RepoRate+Q24,"FD rate",IFERROR(FD_Rate_RBL,0)+Q24,Q24),0)} -> 0 | S24: TBD | T24: 0 | U24: On Demand | V24: 6 | W24: 0 | X24: 46100 | Y24: =IFERROR(EDATE(X24,T24),"") -> 46100 | Z24: =IFERROR(EDATE(X24,V24),"") -> 46284 | AA24: 46100 | AB24: 46490 | AC24: Working capital | AD24: 1st p-p on CA; mortgage on Faridabad property; 2nd p-p on FA; Personal Guarantee | AE24: YBL Renewal cum Addendum dated 19-Mar-2026 | AF24: Min utilisation covenant: 40% of YBL limits. | AG24: =FALSE() -> FALSE
A25: 21 | B25: YES Bank | C25: Term Loan (Refinance Canara) | D25: FB-Term | E25: Non-Revolving | F25: =FALSE() -> FALSE | G25: =FALSE() -> FALSE | H25: 1 | I25: INR | J25: 320.7 | K25: =IFERROR(J25,0) -> 320.7 | M25: =IFERROR(IF(D25="FB-Term",IF(A25=RBL_TL_SNo,RBL_TL_PrincOS,IF(A25=YBL_TL_SNo,YBL_TL_PrincOS,IF(A25=Bajaj_TL_SNo,Bajaj_TL_PrincOS,0))),IF(L25<>"",L25,IF(UseFullUtil,K25,0))),0) -> 295.9612 | N25: =IFERROR(M25/K25,0) -> 0.92285999 | O25: =IFERROR(K25-M25,0) -> 24.7388 | P25: 3M T-Bill | Q25: 0.0252 | R25: {=IFERROR(_xlfn.SWITCH(P25,"1Y MCLR (RBL Bank)",MCLR_RBL_1Y+Q25,"3M MCLR (YBL)",MCLR_YBL_3M+Q25,"6M I-MCLR (ICICI)",IMCLR_ICICI_6M+Q25,"12M MCLR (SIB)",MCLR_SIB_12M+Q25,"Bajaj Floating Reference Rate (BFRR)",BFRR_Bajaj+Q25,"Term SOFR (USD)",SOFR_3M+Q25,"3M T-Bill",TBill_3M+Q25,"Repo Rate",RepoRate+Q25,"FD rate",IFERROR(FD_Rate_RBL,0)+Q25,Q25),0)} -> 0.077 | S25: Floating | T25: 0 | U25: Quarterly | V25: 146 | W25: 46 | X25: 45642 | Y25: 45838 | Z25: =YBL_TL_Maturity -> 49948 | AA25: 45744 | AB25: 46253 | AC25: Refinance Canara TL + reimburse promoter loan + IA | AD25: 2nd p-p on CA; 1st p-p on FA; 1st p-p EM Kalinga Nagar | AE25: YBL TL Addendum dated 28-Mar-2025 | AF25: 47 EQI of ₹6.82 Cr per sanction letter 16-Dec-2024. | AG25: =FALSE() -> FALSE
A26: 22 | B26: Bajaj Finance | C26: Term Loan | D26: FB-Term | E26: Non-Revolving | F26: =FALSE() -> FALSE | G26: =FALSE() -> FALSE | H26: 1 | I26: INR | J26: 150 | K26: =IFERROR(J26,0) -> 150 | M26: =IFERROR(IF(D26="FB-Term",IF(A26=RBL_TL_SNo,RBL_TL_PrincOS,IF(A26=YBL_TL_SNo,YBL_TL_PrincOS,IF(A26=Bajaj_TL_SNo,Bajaj_TL_PrincOS,0))),IF(L26<>"",L26,IF(UseFullUtil,K26,0))),0) -> 150 | N26: =IFERROR(M26/K26,0) -> 1 | O26: =IFERROR(K26-M26,0) -> 0 | P26: Bajaj Floating Reference Rate (BFRR) | Q26: 0.001 | R26: {=IFERROR(_xlfn.SWITCH(P26,"1Y MCLR (RBL Bank)",MCLR_RBL_1Y+Q26,"3M MCLR (YBL)",MCLR_YBL_3M+Q26,"6M I-MCLR (ICICI)",IMCLR_ICICI_6M+Q26,"12M MCLR (SIB)",MCLR_SIB_12M+Q26,"Bajaj Floating Reference Rate (BFRR)",BFRR_Bajaj+Q26,"Term SOFR (USD)",SOFR_3M+Q26,"3M T-Bill",TBill_3M+Q26,"Repo Rate",RepoRate+Q26,"FD rate",IFERROR(FD_Rate_RBL,0)+Q26,Q26),0)} -> 0.086 | S26: Floating | T26: 12 | U26: Quarterly | V26: 96 | W26: 28 | X26: 45894 | Y26: 46361 | Z26: =Bajaj_TL_Maturity -> 48816 | AA26: 45887 | AB26: 45894 | AC26: CAPEX reimbursement + CAPEX + GCP | AD26: 1st p-p on FA at Coke Plant Khurunti; 2nd p-p on CA; MSC 1.25x; Personal guarantee | AE26: Bajaj TL Sanction BFL/CL-MM/2025-26/JCL/01 dated 18-Aug-2025 | AF26: Floating; quarterly reset; WDV basis. 12-month moratorium. | AG26: =FALSE() -> FALSE
A27: 23 | B27: ICICI Bank | C27: Cash Credit | D27: FB | E27: Revolving | F27: =FALSE() -> FALSE | G27: =FALSE() -> FALSE | H27: 1 | I27: INR | J27: 50 | K27: =IFERROR(J27,0) -> 50 | M27: =IFERROR(IF(D27="FB-Term",IF(A27=RBL_TL_SNo,RBL_TL_PrincOS,IF(A27=YBL_TL_SNo,YBL_TL_PrincOS,IF(A27=Bajaj_TL_SNo,Bajaj_TL_PrincOS,0))),IF(L27<>"",L27,IF(UseFullUtil,K27,0))),0) -> 50 | N27: =IFERROR(M27/K27,0) -> 1 | O27: =IFERROR(K27-M27,0) -> 0 | P27: 6M I-MCLR (ICICI) | Q27: 0.0045 | R27: {=IFERROR(_xlfn.SWITCH(P27,"1Y MCLR (RBL Bank)",MCLR_RBL_1Y+Q27,"3M MCLR (YBL)",MCLR_YBL_3M+Q27,"6M I-MCLR (ICICI)",IMCLR_ICICI_6M+Q27,"12M MCLR (SIB)",MCLR_SIB_12M+Q27,"Bajaj Floating Reference Rate (BFRR)",BFRR_Bajaj+Q27,"Term SOFR (USD)",SOFR_3M+Q27,"3M T-Bill",TBill_3M+Q27,"Repo Rate",RepoRate+Q27,"FD rate",IFERROR(FD_Rate_RBL,0)+Q27,Q27),0)} -> 0.0875 | S27: Floating | T27: 0 | U27: On Demand | V27: 12 | W27: 0 | X27: 45916 | Y27: =IFERROR(EDATE(X27,T27),"") -> 45916 | Z27: =IFERROR(EDATE(X27,V27),"") -> 46281 | AA27: 45916 | AB27: 46268 | AC27: Working capital | AD27: 1st p-p on CA; 2nd p-p on FA; 2nd p-p mortgage Kalinga Nagar | AE27: ICICI Credit Arrangement Letter dated 16-Sep-2025 | AF27: Reset 6 monthly; one-way interchangeability CC→LC. | AG27: =FALSE() -> FALSE
A28: 24 | B28: ICICI Bank | C28: Working Capital Demand Loan (WCDL) | D28: FB | E28: Revolving | F28: =TRUE() -> TRUE | G28: =FALSE() -> FALSE | H28: 0 | I28: INR | J28: 50 | K28: =IFERROR(J28,0) -> 50 | M28: =IFERROR(IF(D28="FB-Term",IF(A28=RBL_TL_SNo,RBL_TL_PrincOS,IF(A28=YBL_TL_SNo,YBL_TL_PrincOS,IF(A28=Bajaj_TL_SNo,Bajaj_TL_PrincOS,0))),IF(L28<>"",L28,IF(UseFullUtil,K28,0))),0) -> 50 | N28: =IFERROR(M28/K28,0) -> 1 | O28: =IFERROR(K28-M28,0) -> 0 | P28: Repo Rate | Q28: 0 | R28: {=IFERROR(_xlfn.SWITCH(P28,"1Y MCLR (RBL Bank)",MCLR_RBL_1Y+Q28,"3M MCLR (YBL)",MCLR_YBL_3M+Q28,"6M I-MCLR (ICICI)",IMCLR_ICICI_6M+Q28,"12M MCLR (SIB)",MCLR_SIB_12M+Q28,"Bajaj Floating Reference Rate (BFRR)",BFRR_Bajaj+Q28,"Term SOFR (USD)",SOFR_3M+Q28,"3M T-Bill",TBill_3M+Q28,"Repo Rate",RepoRate+Q28,"FD rate",IFERROR(FD_Rate_RBL,0)+Q28,Q28),0)} -> 0.0525 | S28: Floating | T28: 0 | U28: On Maturity | V28: 3 | W28: 0 | X28: 45972 | Y28: =IFERROR(EDATE(X28,T28),"") -> 45972 | Z28: =IFERROR(EDATE(X28,V28),"") -> 46064 | AA28: 45972 | AB28: 46268 | AC28: Working capital (bullet) | AD28: 1st p-p on CA; 2nd p-p on FA; 2nd p-p mortgage Kalinga Nagar | AE28: ICICI WCDL Addendum dated 11-Nov-2025 | AF28: Repo reset; spread TBD. | AG28: =FALSE() -> FALSE
A29: 25 | B29: ICICI Bank | C29: Letter of Credit (Inland/Foreign) | D29: NFB | E29: Revolving | F29: =FALSE() -> FALSE | G29: =FALSE() -> FALSE | H29: 2 | I29: INR | J29: 150 | K29: =IFERROR(J29,0) -> 150 | M29: =IFERROR(IF(D29="FB-Term",IF(A29=RBL_TL_SNo,RBL_TL_PrincOS,IF(A29=YBL_TL_SNo,YBL_TL_PrincOS,IF(A29=Bajaj_TL_SNo,Bajaj_TL_PrincOS,0))),IF(L29<>"",L29,IF(UseFullUtil,K29,0))),0) -> 150 | N29: =IFERROR(M29/K29,0) -> 1 | O29: =IFERROR(K29-M29,0) -> 0 | P29: Fixed commission | Q29: 0.005 | R29: {=IFERROR(_xlfn.SWITCH(P29,"1Y MCLR (RBL Bank)",MCLR_RBL_1Y+Q29,"3M MCLR (YBL)",MCLR_YBL_3M+Q29,"6M I-MCLR (ICICI)",IMCLR_ICICI_6M+Q29,"12M MCLR (SIB)",MCLR_SIB_12M+Q29,"Bajaj Floating Reference Rate (BFRR)",BFRR_Bajaj+Q29,"Term SOFR (USD)",SOFR_3M+Q29,"3M T-Bill",TBill_3M+Q29,"Repo Rate",RepoRate+Q29,"FD rate",IFERROR(FD_Rate_RBL,0)+Q29,Q29),0)} -> 0.005 | S29: Fixed | T29: 0 | U29: On Maturity | V29: 5 | W29: 0 | X29: 45916 | Y29: =IFERROR(EDATE(X29,T29),"") -> 45916 | Z29: =IFERROR(EDATE(X29,V29),"") -> 46069 | AA29: 45916 | AB29: 46268 | AC29: RM, consumables, stores, spares, tools | AD29: 1st p-p on CA; 2nd p-p on FA; 2nd p-p mortgage Kalinga Nagar | AE29: ICICI Credit Arrangement Letter dated 16-Sep-2025 | AF29: LC to JSL Global Commodities Pte Ltd capped at INR 25 Cr. | AG29: =TRUE() -> TRUE
A30: 26 | B30: ICICI Bank | C30: SBLC for Buyers' Credit | D30: NFB | E30: Revolving | F30: =TRUE() -> TRUE | G30: =FALSE() -> FALSE | H30: 0 | I30: INR | J30: 150 | K30: =IFERROR(J30,0) -> 150 | M30: =IFERROR(IF(D30="FB-Term",IF(A30=RBL_TL_SNo,RBL_TL_PrincOS,IF(A30=YBL_TL_SNo,YBL_TL_PrincOS,IF(A30=Bajaj_TL_SNo,Bajaj_TL_PrincOS,0))),IF(L30<>"",L30,IF(UseFullUtil,K30,0))),0) -> 150 | N30: =IFERROR(M30/K30,0) -> 1 | O30: =IFERROR(K30-M30,0) -> 0 | P30: Fixed commission | Q30: 0.005 | R30: {=IFERROR(_xlfn.SWITCH(P30,"1Y MCLR (RBL Bank)",MCLR_RBL_1Y+Q30,"3M MCLR (YBL)",MCLR_YBL_3M+Q30,"6M I-MCLR (ICICI)",IMCLR_ICICI_6M+Q30,"12M MCLR (SIB)",MCLR_SIB_12M+Q30,"Bajaj Floating Reference Rate (BFRR)",BFRR_Bajaj+Q30,"Term SOFR (USD)",SOFR_3M+Q30,"3M T-Bill",TBill_3M+Q30,"Repo Rate",RepoRate+Q30,"FD rate",IFERROR(FD_Rate_RBL,0)+Q30,Q30),0)} -> 0.005 | S30: Fixed | T30: 0 | U30: On Maturity | V30: 5 | W30: 0 | X30: 45916 | Y30: =IFERROR(EDATE(X30,T30),"") -> 45916 | Z30: =IFERROR(EDATE(X30,V30),"") -> 46069 | AA30: 45916 | AB30: 46268 | AC30: Buyer's credit (USD/INR) | AD30: 1st p-p on CA; 2nd p-p on FA; 2nd p-p mortgage Kalinga Nagar | AE30: ICICI Credit Arrangement Letter dated 16-Sep-2025 | AF30: Sub-limit of LC. | AG30: =FALSE() -> FALSE
A31: 27 | B31: ICICI Bank | C31: Bank Guarantee - Performance | D31: NFB | E31: Revolving | F31: =TRUE() -> TRUE | G31: =FALSE() -> FALSE | H31: 0 | I31: INR | J31: 25 | K31: =IFERROR(J31,0) -> 25 | M31: =IFERROR(IF(D31="FB-Term",IF(A31=RBL_TL_SNo,RBL_TL_PrincOS,IF(A31=YBL_TL_SNo,YBL_TL_PrincOS,IF(A31=Bajaj_TL_SNo,Bajaj_TL_PrincOS,0))),IF(L31<>"",L31,IF(UseFullUtil,K31,0))),0) -> 25 | N31: =IFERROR(M31/K31,0) -> 1 | O31: =IFERROR(K31-M31,0) -> 0 | P31: Fixed commission | Q31: 0.005 | R31: {=IFERROR(_xlfn.SWITCH(P31,"1Y MCLR (RBL Bank)",MCLR_RBL_1Y+Q31,"3M MCLR (YBL)",MCLR_YBL_3M+Q31,"6M I-MCLR (ICICI)",IMCLR_ICICI_6M+Q31,"12M MCLR (SIB)",MCLR_SIB_12M+Q31,"Bajaj Floating Reference Rate (BFRR)",BFRR_Bajaj+Q31,"Term SOFR (USD)",SOFR_3M+Q31,"3M T-Bill",TBill_3M+Q31,"Repo Rate",RepoRate+Q31,"FD rate",IFERROR(FD_Rate_RBL,0)+Q31,Q31),0)} -> 0.005 | S31: Fixed | T31: 0 | U31: On Maturity | V31: 36 | W31: 0 | X31: 45916 | Y31: =IFERROR(EDATE(X31,T31),"") -> 45916 | Z31: =IFERROR(EDATE(X31,V31),"") -> 47012 | AA31: 45916 | AB31: 46268 | AC31: Bid bond, EMD, performance, customs | AD31: 1st p-p on CA; 2nd p-p on FA; 2nd p-p mortgage Kalinga Nagar | AE31: ICICI Credit Arrangement Letter dated 16-Sep-2025 | AF31: Sub-limit of LC. | AG31: =FALSE() -> FALSE
A32: 28 | B32: ICICI Bank | C32: Bank Guarantee - Financial | D32: NFB | E32: Revolving | F32: =TRUE() -> TRUE | G32: =FALSE() -> FALSE | H32: 0 | I32: INR | J32: 5 | K32: =IFERROR(J32,0) -> 5 | M32: =IFERROR(IF(D32="FB-Term",IF(A32=RBL_TL_SNo,RBL_TL_PrincOS,IF(A32=YBL_TL_SNo,YBL_TL_PrincOS,IF(A32=Bajaj_TL_SNo,Bajaj_TL_PrincOS,0))),IF(L32<>"",L32,IF(UseFullUtil,K32,0))),0) -> 5 | N32: =IFERROR(M32/K32,0) -> 1 | O32: =IFERROR(K32-M32,0) -> 0 | P32: Fixed commission | Q32: 0.006 | R32: {=IFERROR(_xlfn.SWITCH(P32,"1Y MCLR (RBL Bank)",MCLR_RBL_1Y+Q32,"3M MCLR (YBL)",MCLR_YBL_3M+Q32,"6M I-MCLR (ICICI)",IMCLR_ICICI_6M+Q32,"12M MCLR (SIB)",MCLR_SIB_12M+Q32,"Bajaj Floating Reference Rate (BFRR)",BFRR_Bajaj+Q32,"Term SOFR (USD)",SOFR_3M+Q32,"3M T-Bill",TBill_3M+Q32,"Repo Rate",RepoRate+Q32,"FD rate",IFERROR(FD_Rate_RBL,0)+Q32,Q32),0)} -> 0.006 | S32: Fixed | T32: 0 | U32: On Maturity | V32: 36 | W32: 0 | X32: 45916 | Y32: =IFERROR(EDATE(X32,T32),"") -> 45916 | Z32: =IFERROR(EDATE(X32,V32),"") -> 47012 | AA32: 45916 | AB32: 46268 | AC32: Financial guarantees | AD32: 1st p-p on CA; 2nd p-p on FA; 2nd p-p mortgage Kalinga Nagar | AE32: ICICI Credit Arrangement Letter dated 16-Sep-2025 | AF32: Sub-limit of LC. | AG32: =FALSE() -> FALSE
A33: 29 | B33: South Indian Bank | C33: CCOL (Cash Credit) | D33: FB | E33: Revolving | F33: =TRUE() -> TRUE | G33: =FALSE() -> FALSE | H33: 0 | I33: INR | J33: 50 | K33: =IFERROR(J33,0) -> 50 | M33: =IFERROR(IF(D33="FB-Term",IF(A33=RBL_TL_SNo,RBL_TL_PrincOS,IF(A33=YBL_TL_SNo,YBL_TL_PrincOS,IF(A33=Bajaj_TL_SNo,Bajaj_TL_PrincOS,0))),IF(L33<>"",L33,IF(UseFullUtil,K33,0))),0) -> 50 | N33: =IFERROR(M33/K33,0) -> 1 | O33: =IFERROR(K33-M33,0) -> 0 | P33: 12M MCLR (SIB) | Q33: 0.0045 | R33: {=IFERROR(_xlfn.SWITCH(P33,"1Y MCLR (RBL Bank)",MCLR_RBL_1Y+Q33,"3M MCLR (YBL)",MCLR_YBL_3M+Q33,"6M I-MCLR (ICICI)",IMCLR_ICICI_6M+Q33,"12M MCLR (SIB)",MCLR_SIB_12M+Q33,"Bajaj Floating Reference Rate (BFRR)",BFRR_Bajaj+Q33,"Term SOFR (USD)",SOFR_3M+Q33,"3M T-Bill",TBill_3M+Q33,"Repo Rate",RepoRate+Q33,"FD rate",IFERROR(FD_Rate_RBL,0)+Q33,Q33),0)} -> 0.102 | S33: Floating | T33: 0 | U33: On Demand | V33: 12 | W33: 0 | X33: 45829 | Y33: =IFERROR(EDATE(X33,T33),"") -> 45829 | Z33: =IFERROR(EDATE(X33,V33),"") -> 46194 | AA33: 45829 | AB33: 46194 | AC33: Pre-sale and post-sale working capital | AD33: 1st p-p on CA; 2nd p-p on FA; 2nd p-p mortgage Kalinga Nagar | AE33: SIB Renewal BR/SANC/01/2025-26 dated 21-Jun-2025 | AF33: Annual reset. | AG33: =FALSE() -> FALSE
A34: 30 | B34: South Indian Bank | C34: WCL / WCDL | D34: FB | E34: Revolving | F34: =TRUE() -> TRUE | G34: =FALSE() -> FALSE | H34: 0 | I34: INR | J34: 50 | K34: =IFERROR(J34,0) -> 50 | M34: =IFERROR(IF(D34="FB-Term",IF(A34=RBL_TL_SNo,RBL_TL_PrincOS,IF(A34=YBL_TL_SNo,YBL_TL_PrincOS,IF(A34=Bajaj_TL_SNo,Bajaj_TL_PrincOS,0))),IF(L34<>"",L34,IF(UseFullUtil,K34,0))),0) -> 50 | N34: =IFERROR(M34/K34,0) -> 1 | O34: =IFERROR(K34-M34,0) -> 0 | P34: To be decided | Q34: 0 | R34: {=IFERROR(_xlfn.SWITCH(P34,"1Y MCLR (RBL Bank)",MCLR_RBL_1Y+Q34,"3M MCLR (YBL)",MCLR_YBL_3M+Q34,"6M I-MCLR (ICICI)",IMCLR_ICICI_6M+Q34,"12M MCLR (SIB)",MCLR_SIB_12M+Q34,"Bajaj Floating Reference Rate (BFRR)",BFRR_Bajaj+Q34,"Term SOFR (USD)",SOFR_3M+Q34,"3M T-Bill",TBill_3M+Q34,"Repo Rate",RepoRate+Q34,"FD rate",IFERROR(FD_Rate_RBL,0)+Q34,Q34),0)} -> 0 | S34: TBD | T34: 0 | U34: On Maturity | V34: 12 | W34: 0 | X34: 45829 | Y34: =IFERROR(EDATE(X34,T34),"") -> 45829 | Z34: =IFERROR(EDATE(X34,V34),"") -> 46194 | AA34: 45829 | AB34: 46194 | AC34: Working capital (bullet) | AD34: 1st p-p on CA; 2nd p-p on FA; 2nd p-p mortgage Kalinga Nagar | AE34: SIB Renewal BR/SANC/01/2025-26 dated 21-Jun-2025 | AF34: Sub-limit of CCOL. | AG34: =FALSE() -> FALSE
A35: 31 | B35: South Indian Bank | C35: Inland / Import LC | D35: NFB | E35: Revolving | F35: =FALSE() -> FALSE | G35: =FALSE() -> FALSE | H35: 2 | I35: INR | J35: 150 | K35: =IFERROR(J35,0) -> 150 | M35: =IFERROR(IF(D35="FB-Term",IF(A35=RBL_TL_SNo,RBL_TL_PrincOS,IF(A35=YBL_TL_SNo,YBL_TL_PrincOS,IF(A35=Bajaj_TL_SNo,Bajaj_TL_PrincOS,0))),IF(L35<>"",L35,IF(UseFullUtil,K35,0))),0) -> 150 | N35: =IFERROR(M35/K35,0) -> 1 | O35: =IFERROR(K35-M35,0) -> 0 | P35: Fixed commission | Q35: 0.0065 | R35: {=IFERROR(_xlfn.SWITCH(P35,"1Y MCLR (RBL Bank)",MCLR_RBL_1Y+Q35,"3M MCLR (YBL)",MCLR_YBL_3M+Q35,"6M I-MCLR (ICICI)",IMCLR_ICICI_6M+Q35,"12M MCLR (SIB)",MCLR_SIB_12M+Q35,"Bajaj Floating Reference Rate (BFRR)",BFRR_Bajaj+Q35,"Term SOFR (USD)",SOFR_3M+Q35,"3M T-Bill",TBill_3M+Q35,"Repo Rate",RepoRate+Q35,"FD rate",IFERROR(FD_Rate_RBL,0)+Q35,Q35),0)} -> 0.0065 | S35: Fixed | T35: 0 | U35: On Maturity | V35: 6 | W35: 0 | X35: 45829 | Y35: =IFERROR(EDATE(X35,T35),"") -> 45829 | Z35: =IFERROR(EDATE(X35,V35),"") -> 46012 | AA35: 45829 | AB35: 46194 | AC35: Purchase / import of RM, trading goods, services | AD35: 1st p-p on CA; 2nd p-p on FA; 2nd p-p mortgage Kalinga Nagar | AE35: SIB Renewal BR/SANC/01/2025-26 dated 21-Jun-2025 | AF35: Total LC + Capex LC ≤ INR 150 Cr. | AG35: =TRUE() -> TRUE
A36: 32 | B36: South Indian Bank | C36: Capex LC | D36: NFB | E36: Revolving | F36: =TRUE() -> TRUE | G36: =FALSE() -> FALSE | H36: 0 | I36: INR | J36: 50 | K36: =IFERROR(J36,0) -> 50 | M36: =IFERROR(IF(D36="FB-Term",IF(A36=RBL_TL_SNo,RBL_TL_PrincOS,IF(A36=YBL_TL_SNo,YBL_TL_PrincOS,IF(A36=Bajaj_TL_SNo,Bajaj_TL_PrincOS,0))),IF(L36<>"",L36,IF(UseFullUtil,K36,0))),0) -> 50 | N36: =IFERROR(M36/K36,0) -> 1 | O36: =IFERROR(K36-M36,0) -> 0 | P36: Fixed commission | Q36: 0.0075 | R36: {=IFERROR(_xlfn.SWITCH(P36,"1Y MCLR (RBL Bank)",MCLR_RBL_1Y+Q36,"3M MCLR (YBL)",MCLR_YBL_3M+Q36,"6M I-MCLR (ICICI)",IMCLR_ICICI_6M+Q36,"12M MCLR (SIB)",MCLR_SIB_12M+Q36,"Bajaj Floating Reference Rate (BFRR)",BFRR_Bajaj+Q36,"Term SOFR (USD)",SOFR_3M+Q36,"3M T-Bill",TBill_3M+Q36,"Repo Rate",RepoRate+Q36,"FD rate",IFERROR(FD_Rate_RBL,0)+Q36,Q36),0)} -> 0.0075 | S36: Fixed | T36: 0 | U36: On Maturity | V36: 12 | W36: 0 | X36: 45829 | Y36: =IFERROR(EDATE(X36,T36),"") -> 45829 | Z36: =IFERROR(EDATE(X36,V36),"") -> 46194 | AA36: 45829 | AB36: 46194 | AC36: Capital goods and capital maintenance | AD36: 1st p-p on CA; 2nd p-p on FA; 2nd p-p mortgage Kalinga Nagar | AE36: SIB Renewal BR/SANC/01/2025-26 dated 21-Jun-2025 | AF36: Combined with Inland/Import LC limit. | AG36: =FALSE() -> FALSE
A37: 33 | B37: South Indian Bank | C37: SBLC | D37: NFB | E37: Revolving | F37: =TRUE() -> TRUE | G37: =FALSE() -> FALSE | H37: 0 | I37: INR | J37: 150 | K37: =IFERROR(J37,0) -> 150 | M37: =IFERROR(IF(D37="FB-Term",IF(A37=RBL_TL_SNo,RBL_TL_PrincOS,IF(A37=YBL_TL_SNo,YBL_TL_PrincOS,IF(A37=Bajaj_TL_SNo,Bajaj_TL_PrincOS,0))),IF(L37<>"",L37,IF(UseFullUtil,K37,0))),0) -> 150 | N37: =IFERROR(M37/K37,0) -> 1 | O37: =IFERROR(K37-M37,0) -> 0 | P37: Fixed commission | Q37: 0.0065 | R37: {=IFERROR(_xlfn.SWITCH(P37,"1Y MCLR (RBL Bank)",MCLR_RBL_1Y+Q37,"3M MCLR (YBL)",MCLR_YBL_3M+Q37,"6M I-MCLR (ICICI)",IMCLR_ICICI_6M+Q37,"12M MCLR (SIB)",MCLR_SIB_12M+Q37,"Bajaj Floating Reference Rate (BFRR)",BFRR_Bajaj+Q37,"Term SOFR (USD)",SOFR_3M+Q37,"3M T-Bill",TBill_3M+Q37,"Repo Rate",RepoRate+Q37,"FD rate",IFERROR(FD_Rate_RBL,0)+Q37,Q37),0)} -> 0.0065 | S37: Fixed | T37: 0 | U37: On Maturity | V37: 4 | W37: 0 | X37: 45829 | Y37: =IFERROR(EDATE(X37,T37),"") -> 45829 | Z37: =IFERROR(EDATE(X37,V37),"") -> 45951 | AA37: 45829 | AB37: 46194 | AC37: Buyer's credit for import payments | AD37: 1st p-p on CA; 2nd p-p on FA; 2nd p-p mortgage Kalinga Nagar | AE37: SIB Renewal BR/SANC/01/2025-26 dated 21-Jun-2025 | AF37: Sub-limit of LC. | AG37: =FALSE() -> FALSE
A38: 34 | B38: South Indian Bank | C38: Forward Contract Limit | D38: Hedge | E38: Revolving | F38: =FALSE() -> FALSE | G38: =FALSE() -> FALSE | H38: 0 | I38: INR | J38: 3 | K38: =IFERROR(J38,0) -> 3 | M38: =IFERROR(IF(D38="FB-Term",IF(A38=RBL_TL_SNo,RBL_TL_PrincOS,IF(A38=YBL_TL_SNo,YBL_TL_PrincOS,IF(A38=Bajaj_TL_SNo,Bajaj_TL_PrincOS,0))),IF(L38<>"",L38,IF(UseFullUtil,K38,0))),0) -> 3 | N38: =IFERROR(M38/K38,0) -> 1 | O38: =IFERROR(K38-M38,0) -> 0 | P38: N/A | Q38: 0 | R38: {=IFERROR(_xlfn.SWITCH(P38,"1Y MCLR (RBL Bank)",MCLR_RBL_1Y+Q38,"3M MCLR (YBL)",MCLR_YBL_3M+Q38,"6M I-MCLR (ICICI)",IMCLR_ICICI_6M+Q38,"12M MCLR (SIB)",MCLR_SIB_12M+Q38,"Bajaj Floating Reference Rate (BFRR)",BFRR_Bajaj+Q38,"Term SOFR (USD)",SOFR_3M+Q38,"3M T-Bill",TBill_3M+Q38,"Repo Rate",RepoRate+Q38,"FD rate",IFERROR(FD_Rate_RBL,0)+Q38,Q38),0)} -> 0 | S38: Fixed | T38: 0 | U38: On Settlement | V38: 12 | W38: 0 | X38: 45829 | Y38: =IFERROR(EDATE(X38,T38),"") -> 45829 | Z38: =IFERROR(EDATE(X38,V38),"") -> 46194 | AA38: 45829 | AB38: 46194 | AC38: Hedging exchange risk | AD38: N/A | AE38: SIB Renewal BR/SANC/01/2025-26 dated 21-Jun-2025 | AF38: Notional limit. | AG38: =FALSE() -> FALSE
A39: ★ Sanctioned Debt KPI (Bucket 1 + Bucket 2) | K39: =Bucket1_DebtTotal -> 1320.7
A40: NFB Mains face value (Bucket 2 only — excludes NFB sub of FB-Main) | K40: =IFERROR(SUMIFS(K5:K38,H5:H38,2),0) -> 600
A41: Separate Lines Face Value (Bucket 3) | K41: =IFERROR(SUMIFS(K5:K38,H5:H38,3),0) -> 100
A42: Memo — NFB Contingent KPI (B2 + NFB sub of FB-Main) | K42: =NFBContingent -> 815

Sheet Lender Summary
A1: LENDER SUMMARY — Three-Bucket View
A2: Path B (Optimized): Sanctioned Debt = sum of all FB & NFB main parent facilities. NFB Contingent includes NFB sublimits of FB-Main parents (distinct contingent exposure).
A3: Sanctioned Debt — Bucket 1 (FB Mains) + Bucket 2 (NFB Mains)
A4: Lender | B4: Bucket 1: FB Mains (₹ Cr) | C4: Bucket 2: NFB Mains (₹ Cr) | D4: Sanctioned Debt (₹ Cr) | E4: % of Total
A5: RBL Bank | B5: =SUMIFS('Facility Master'!K:K,'Facility Master'!B:B,"RBL Bank",'Facility Master'!H:H,1) -> 200 | C5: =SUMIFS('Facility Master'!K:K,'Facility Master'!B:B,"RBL Bank",'Facility Master'!H:H,2) -> 100 | D5: =B5+C5 -> 300 | E5: =IFERROR(D5/$D$10,0) -> 0.22715227
A6: YES Bank | B6: =SUMIFS('Facility Master'!K:K,'Facility Master'!B:B,"YES Bank",'Facility Master'!H:H,1) -> 320.7 | C6: =SUMIFS('Facility Master'!K:K,'Facility Master'!B:B,"YES Bank",'Facility Master'!H:H,2) -> 200 | D6: =B6+C6 -> 520.7 | E6: =IFERROR(D6/$D$10,0) -> 0.39426062
A7: Bajaj Finance | B7: =SUMIFS('Facility Master'!K:K,'Facility Master'!B:B,"Bajaj Finance",'Facility Master'!H:H,1) -> 150 | C7: =SUMIFS('Facility Master'!K:K,'Facility Master'!B:B,"Bajaj Finance",'Facility Master'!H:H,2) -> 0 | D7: =B7+C7 -> 150 | E7: =IFERROR(D7/$D$10,0) -> 0.11357613
A8: ICICI Bank | B8: =SUMIFS('Facility Master'!K:K,'Facility Master'!B:B,"ICICI Bank",'Facility Master'!H:H,1) -> 50 | C8: =SUMIFS('Facility Master'!K:K,'Facility Master'!B:B,"ICICI Bank",'Facility Master'!H:H,2) -> 150 | D8: =B8+C8 -> 200 | E8: =IFERROR(D8/$D$10,0) -> 0.15143485
A9: South Indian Bank | B9: =SUMIFS('Facility Master'!K:K,'Facility Master'!B:B,"South Indian Bank",'Facility Master'!H:H,1) -> 0 | C9: =SUMIFS('Facility Master'!K:K,'Facility Master'!B:B,"South Indian Bank",'Facility Master'!H:H,2) -> 150 | D9: =B9+C9 -> 150 | E9: =IFERROR(D9/$D$10,0) -> 0.11357613
A10: Grand Total | B10: =SUM(B5:B9) -> 720.7 | C10: =SUM(C5:C9) -> 600 | D10: =SUM(D5:D9) -> 1320.7 | E10: =IFERROR(D10/D10,1) -> 1
A11: Reconciles to ₹1,320.7 Cr — sum of each lender's binding sanctioned cap (excl FD-backed). Sub-limits → Bucket 0 (excluded).
A13: NFB Contingent Exposure — Off-Balance-Sheet Commitments
A14: Lender | B14: NFB Mains (Bucket 2) | C14: NFB sub of FB-Main* | D14: Total NFB Contingent | E14: % of NFB
A15: RBL Bank | B15: =SUMIFS('Facility Master'!K:K,'Facility Master'!B:B,"RBL Bank",'Facility Master'!H:H,2) -> 100 | C15: =SUMIFS('Facility Master'!K:K,'Facility Master'!B:B,"RBL Bank",'Facility Master'!AG:AG,TRUE(),'Facility Master'!H:H,0) -> 215 | D15: =B15+C15 -> 315 | E15: =IFERROR(D15/$D$20,0) -> 0.38650307
A16: YES Bank | B16: =SUMIFS('Facility Master'!K:K,'Facility Master'!B:B,"YES Bank",'Facility Master'!H:H,2) -> 200 | C16: =SUMIFS('Facility Master'!K:K,'Facility Master'!B:B,"YES Bank",'Facility Master'!AG:AG,TRUE(),'Facility Master'!H:H,0) -> 0 | D16: =B16+C16 -> 200 | E16: =IFERROR(D16/$D$20,0) -> 0.24539877
A17: Bajaj Finance | B17: =SUMIFS('Facility Master'!K:K,'Facility Master'!B:B,"Bajaj Finance",'Facility Master'!H:H,2) -> 0 | C17: =SUMIFS('Facility Master'!K:K,'Facility Master'!B:B,"Bajaj Finance",'Facility Master'!AG:AG,TRUE(),'Facility Master'!H:H,0) -> 0 | D17: =B17+C17 -> 0 | E17: =IFERROR(D17/$D$20,0) -> 0
A18: ICICI Bank | B18: =SUMIFS('Facility Master'!K:K,'Facility Master'!B:B,"ICICI Bank",'Facility Master'!H:H,2) -> 150 | C18: =SUMIFS('Facility Master'!K:K,'Facility Master'!B:B,"ICICI Bank",'Facility Master'!AG:AG,TRUE(),'Facility Master'!H:H,0) -> 0 | D18: =B18+C18 -> 150 | E18: =IFERROR(D18/$D$20,0) -> 0.18404908
A19: South Indian Bank | B19: =SUMIFS('Facility Master'!K:K,'Facility Master'!B:B,"South Indian Bank",'Facility Master'!H:H,2) -> 150 | C19: =SUMIFS('Facility Master'!K:K,'Facility Master'!B:B,"South Indian Bank",'Facility Master'!AG:AG,TRUE(),'Facility Master'!H:H,0) -> 0 | D19: =B19+C19 -> 150 | E19: =IFERROR(D19/$D$20,0) -> 0.18404908
A20: Grand Total | B20: =SUM(B15:B19) -> 600 | C20: =SUM(C15:C19) -> 215 | D20: =SUM(D15:D19) -> 815 | E20: =IFERROR(D20/D20,1) -> 1 | F20: =D20 -> 815
A21: *NFB sub of FB-Main = RBL SBLC for Buyer's Credit ₹190 + RBL Capex LC ₹25, both sub-limits of TL Main ₹200. Counted because they create third-party contingent within FB facility umbrella.
A23: Separate Lines — FD-Backed Facilities Only
A24: Lender | B24: FD-Backed (₹ Cr) | C24: % Share
A25: RBL Bank | B25: =SUMIFS('Facility Master'!K:K,'Facility Master'!B:B,"RBL Bank",'Facility Master'!H:H,3) -> 100 | C25: =IFERROR(B25/$B$30,0) -> 1
A26: YES Bank | B26: =SUMIFS('Facility Master'!K:K,'Facility Master'!B:B,"YES Bank",'Facility Master'!H:H,3) -> 0 | C26: =IFERROR(B26/$B$30,0) -> 0
A27: Bajaj Finance | B27: =SUMIFS('Facility Master'!K:K,'Facility Master'!B:B,"Bajaj Finance",'Facility Master'!H:H,3) -> 0 | C27: =IFERROR(B27/$B$30,0) -> 0
A28: ICICI Bank | B28: =SUMIFS('Facility Master'!K:K,'Facility Master'!B:B,"ICICI Bank",'Facility Master'!H:H,3) -> 0 | C28: =IFERROR(B28/$B$30,0) -> 0
A29: South Indian Bank | B29: =SUMIFS('Facility Master'!K:K,'Facility Master'!B:B,"South Indian Bank",'Facility Master'!H:H,3) -> 0 | C29: =IFERROR(B29/$B$30,0) -> 0
A30: Grand Total | B30: =SUM(B25:B29) -> 100 | C30: =IFERROR(B30/B30,1) -> 1 | D30: =B30 -> 100
A31: Self-collateralised by 100% Fixed Deposit; excluded from RBL ₹300 Cr Overall Borrower cap (per 31-Dec-2025 letter). Hedge notional limits (LER ₹20 + SIB Forward ₹3) shown in Memo below — not credit facilities.
A33: Memo — Hedge Notional Limits (informational; out of all buckets)
A34: Lender | B34: Facility | C34: Notional (₹ Cr) | D34: Purpose
A35: RBL Bank | B35: Loan Equivalent Risk (LER) | C35: 20 | D35: Pre-settlement counterparty exposure on derivatives
A36: South Indian Bank | B36: Forward Contract Limit | C36: 3 | D36: FX hedge notional (per-contract limit)
A37: Total Hedge Notional | C37: =SUM(C35:C36) -> 23
A38: Hedge notional limits are derivative caps, not credit facilities. Do not aggregate with debt or NFB exposures.
A40: METHODOLOGY NOTES
A41: 1. Decision tree (Bucket assignment): (a) Sub-limit of another facility OR shared cap with umbrella → Bucket 0; (b) FD-backed → Bucket 3; (c) FB Main → Bucket 1; (d) NFB Main → Bucket 2.
A42: 2. Sanctioned Debt KPI = B1 + B2 (industry-standard "total credit sanctioned at parent level"). Does NOT add Bucket 3 (FD-backed has different risk profile).
A43: 3. NFB Contingent KPI = Bucket 2 + NFB sub-limits whose parent is a FB Main (S.No 10 RBL SBLC for BC ₹190 + S.No 11 RBL Capex LC ₹25). These create third-party contingent within FB umbrella — distinct off-balance-sheet exposure.

Sheet Working Capital Facilities
A1: WORKING CAPITAL FACILITIES
A2: JCL Debt Model | Fund-Based WC Lines | May 2026
A3: S.No | B3: Lender | C3: Facility | D3: Category | E3: Sub-Limit | F3: Currency | G3: Sanc INR Cr | H3: Effective O/S | I3: Util % | J3: Headroom | K3: Benchmark | L3: Spread | M3: Eff Rate
A4: 3 | B4: =IFERROR('Facility Master'!B7,"") -> RBL Bank | C4: =IFERROR('Facility Master'!C7,"") -> Invoice Discounting (PID) | D4: =IFERROR('Facility Master'!D7,"") -> FB | E4: =IFERROR(IF('Facility Master'!F7,"Sub-limit","Standalone"),"") -> Sub-limit | F4: =IFERROR('Facility Master'!I7,"") -> INR | G4: =IFERROR('Facility Master'!K7,0) -> 100 | H4: =IFERROR('Facility Master'!M7,0) -> 100 | I4: =IFERROR('Facility Master'!N7,0) -> 1 | J4: =IFERROR('Facility Master'!O7,0) -> 0 | K4: =IFERROR('Facility Master'!P7,"") -> 1Y MCLR (RBL Bank) | L4: =IFERROR('Facility Master'!Q7,0) -> 0.005 | M4: =IFERROR('Facility Master'!R7,0) -> 0.095
A5: 5 | B5: =IFERROR('Facility Master'!B9,"") -> RBL Bank | C5: =IFERROR('Facility Master'!C9,"") -> Pre-Acceptance LCBD | D5: =IFERROR('Facility Master'!D9,"") -> FB | E5: =IFERROR(IF('Facility Master'!F9,"Sub-limit","Standalone"),"") -> Sub-limit | F5: =IFERROR('Facility Master'!I9,"") -> INR | G5: =IFERROR('Facility Master'!K9,0) -> 100 | H5: =IFERROR('Facility Master'!M9,0) -> 100 | I5: =IFERROR('Facility Master'!N9,0) -> 1 | J5: =IFERROR('Facility Master'!O9,0) -> 0 | K5: =IFERROR('Facility Master'!P9,"") -> 1Y MCLR (RBL Bank) | L5: =IFERROR('Facility Master'!Q9,0) -> 0.0075 | M5: =IFERROR('Facility Master'!R9,0) -> 0.0975
A6: 6 | B6: =IFERROR('Facility Master'!B10,"") -> RBL Bank | C6: =IFERROR('Facility Master'!C10,"") -> Cash Credit | D6: =IFERROR('Facility Master'!D10,"") -> FB | E6: =IFERROR(IF('Facility Master'!F10,"Sub-limit","Standalone"),"") -> Sub-limit | F6: =IFERROR('Facility Master'!I10,"") -> INR | G6: =IFERROR('Facility Master'!K10,0) -> 100 | H6: =IFERROR('Facility Master'!M10,0) -> 100 | I6: =IFERROR('Facility Master'!N10,0) -> 1 | J6: =IFERROR('Facility Master'!O10,0) -> 0 | K6: =IFERROR('Facility Master'!P10,"") -> 1Y MCLR (RBL Bank) | L6: =IFERROR('Facility Master'!Q10,0) -> 0.0005 | M6: =IFERROR('Facility Master'!R10,0) -> 0.0905
A7: 7 | B7: =IFERROR('Facility Master'!B11,"") -> RBL Bank | C7: =IFERROR('Facility Master'!C11,"") -> Working Capital Demand Loan (WCDL) | D7: =IFERROR('Facility Master'!D11,"") -> FB | E7: =IFERROR(IF('Facility Master'!F11,"Sub-limit","Standalone"),"") -> Sub-limit | F7: =IFERROR('Facility Master'!I11,"") -> INR | G7: =IFERROR('Facility Master'!K11,0) -> 100 | H7: =IFERROR('Facility Master'!M11,0) -> 100 | I7: =IFERROR('Facility Master'!N11,0) -> 1 | J7: =IFERROR('Facility Master'!O11,0) -> 0 | K7: =IFERROR('Facility Master'!P11,"") -> To be decided | L7: =IFERROR('Facility Master'!Q11,0) -> 0 | M7: =IFERROR('Facility Master'!R11,0) -> 0
A8: —— FD-Backed Line (Bucket 3 — Separate Lines, EXCLUDED from WC Sanctioned Debt) ——
A9: 12 | B9: =IFERROR('Facility Master'!B16,"") -> RBL Bank | C9: =IFERROR('Facility Master'!C16,"") -> Overdraft backed by 100% FD (FDOD) | D9: =IFERROR('Facility Master'!D16,"") -> FB-FDbacked | E9: =IFERROR(IF('Facility Master'!F16,"Sub-limit","Standalone"),"") -> Standalone | F9: =IFERROR('Facility Master'!I16,"") -> INR | G9: =IFERROR('Facility Master'!K16,0) -> 100 | H9: =IFERROR('Facility Master'!M16,0) -> 100 | I9: =IFERROR('Facility Master'!N16,0) -> 1 | J9: =IFERROR('Facility Master'!O16,0) -> 0 | K9: =IFERROR('Facility Master'!P16,"") -> FD rate | L9: =IFERROR('Facility Master'!Q16,0) -> 0.0025 | M9: =IFERROR('Facility Master'!R16,0) -> 0.0725
A10: 14 | B10: =IFERROR('Facility Master'!B18,"") -> RBL Bank | C10: =IFERROR('Facility Master'!C18,"") -> Buyer's Credit from GIFT City - WC | D10: =IFERROR('Facility Master'!D18,"") -> FB-FCY | E10: =IFERROR(IF('Facility Master'!F18,"Sub-limit","Standalone"),"") -> Sub-limit | F10: =IFERROR('Facility Master'!I18,"") -> USD | G10: =IFERROR('Facility Master'!K18,0) -> 100 | H10: =IFERROR('Facility Master'!M18,0) -> 100 | I10: =IFERROR('Facility Master'!N18,0) -> 1 | J10: =IFERROR('Facility Master'!O18,0) -> 0 | K10: =IFERROR('Facility Master'!P18,"") -> Term SOFR (USD) | L10: =IFERROR('Facility Master'!Q18,0) -> 0 | M10: =IFERROR('Facility Master'!R18,0) -> 0.043
A11: —— Fund-Based, CAPEX Purpose (included in FB aggregation; CAPEX, not pure WC use) ——
A12: 15 | B12: =IFERROR('Facility Master'!B19,"") -> RBL Bank | C12: =IFERROR('Facility Master'!C19,"") -> Buyer's Credit from GIFT City - CAPEX | D12: =IFERROR('Facility Master'!D19,"") -> FB-FCY | E12: =IFERROR(IF('Facility Master'!F19,"Sub-limit","Standalone"),"") -> Sub-limit | F12: =IFERROR('Facility Master'!I19,"") -> USD | G12: =IFERROR('Facility Master'!K19,0) -> 172 | H12: =IFERROR('Facility Master'!M19,0) -> 172 | I12: =IFERROR('Facility Master'!N19,0) -> 1 | J12: =IFERROR('Facility Master'!O19,0) -> 0 | K12: =IFERROR('Facility Master'!P19,"") -> Term SOFR (USD) | L12: =IFERROR('Facility Master'!Q19,0) -> 0 | M12: =IFERROR('Facility Master'!R19,0) -> 0.043
A13: 16 | B13: =IFERROR('Facility Master'!B20,"") -> YES Bank | C13: =IFERROR('Facility Master'!C20,"") -> Purchase Invoice Financing | D13: =IFERROR('Facility Master'!D20,"") -> FB | E13: =IFERROR(IF('Facility Master'!F20,"Sub-limit","Standalone"),"") -> Sub-limit | F13: =IFERROR('Facility Master'!I20,"") -> INR | G13: =IFERROR('Facility Master'!K20,0) -> 100 | H13: =IFERROR('Facility Master'!M20,0) -> 100 | I13: =IFERROR('Facility Master'!N20,0) -> 1 | J13: =IFERROR('Facility Master'!O20,0) -> 0 | K13: =IFERROR('Facility Master'!P20,"") -> 3M MCLR (YBL) | L13: =IFERROR('Facility Master'!Q20,0) -> 0.005 | M13: =IFERROR('Facility Master'!R20,0) -> 0.095
A14: 17 | B14: =IFERROR('Facility Master'!B21,"") -> YES Bank | C14: =IFERROR('Facility Master'!C21,"") -> Cash Credit | D14: =IFERROR('Facility Master'!D21,"") -> FB | E14: =IFERROR(IF('Facility Master'!F21,"Sub-limit","Standalone"),"") -> Sub-limit | F14: =IFERROR('Facility Master'!I21,"") -> INR | G14: =IFERROR('Facility Master'!K21,0) -> 25 | H14: =IFERROR('Facility Master'!M21,0) -> 25 | I14: =IFERROR('Facility Master'!N21,0) -> 1 | J14: =IFERROR('Facility Master'!O21,0) -> 0 | K14: =IFERROR('Facility Master'!P21,"") -> 3M MCLR (YBL) | L14: =IFERROR('Facility Master'!Q21,0) -> 0.0007 | M14: =IFERROR('Facility Master'!R21,0) -> 0.0907
A15: 20 | B15: =IFERROR('Facility Master'!B24,"") -> YES Bank | C15: =IFERROR('Facility Master'!C24,"") -> Working Capital Demand Loan (WCDL) | D15: =IFERROR('Facility Master'!D24,"") -> FB | E15: =IFERROR(IF('Facility Master'!F24,"Sub-limit","Standalone"),"") -> Sub-limit | F15: =IFERROR('Facility Master'!I24,"") -> INR | G15: =IFERROR('Facility Master'!K24,0) -> 50 | H15: =IFERROR('Facility Master'!M24,0) -> 50 | I15: =IFERROR('Facility Master'!N24,0) -> 1 | J15: =IFERROR('Facility Master'!O24,0) -> 0 | K15: =IFERROR('Facility Master'!P24,"") -> To be decided | L15: =IFERROR('Facility Master'!Q24,0) -> 0 | M15: =IFERROR('Facility Master'!R24,0) -> 0
A16: 23 | B16: =IFERROR('Facility Master'!B27,"") -> ICICI Bank | C16: =IFERROR('Facility Master'!C27,"") -> Cash Credit | D16: =IFERROR('Facility Master'!D27,"") -> FB | E16: =IFERROR(IF('Facility Master'!F27,"Sub-limit","Standalone"),"") -> Standalone | F16: =IFERROR('Facility Master'!I27,"") -> INR | G16: =IFERROR('Facility Master'!K27,0) -> 50 | H16: =IFERROR('Facility Master'!M27,0) -> 50 | I16: =IFERROR('Facility Master'!N27,0) -> 1 | J16: =IFERROR('Facility Master'!O27,0) -> 0 | K16: =IFERROR('Facility Master'!P27,"") -> 6M I-MCLR (ICICI) | L16: =IFERROR('Facility Master'!Q27,0) -> 0.0045 | M16: =IFERROR('Facility Master'!R27,0) -> 0.0875
A17: 24 | B17: =IFERROR('Facility Master'!B28,"") -> ICICI Bank | C17: =IFERROR('Facility Master'!C28,"") -> Working Capital Demand Loan (WCDL) | D17: =IFERROR('Facility Master'!D28,"") -> FB | E17: =IFERROR(IF('Facility Master'!F28,"Sub-limit","Standalone"),"") -> Sub-limit | F17: =IFERROR('Facility Master'!I28,"") -> INR | G17: =IFERROR('Facility Master'!K28,0) -> 50 | H17: =IFERROR('Facility Master'!M28,0) -> 50 | I17: =IFERROR('Facility Master'!N28,0) -> 1 | J17: =IFERROR('Facility Master'!O28,0) -> 0 | K17: =IFERROR('Facility Master'!P28,"") -> Repo Rate | L17: =IFERROR('Facility Master'!Q28,0) -> 0 | M17: =IFERROR('Facility Master'!R28,0) -> 0.0525
A18: 29 | B18: =IFERROR('Facility Master'!B33,"") -> South Indian Bank | C18: =IFERROR('Facility Master'!C33,"") -> CCOL (Cash Credit) | D18: =IFERROR('Facility Master'!D33,"") -> FB | E18: =IFERROR(IF('Facility Master'!F33,"Sub-limit","Standalone"),"") -> Sub-limit | F18: =IFERROR('Facility Master'!I33,"") -> INR | G18: =IFERROR('Facility Master'!K33,0) -> 50 | H18: =IFERROR('Facility Master'!M33,0) -> 50 | I18: =IFERROR('Facility Master'!N33,0) -> 1 | J18: =IFERROR('Facility Master'!O33,0) -> 0 | K18: =IFERROR('Facility Master'!P33,"") -> 12M MCLR (SIB) | L18: =IFERROR('Facility Master'!Q33,0) -> 0.0045 | M18: =IFERROR('Facility Master'!R33,0) -> 0.102
A19: 30 | B19: =IFERROR('Facility Master'!B34,"") -> South Indian Bank | C19: =IFERROR('Facility Master'!C34,"") -> WCL / WCDL | D19: =IFERROR('Facility Master'!D34,"") -> FB | E19: =IFERROR(IF('Facility Master'!F34,"Sub-limit","Standalone"),"") -> Sub-limit | F19: =IFERROR('Facility Master'!I34,"") -> INR | G19: =IFERROR('Facility Master'!K34,0) -> 50 | H19: =IFERROR('Facility Master'!M34,0) -> 50 | I19: =IFERROR('Facility Master'!N34,0) -> 1 | J19: =IFERROR('Facility Master'!O34,0) -> 0 | K19: =IFERROR('Facility Master'!P34,"") -> To be decided | L19: =IFERROR('Facility Master'!Q34,0) -> 0 | M19: =IFERROR('Facility Master'!R34,0) -> 0
A21: Working Capital Summary
A22: Total WC Face Value (incl. FB-FCY and FD-Backed sub-line shown above) | G22: {=IFERROR(SUMPRODUCT((('Facility Master'!D5:D38="FB")+('Facility Master'!D5:D38="FB-FCY")+('Facility Master'!D5:D38="FB-FDbacked"))*'Facility Master'!K5:K38),0)} -> 1147
A23: ★ NFB Mains (Bucket 2 — parent NFB only) (₹ Cr) | G23: =NFBMainsTotal -> 600
A24: Total WC Utilised (Effective Outstanding, Bucket 1 only) | G24: =IFERROR(SUMIFS('Facility Master'!M:M,'Facility Master'!H:H,1)-SUMIFS('Facility Master'!M:M,'Facility Master'!D:D,"FB-Term",'Facility Master'!H:H,1),0) -> 50
A25: WC Headroom (Bucket 1 ex-TL: Sanctioned − Utilised) | G25: =IFERROR(SUMIFS('Facility Master'!K:K,'Facility Master'!H:H,1)-SUMIFS('Facility Master'!K:K,'Facility Master'!D:D,"FB-Term",'Facility Master'!H:H,1)-G24,0) -> 0
A26: Weighted Avg WC Interest Rate (utilisation-weighted) | G26: {=IFERROR(SUMPRODUCT((('Facility Master'!D5:D38="FB")+('Facility Master'!D5:D38="FB-FCY"))*('Facility Master'!H5:H38=1)*'Facility Master'!M5:M38*'Facility Master'!R5:R38)/SUMPRODUCT((('Facility Master'!D5:D38="FB")+('Facility Master'!D5:D38="FB-FCY"))*('Facility Master'!H5:H38=1)*'Facility Master'!M5:M38),0)} -> 0.0875
A27: FD-Backed Lines (Bucket 3, excluded from WC Debt) | G27: =IFERROR(SUMIFS('Facility Master'!K:K,'Facility Master'!G:G,TRUE(),'Facility Master'!H:H,3),0) -> 100

Sheet Term Loans
A1: TERM LOANS
A2: JCL Debt Model | Term Loan Summary | May 2026
A3: Term Loan | B3: RBL Bank | C3: YES Bank | D3: Bajaj Finance | F3: Combined Total
A4: Sanctioned (₹ Cr) | B4: =IFERROR(INDEX('Facility Master'!K:K,MATCH(RBL_TL_SNo,'Facility Master'!A:A,0)),0) -> 200 | C4: =IFERROR(INDEX('Facility Master'!K:K,MATCH(YBL_TL_SNo,'Facility Master'!A:A,0)),0) -> 320.7 | D4: =IFERROR(INDEX('Facility Master'!K:K,MATCH(Bajaj_TL_SNo,'Facility Master'!A:A,0)),0) -> 150 | F4: =B4+C4+D4 -> 670.7
A5: Drawdown Date | B5: =IFERROR(INDEX('Facility Master'!X:X,MATCH(RBL_TL_SNo,'Facility Master'!A:A,0)),"") -> 45315 | C5: =IFERROR(INDEX('Facility Master'!X:X,MATCH(YBL_TL_SNo,'Facility Master'!A:A,0)),"") -> 45642 | D5: =IFERROR(INDEX('Facility Master'!X:X,MATCH(Bajaj_TL_SNo,'Facility Master'!A:A,0)),"") -> 45894
A6: Moratorium (Months) | B6: =IFERROR(INDEX('Facility Master'!T:T,MATCH(RBL_TL_SNo,'Facility Master'!A:A,0)),"") -> 24 | C6: =IFERROR(INDEX('Facility Master'!T:T,MATCH(YBL_TL_SNo,'Facility Master'!A:A,0)),"") -> 0 | D6: =IFERROR(INDEX('Facility Master'!T:T,MATCH(Bajaj_TL_SNo,'Facility Master'!A:A,0)),"") -> 12
A7: Repayment Start | B7: =IFERROR(INDEX('Facility Master'!Y:Y,MATCH(RBL_TL_SNo,'Facility Master'!A:A,0)),"") -> 46046 | C7: =IFERROR(INDEX('Facility Master'!Y:Y,MATCH(YBL_TL_SNo,'Facility Master'!A:A,0)),"") -> 45838 | D7: =IFERROR(INDEX('Facility Master'!Y:Y,MATCH(Bajaj_TL_SNo,'Facility Master'!A:A,0)),"") -> 46361
A8: Maturity Date | B8: =IFERROR(INDEX('Facility Master'!Z:Z,MATCH(RBL_TL_SNo,'Facility Master'!A:A,0)),"") -> 47208 | C8: =IFERROR(INDEX('Facility Master'!Z:Z,MATCH(YBL_TL_SNo,'Facility Master'!A:A,0)),"") -> 49948 | D8: =IFERROR(INDEX('Facility Master'!Z:Z,MATCH(Bajaj_TL_SNo,'Facility Master'!A:A,0)),"") -> 48816
A9: No. of Instalments | B9: =IFERROR(INDEX('Facility Master'!W:W,MATCH(RBL_TL_SNo,'Facility Master'!A:A,0)),"") -> 12 | C9: =IFERROR(INDEX('Facility Master'!W:W,MATCH(YBL_TL_SNo,'Facility Master'!A:A,0)),"") -> 46 | D9: =IFERROR(INDEX('Facility Master'!W:W,MATCH(Bajaj_TL_SNo,'Facility Master'!A:A,0)),"") -> 28
A10: Quarterly Instalment | B10: =IFERROR(INDEX('Facility Master'!K:K,MATCH(RBL_TL_SNo,'Facility Master'!A:A,0))/INDEX('Facility Master'!W:W,MATCH(RBL_TL_SNo,'Facility Master'!A:A,0)),0) -> 16.666667 | C10: ₹6.18–₹9.03 Cr (graduated) | D10: =IFERROR(INDEX('Facility Master'!K:K,MATCH(Bajaj_TL_SNo,'Facility Master'!A:A,0))/INDEX('Facility Master'!W:W,MATCH(Bajaj_TL_SNo,'Facility Master'!A:A,0)),0) -> 5.3571429
A11: Effective Rate p.a. | B11: =IFERROR(INDEX('Facility Master'!R:R,MATCH(RBL_TL_SNo,'Facility Master'!A:A,0)),"") -> 0.0975 | C11: =IFERROR(INDEX('Facility Master'!R:R,MATCH(YBL_TL_SNo,'Facility Master'!A:A,0)),"") -> 0.077 | D11: =IFERROR(INDEX('Facility Master'!R:R,MATCH(Bajaj_TL_SNo,'Facility Master'!A:A,0)),"") -> 0.086
A12: Benchmark | B12: =IFERROR(INDEX('Facility Master'!P:P,MATCH(RBL_TL_SNo,'Facility Master'!A:A,0)),"") -> 1Y MCLR (RBL Bank) | C12: =IFERROR(INDEX('Facility Master'!P:P,MATCH(YBL_TL_SNo,'Facility Master'!A:A,0)),"") -> 3M T-Bill | D12: =IFERROR(INDEX('Facility Master'!P:P,MATCH(Bajaj_TL_SNo,'Facility Master'!A:A,0)),"") -> Bajaj Floating Reference Rate (BFRR)
A13: Spread (bps) | B13: =IFERROR(INDEX('Facility Master'!Q:Q,MATCH(RBL_TL_SNo,'Facility Master'!A:A,0))*10000,0) -> 75 | C13: =IFERROR(INDEX('Facility Master'!Q:Q,MATCH(YBL_TL_SNo,'Facility Master'!A:A,0))*10000,0) -> 252 | D13: =IFERROR(INDEX('Facility Master'!Q:Q,MATCH(Bajaj_TL_SNo,'Facility Master'!A:A,0))*10000,0) -> 10
A14: Currency | B14: =IFERROR(INDEX('Facility Master'!I:I,MATCH(RBL_TL_SNo,'Facility Master'!A:A,0)),"") -> INR | C14: =IFERROR(INDEX('Facility Master'!I:I,MATCH(YBL_TL_SNo,'Facility Master'!A:A,0)),"") -> INR | D14: =IFERROR(INDEX('Facility Master'!I:I,MATCH(Bajaj_TL_SNo,'Facility Master'!A:A,0)),"") -> INR
A16: Total TL Sanctioned | F16: =IFERROR(SUMIFS('Facility Master'!K:K,'Facility Master'!D:D,"FB-Term",'Facility Master'!H:H,1),0) -> 670.7
A17: Total TL Outstanding (as of As-of Date) | B17: =RBL_TL_PrincOS -> 0 | C17: =YBL_TL_PrincOS -> 295.9612 | D17: =Bajaj_TL_PrincOS -> 150 | F17: =Total_TL_PrincOS -> 445.9612
A18: MODEL NOTES
A19: YBL TL Note: 46 graduated quarterly tranches Jun-2025 to Sep-2036 per the YBL Final Repayment Schedule (sanction ₹320.7 Cr; disbursed ₹306.59 Cr; first tranche ₹6.18 Cr Jun-2025; tranches step up across 7 tiers to ₹9.03 Cr; final two stub tranches ₹2.43 / ₹2.39 Cr).
A20: RBL TL Note: Repayment schedule excluded — drawdown pending; existing BC instruments converting to TL by Dec-2026 per 31-Dec-2025 letter. Sanction face ₹200 Cr remains in Sanctioned Debt; quarterly schedule resumes after drawdown.
A21: RBL TL Rate Note: Indicative 9.75% (1Y MCLR of 9.00% + spread of 75 bps). Sanction letter defers actual rate to drawdown. Update Facility Master row corresponding to RBL_TL_SNo (S.No 9) when RBL confirms the rate at drawdown.

Sheet Non-Fund Based Facilities
A1: NON-FUND BASED FACILITIES
A2: JCL Debt Model | Non-Fund Based (NFB) Lines | May 2026
A3: S.No | B3: Lender | C3: Facility | D3: Category | E3: Sub-Limit | F3: Sanc INR Cr | G3: Effective O/S | H3: Util % | I3: Commission % | J3: Annual Commission ₹Cr | K3: Validity | L3: Bucket
A4: 1 | B4: =IFERROR('Facility Master'!B5,"") -> RBL Bank | C4: =IFERROR('Facility Master'!C5,"") -> Letter of Credit - Main Limit | D4: =IFERROR('Facility Master'!D5,"") -> NFB | E4: =IFERROR(IF('Facility Master'!F5,"Sub-limit","Standalone"),"") -> Standalone | F4: =IFERROR('Facility Master'!K5,0) -> 100 | G4: =IFERROR('Facility Master'!M5,0) -> 100 | H4: =IFERROR('Facility Master'!N5,0) -> 1 | I4: =IFERROR('Facility Master'!R5,0) -> 0 | J4: =IFERROR(G4*I4,0) -> 0 | K4: =IFERROR('Facility Master'!AB5,"") -> 46356 | L4: =IFERROR('Facility Master'!H5,0) -> 2
A5: 2 | B5: =IFERROR('Facility Master'!B6,"") -> RBL Bank | C5: =IFERROR('Facility Master'!C6,"") -> Bank Guarantee | D5: =IFERROR('Facility Master'!D6,"") -> NFB | E5: =IFERROR(IF('Facility Master'!F6,"Sub-limit","Standalone"),"") -> Sub-limit | F5: =IFERROR('Facility Master'!K6,0) -> 25 | G5: =IFERROR('Facility Master'!M6,0) -> 25 | H5: =IFERROR('Facility Master'!N6,0) -> 1 | I5: =IFERROR('Facility Master'!R6,0) -> 0 | J5: =IFERROR(G5*I5,0) -> 0 | K5: =IFERROR('Facility Master'!AB6,"") -> 46356 | L5: =IFERROR('Facility Master'!H6,0) -> 0
A6: 4 | B6: =IFERROR('Facility Master'!B8,"") -> RBL Bank | C6: =IFERROR('Facility Master'!C8,"") -> SBLC | D6: =IFERROR('Facility Master'!D8,"") -> NFB | E6: =IFERROR(IF('Facility Master'!F8,"Sub-limit","Standalone"),"") -> Sub-limit | F6: =IFERROR('Facility Master'!K8,0) -> 100 | G6: =IFERROR('Facility Master'!M8,0) -> 100 | H6: =IFERROR('Facility Master'!N8,0) -> 1 | I6: =IFERROR('Facility Master'!R8,0) -> 0.005 | J6: =IFERROR(G6*I6,0) -> 0.5 | K6: =IFERROR('Facility Master'!AB8,"") -> 46356 | L6: =IFERROR('Facility Master'!H8,0) -> 0
A7: 8 | B7: =IFERROR('Facility Master'!B12,"") -> RBL Bank | C7: =IFERROR('Facility Master'!C12,"") -> Loan Equivalent Risk (LER) | D7: =IFERROR('Facility Master'!D12,"") -> Hedge | E7: =IFERROR(IF('Facility Master'!F12,"Sub-limit","Standalone"),"") -> Sub-limit | F7: =IFERROR('Facility Master'!K12,0) -> 20 | G7: =IFERROR('Facility Master'!M12,0) -> 20 | H7: =IFERROR('Facility Master'!N12,0) -> 1 | I7: =IFERROR('Facility Master'!R12,0) -> 0 | J7: =IFERROR(G7*I7,0) -> 0 | K7: =IFERROR('Facility Master'!AB12,"") -> 46356 | L7: =IFERROR('Facility Master'!H12,0) -> 0
A8: 10 | B8: =IFERROR('Facility Master'!B14,"") -> RBL Bank | C8: =IFERROR('Facility Master'!C14,"") -> SBLC for Buyer's Credit (GIFT City) | D8: =IFERROR('Facility Master'!D14,"") -> NFB | E8: =IFERROR(IF('Facility Master'!F14,"Sub-limit","Standalone"),"") -> Sub-limit | F8: =IFERROR('Facility Master'!K14,0) -> 190 | G8: =IFERROR('Facility Master'!M14,0) -> 190 | H8: =IFERROR('Facility Master'!N14,0) -> 1 | I8: =IFERROR('Facility Master'!R14,0) -> 0.005 | J8: =IFERROR(G8*I8,0) -> 0.95 | K8: =IFERROR('Facility Master'!AB14,"") -> 46356 | L8: =IFERROR('Facility Master'!H14,0) -> 0
A9: 11 | B9: =IFERROR('Facility Master'!B15,"") -> RBL Bank | C9: =IFERROR('Facility Master'!C15,"") -> Capex LC | D9: =IFERROR('Facility Master'!D15,"") -> NFB | E9: =IFERROR(IF('Facility Master'!F15,"Sub-limit","Standalone"),"") -> Sub-limit | F9: =IFERROR('Facility Master'!K15,0) -> 25 | G9: =IFERROR('Facility Master'!M15,0) -> 25 | H9: =IFERROR('Facility Master'!N15,0) -> 1 | I9: =IFERROR('Facility Master'!R15,0) -> 0.005 | J9: =IFERROR(G9*I9,0) -> 0.125 | K9: =IFERROR('Facility Master'!AB15,"") -> 46356 | L9: =IFERROR('Facility Master'!H15,0) -> 0
A10: 13 | B10: =IFERROR('Facility Master'!B17,"") -> RBL Bank | C10: =IFERROR('Facility Master'!C17,"") -> LC backed by 100% FD | D10: =IFERROR('Facility Master'!D17,"") -> NFB-FDbacked | E10: =IFERROR(IF('Facility Master'!F17,"Sub-limit","Standalone"),"") -> Sub-limit | F10: =IFERROR('Facility Master'!K17,0) -> 50 | G10: =IFERROR('Facility Master'!M17,0) -> 50 | H10: =IFERROR('Facility Master'!N17,0) -> 1 | I10: =IFERROR('Facility Master'!R17,0) -> 0 | J10: =IFERROR(G10*I10,0) -> 0 | K10: =IFERROR('Facility Master'!AB17,"") -> 46356 | L10: =IFERROR('Facility Master'!H17,0) -> 0
A11: 18 | B11: =IFERROR('Facility Master'!B22,"") -> YES Bank | C11: =IFERROR('Facility Master'!C22,"") -> Letter of Credit | D11: =IFERROR('Facility Master'!D22,"") -> NFB | E11: =IFERROR(IF('Facility Master'!F22,"Sub-limit","Standalone"),"") -> Standalone | F11: =IFERROR('Facility Master'!K22,0) -> 200 | G11: =IFERROR('Facility Master'!M22,0) -> 200 | H11: =IFERROR('Facility Master'!N22,0) -> 1 | I11: =IFERROR('Facility Master'!R22,0) -> 0 | J11: =IFERROR(G11*I11,0) -> 0 | K11: =IFERROR('Facility Master'!AB22,"") -> 46472 | L11: =IFERROR('Facility Master'!H22,0) -> 2
A12: 19 | B12: =IFERROR('Facility Master'!B23,"") -> YES Bank | C12: =IFERROR('Facility Master'!C23,"") -> Financial BG / SBLC | D12: =IFERROR('Facility Master'!D23,"") -> NFB | E12: =IFERROR(IF('Facility Master'!F23,"Sub-limit","Standalone"),"") -> Sub-limit | F12: =IFERROR('Facility Master'!K23,0) -> 200 | G12: =IFERROR('Facility Master'!M23,0) -> 200 | H12: =IFERROR('Facility Master'!N23,0) -> 1 | I12: =IFERROR('Facility Master'!R23,0) -> 0.005 | J12: =IFERROR(G12*I12,0) -> 1 | K12: =IFERROR('Facility Master'!AB23,"") -> 46490 | L12: =IFERROR('Facility Master'!H23,0) -> 0
A13: 25 | B13: =IFERROR('Facility Master'!B29,"") -> ICICI Bank | C13: =IFERROR('Facility Master'!C29,"") -> Letter of Credit (Inland/Foreign) | D13: =IFERROR('Facility Master'!D29,"") -> NFB | E13: =IFERROR(IF('Facility Master'!F29,"Sub-limit","Standalone"),"") -> Standalone | F13: =IFERROR('Facility Master'!K29,0) -> 150 | G13: =IFERROR('Facility Master'!M29,0) -> 150 | H13: =IFERROR('Facility Master'!N29,0) -> 1 | I13: =IFERROR('Facility Master'!R29,0) -> 0.005 | J13: =IFERROR(G13*I13,0) -> 0.75 | K13: =IFERROR('Facility Master'!AB29,"") -> 46268 | L13: =IFERROR('Facility Master'!H29,0) -> 2
A14: 26 | B14: =IFERROR('Facility Master'!B30,"") -> ICICI Bank | C14: =IFERROR('Facility Master'!C30,"") -> SBLC for Buyers' Credit | D14: =IFERROR('Facility Master'!D30,"") -> NFB | E14: =IFERROR(IF('Facility Master'!F30,"Sub-limit","Standalone"),"") -> Sub-limit | F14: =IFERROR('Facility Master'!K30,0) -> 150 | G14: =IFERROR('Facility Master'!M30,0) -> 150 | H14: =IFERROR('Facility Master'!N30,0) -> 1 | I14: =IFERROR('Facility Master'!R30,0) -> 0.005 | J14: =IFERROR(G14*I14,0) -> 0.75 | K14: =IFERROR('Facility Master'!AB30,"") -> 46268 | L14: =IFERROR('Facility Master'!H30,0) -> 0
A15: 27 | B15: =IFERROR('Facility Master'!B31,"") -> ICICI Bank | C15: =IFERROR('Facility Master'!C31,"") -> Bank Guarantee - Performance | D15: =IFERROR('Facility Master'!D31,"") -> NFB | E15: =IFERROR(IF('Facility Master'!F31,"Sub-limit","Standalone"),"") -> Sub-limit | F15: =IFERROR('Facility Master'!K31,0) -> 25 | G15: =IFERROR('Facility Master'!M31,0) -> 25 | H15: =IFERROR('Facility Master'!N31,0) -> 1 | I15: =IFERROR('Facility Master'!R31,0) -> 0.005 | J15: =IFERROR(G15*I15,0) -> 0.125 | K15: =IFERROR('Facility Master'!AB31,"") -> 46268 | L15: =IFERROR('Facility Master'!H31,0) -> 0
A16: 28 | B16: =IFERROR('Facility Master'!B32,"") -> ICICI Bank | C16: =IFERROR('Facility Master'!C32,"") -> Bank Guarantee - Financial | D16: =IFERROR('Facility Master'!D32,"") -> NFB | E16: =IFERROR(IF('Facility Master'!F32,"Sub-limit","Standalone"),"") -> Sub-limit | F16: =IFERROR('Facility Master'!K32,0) -> 5 | G16: =IFERROR('Facility Master'!M32,0) -> 5 | H16: =IFERROR('Facility Master'!N32,0) -> 1 | I16: =IFERROR('Facility Master'!R32,0) -> 0.006 | J16: =IFERROR(G16*I16,0) -> 0.03 | K16: =IFERROR('Facility Master'!AB32,"") -> 46268 | L16: =IFERROR('Facility Master'!H32,0) -> 0
A17: 31 | B17: =IFERROR('Facility Master'!B35,"") -> South Indian Bank | C17: =IFERROR('Facility Master'!C35,"") -> Inland / Import LC | D17: =IFERROR('Facility Master'!D35,"") -> NFB | E17: =IFERROR(IF('Facility Master'!F35,"Sub-limit","Standalone"),"") -> Standalone | F17: =IFERROR('Facility Master'!K35,0) -> 150 | G17: =IFERROR('Facility Master'!M35,0) -> 150 | H17: =IFERROR('Facility Master'!N35,0) -> 1 | I17: =IFERROR('Facility Master'!R35,0) -> 0.0065 | J17: =IFERROR(G17*I17,0) -> 0.975 | K17: =IFERROR('Facility Master'!AB35,"") -> 46194 | L17: =IFERROR('Facility Master'!H35,0) -> 2
A18: 32 | B18: =IFERROR('Facility Master'!B36,"") -> South Indian Bank | C18: =IFERROR('Facility Master'!C36,"") -> Capex LC | D18: =IFERROR('Facility Master'!D36,"") -> NFB | E18: =IFERROR(IF('Facility Master'!F36,"Sub-limit","Standalone"),"") -> Sub-limit | F18: =IFERROR('Facility Master'!K36,0) -> 50 | G18: =IFERROR('Facility Master'!M36,0) -> 50 | H18: =IFERROR('Facility Master'!N36,0) -> 1 | I18: =IFERROR('Facility Master'!R36,0) -> 0.0075 | J18: =IFERROR(G18*I18,0) -> 0.375 | K18: =IFERROR('Facility Master'!AB36,"") -> 46194 | L18: =IFERROR('Facility Master'!H36,0) -> 0
A19: 33 | B19: =IFERROR('Facility Master'!B37,"") -> South Indian Bank | C19: =IFERROR('Facility Master'!C37,"") -> SBLC | D19: =IFERROR('Facility Master'!D37,"") -> NFB | E19: =IFERROR(IF('Facility Master'!F37,"Sub-limit","Standalone"),"") -> Sub-limit | F19: =IFERROR('Facility Master'!K37,0) -> 150 | G19: =IFERROR('Facility Master'!M37,0) -> 150 | H19: =IFERROR('Facility Master'!N37,0) -> 1 | I19: =IFERROR('Facility Master'!R37,0) -> 0.0065 | J19: =IFERROR(G19*I19,0) -> 0.975 | K19: =IFERROR('Facility Master'!AB37,"") -> 46194 | L19: =IFERROR('Facility Master'!H37,0) -> 0
A20: 34 | B20: =IFERROR('Facility Master'!B38,"") -> South Indian Bank | C20: =IFERROR('Facility Master'!C38,"") -> Forward Contract Limit | D20: =IFERROR('Facility Master'!D38,"") -> Hedge | E20: =IFERROR(IF('Facility Master'!F38,"Sub-limit","Standalone"),"") -> Standalone | F20: =IFERROR('Facility Master'!K38,0) -> 3 | G20: =IFERROR('Facility Master'!M38,0) -> 3 | H20: =IFERROR('Facility Master'!N38,0) -> 1 | I20: =IFERROR('Facility Master'!R38,0) -> 0 | J20: =IFERROR(G20*I20,0) -> 0 | K20: =IFERROR('Facility Master'!AB38,"") -> 46194 | L20: =IFERROR('Facility Master'!H38,0) -> 0
A22: NFB Summary
A23: Total NFB Face Value (incl. sub-limits) | F23: {=IFERROR(SUMPRODUCT((('Facility Master'!D5:D38="NFB")+('Facility Master'!D5:D38="NFB-FDbacked")+('Facility Master'!D5:D38="Hedge"))*'Facility Master'!K5:K38),0)} -> 1593
A24: ★ Net NFB Contingent Exposure (Bucket 2 + NFB sub of FB-Main) (₹ Cr) | F24: =NFBContingent -> 815
A25: Hedge / Forward Notional (Memo — Bucket 0; excluded from B1/B2/B3 totals) | F25: =HedgeNotionalTotal -> 23
A26: Annual Commission Run-Rate (Bucket 2) | F26: {=IFERROR(SUMPRODUCT(('Facility Master'!H5:H38=2)*'Facility Master'!M5:M38*'Facility Master'!R5:R38),0)} -> 1.725
A28: NFB Contingent ₹815 Cr = Bucket 2 NFB Mains (₹600) + RBL SBLC for BC ₹190 + RBL Capex LC ₹25 (both sub of TL Main; counted as third-party contingent within FB umbrella).

Sheet Repayment Schedule
A1: REPAYMENT SCHEDULE — Quarterly (Q4 FY24 — Q4 FY37)
D2: Note: RBL TL repayment schedule excluded — drawdown not yet completed (BC instruments converting to TL by Dec-2026 per 31-Dec-2025 letter).
A3: Period | D3: RBL Bank — Term Loan (excluded) | I3: YES Bank — Term Loan | N3: Bajaj Finance — Term Loan | S3: Consolidated
A4: # | B4: Period End | C4: Label | D4: Opening | E4: Drawdown | F4: Prin Rep | G4: Interest | H4: Closing | I4: Opening | J4: Drawdown | K4: Prin Rep | L4: Interest | M4: Closing | N4: Opening | O4: Drawdown | P4: Prin Rep | Q4: Interest | R4: Closing | S4: Total Prin | T4: Total Int | U4: Total DS | V4: Combined O/S
A5: 1 | B5: 45382 | C5: Q4 FY24 | D5: 0 | E5: 0 | F5: 0 | G5: 0 | H5: 0 | I5: =0 -> 0 | J5: =IFERROR(IF(INDEX('Facility Master'!X:X,MATCH(YBL_TL_SNo,'Facility Master'!A:A,0))<=B5,INDEX('Facility Master'!K:K,MATCH(YBL_TL_SNo,'Facility Master'!A:A,0)),0),0) -> 0 | K5: 0 | L5: =IFERROR((I5+J5-K5/2)*INDEX('Facility Master'!R:R,MATCH(YBL_TL_SNo,'Facility Master'!A:A,0))*IF(B5<INDEX('Facility Master'!X:X,MATCH(YBL_TL_SNo,'Facility Master'!A:A,0)),0,IF(I5=0,MAX(0,B5-INDEX('Facility Master'!X:X,MATCH(YBL_TL_SNo,'Facility Master'!A:A,0))),B5-B4))/DaysInYear,0) -> 0 | M5: =IFERROR(ROUND(MAX(I5+J5-K5,0),6),0) -> 0 | N5: =0 -> 0 | O5: =IFERROR(IF(INDEX('Facility Master'!X:X,MATCH(Bajaj_TL_SNo,'Facility Master'!A:A,0))<=B5,INDEX('Facility Master'!K:K,MATCH(Bajaj_TL_SNo,'Facility Master'!A:A,0)),0),0) -> 0 | P5: 0 | Q5: =IFERROR((N5+O5-P5/2)*INDEX('Facility Master'!R:R,MATCH(Bajaj_TL_SNo,'Facility Master'!A:A,0))*IF(B5<INDEX('Facility Master'!X:X,MATCH(Bajaj_TL_SNo,'Facility Master'!A:A,0)),0,IF(N5=0,MAX(0,B5-INDEX('Facility Master'!X:X,MATCH(Bajaj_TL_SNo,'Facility Master'!A:A,0))),B5-B4))/DaysInYear,0) -> 0 | R5: =IFERROR(ROUND(MAX(N5+O5-P5,0),6),0) -> 0 | S5: =K5+P5 -> 0 | T5: =L5+Q5 -> 0 | U5: =S5+T5 -> 0 | V5: =M5+R5 -> 0
A6: 2 | B6: 45473 | C6: Q1 FY25 | D6: 0 | E6: 0 | F6: 0 | G6: 0 | H6: 0 | I6: =IFERROR(MAX(M5,0),0) -> 0 | J6: =IFERROR(IF(AND(INDEX('Facility Master'!X:X,MATCH(YBL_TL_SNo,'Facility Master'!A:A,0))>B5,INDEX('Facility Master'!X:X,MATCH(YBL_TL_SNo,'Facility Master'!A:A,0))<=B6),INDEX('Facility Master'!K:K,MATCH(YBL_TL_SNo,'Facility Master'!A:A,0)),0),0) -> 0 | K6: 0 | L6: =IFERROR((I6+J6-K6/2)*INDEX('Facility Master'!R:R,MATCH(YBL_TL_SNo,'Facility Master'!A:A,0))*IF(B6<INDEX('Facility Master'!X:X,MATCH(YBL_TL_SNo,'Facility Master'!A:A,0)),0,IF(I6=0,MAX(0,B6-INDEX('Facility Master'!X:X,MATCH(YBL_TL_SNo,'Facility Master'!A:A,0))),B6-B5))/DaysInYear,0) -> 0 | M6: =IFERROR(ROUND(MAX(I6+J6-K6,0),6),0) -> 0 | N6: =IFERROR(MAX(R5,0),0) -> 0 | O6: =IFERROR(IF(AND(INDEX('Facility Master'!X:X,MATCH(Bajaj_TL_SNo,'Facility Master'!A:A,0))>B5,INDEX('Facility Master'!X:X,MATCH(Bajaj_TL_SNo,'Facility Master'!A:A,0))<=B6),INDEX('Facility Master'!K:K,MATCH(Bajaj_TL_SNo,'Facility Master'!A:A,0)),0),0) -> 0 | P6: 0 | Q6: =IFERROR((N6+O6-P6/2)*INDEX('Facility Master'!R:R,MATCH(Bajaj_TL_SNo,'Facility Master'!A:A,0))*IF(B6<INDEX('Facility Master'!X:X,MATCH(Bajaj_TL_SNo,'Facility Master'!A:A,0)),0,IF(N6=0,MAX(0,B6-INDEX('Facility Master'!X:X,MATCH(Bajaj_TL_SNo,'Facility Master'!A:A,0))),B6-B5))/DaysInYear,0) -> 0 | R6: =IFERROR(ROUND(MAX(N6+O6-P6,0),6),0) -> 0 | S6: =K6+P6 -> 0 | T6: =L6+Q6 -> 0 | U6: =S6+T6 -> 0 | V6: =M6+R6 -> 0
A7: 3 | B7: 45565 | C7: Q2 FY25 | D7: 0 | E7: 0 | F7: 0 | G7: 0 | H7: 0 | I7: =IFERROR(MAX(M6,0),0) -> 0 | J7: =IFERROR(IF(AND(INDEX('Facility Master'!X:X,MATCH(YBL_TL_SNo,'Facility Master'!A:A,0))>B6,INDEX('Facility Master'!X:X,MATCH(YBL_TL_SNo,'Facility Master'!A:A,0))<=B7),INDEX('Facility Master'!K:K,MATCH(YBL_TL_SNo,'Facility Master'!A:A,0)),0),0) -> 0 | K7: 0 | L7: =IFERROR((I7+J7-K7/2)*INDEX('Facility Master'!R:R,MATCH(YBL_TL_SNo,'Facility Master'!A:A,0))*IF(B7<INDEX('Facility Master'!X:X,MATCH(YBL_TL_SNo,'Facility Master'!A:A,0)),0,IF(I7=0,MAX(0,B7-INDEX('Facility Master'!X:X,MATCH(YBL_TL_SNo,'Facility Master'!A:A,0))),B7-B6))/DaysInYear,0) -> 0 | M7: =IFERROR(ROUND(MAX(I7+J7-K7,0),6),0) -> 0 | N7: =IFERROR(MAX(R6,0),0) -> 0 | O7: =IFERROR(IF(AND(INDEX('Facility Master'!X:X,MATCH(Bajaj_TL_SNo,'Facility Master'!A:A,0))>B6,INDEX('Facility Master'!X:X,MATCH(Bajaj_TL_SNo,'Facility Master'!A:A,0))<=B7),INDEX('Facility Master'!K:K,MATCH(Bajaj_TL_SNo,'Facility Master'!A:A,0)),0),0) -> 0 | P7: 0 | Q7: =IFERROR((N7+O7-P7/2)*INDEX('Facility Master'!R:R,MATCH(Bajaj_TL_SNo,'Facility Master'!A:A,0))*IF(B7<INDEX('Facility Master'!X:X,MATCH(Bajaj_TL_SNo,'Facility Master'!A:A,0)),0,IF(N7=0,MAX(0,B7-INDEX('Facility Master'!X:X,MATCH(Bajaj_TL_SNo,'Facility Master'!A:A,0))),B7-B6))/DaysInYear,0) -> 0 | R7: =IFERROR(ROUND(MAX(N7+O7-P7,0),6),0) -> 0 | S7: =K7+P7 -> 0 | T7: =L7+Q7 -> 0 | U7: =S7+T7 -> 0 | V7: =M7+R7 -> 0
A8: 4 | B8: 45657 | C8: Q3 FY25 | D8: 0 | E8: 0 | F8: 0 | G8: 0 | H8: 0 | I8: =IFERROR(MAX(M7,0),0) -> 0 | J8: =IFERROR(IF(AND(INDEX('Facility Master'!X:X,MATCH(YBL_TL_SNo,'Facility Master'!A:A,0))>B7,INDEX('Facility Master'!X:X,MATCH(YBL_TL_SNo,'Facility Master'!A:A,0))<=B8),INDEX('Facility Master'!K:K,MATCH(YBL_TL_SNo,'Facility Master'!A:A,0)),0),0) -> 320.7 | K8: 0 | L8: =IFERROR((I8+J8-K8/2)*INDEX('Facility Master'!R:R,MATCH(YBL_TL_SNo,'Facility Master'!A:A,0))*IF(B8<INDEX('Facility Master'!X:X,MATCH(YBL_TL_SNo,'Facility Master'!A:A,0)),0,IF(I8=0,MAX(0,B8-INDEX('Facility Master'!X:X,MATCH(YBL_TL_SNo,'Facility Master'!A:A,0))),B8-B7))/DaysInYear,0) -> 1.0148178 | M8: =IFERROR(ROUND(MAX(I8+J8-K8,0),6),0) -> 320.7 | N8: =IFERROR(MAX(R7,0),0) -> 0 | O8: =IFERROR(IF(AND(INDEX('Facility Master'!X:X,MATCH(Bajaj_TL_SNo,'Facility Master'!A:A,0))>B7,INDEX('Facility Master'!X:X,MATCH(Bajaj_TL_SNo,'Facility Master'!A:A,0))<=B8),INDEX('Facility Master'!K:K,MATCH(Bajaj_TL_SNo,'Facility Master'!A:A,0)),0),0) -> 0 | P8: 0 | Q8: =IFERROR((N8+O8-P8/2)*INDEX('Facility Master'!R:R,MATCH(Bajaj_TL_SNo,'Facility Master'!A:A,0))*IF(B8<INDEX('Facility Master'!X:X,MATCH(Bajaj_TL_SNo,'Facility Master'!A:A,0)),0,IF(N8=0,MAX(0,B8-INDEX('Facility Master'!X:X,MATCH(Bajaj_TL_SNo,'Facility Master'!A:A,0))),B8-B7))/DaysInYear,0) -> 0 | R8: =IFERROR(ROUND(MAX(N8+O8-P8,0),6),0) -> 0 | S8: =K8+P8 -> 0 | T8: =L8+Q8 -> 1.0148178 | U8: =S8+T8 -> 1.0148178 | V8: =M8+R8 -> 320.7
A9: 5 | B9: 45747 | C9: Q4 FY25 | D9: 0 | E9: 0 | F9: 0 | G9: 0 | H9: 0 | I9: =IFERROR(MAX(M8,0),0) -> 320.7 | J9: =IFERROR(IF(AND(INDEX('Facility Master'!X:X,MATCH(YBL_TL_SNo,'Facility Master'!A:A,0))>B8,INDEX('Facility Master'!X:X,MATCH(YBL_TL_SNo,'Facility Master'!A:A,0))<=B9),INDEX('Facility Master'!K:K,MATCH(YBL_TL_SNo,'Facility Master'!A:A,0)),0),0) -> 0 | K9: 0 | L9: =IFERROR((I9+J9-K9/2)*INDEX('Facility Master'!R:R,MATCH(YBL_TL_SNo,'Facility Master'!A:A,0))*IF(B9<INDEX('Facility Master'!X:X,MATCH(YBL_TL_SNo,'Facility Master'!A:A,0)),0,IF(I9=0,MAX(0,B9-INDEX('Facility Master'!X:X,MATCH(YBL_TL_SNo,'Facility Master'!A:A,0))),B9-B8))/DaysInYear,0) -> 6.0889068 | M9: =IFERROR(ROUND(MAX(I9+J9-K9,0),6),0) -> 320.7 | N9: =IFERROR(MAX(R8,0),0) -> 0 | O9: =IFERROR(IF(AND(INDEX('Facility Master'!X:X,MATCH(Bajaj_TL_SNo,'Facility Master'!A:A,0))>B8,INDEX('Facility Master'!X:X,MATCH(Bajaj_TL_SNo,'Facility Master'!A:A,0))<=B9),INDEX('Facility Master'!K:K,MATCH(Bajaj_TL_SNo,'Facility Master'!A:A,0)),0),0) -> 0 | P9: 0 | Q9: =IFERROR((N9+O9-P9/2)*INDEX('Facility Master'!R:R,MATCH(Bajaj_TL_SNo,'Facility Master'!A:A,0))*IF(B9<INDEX('Facility Master'!X:X,MATCH(Bajaj_TL_SNo,'Facility Master'!A:A,0)),0,IF(N9=0,MAX(0,B9-INDEX('Facility Master'!X:X,MATCH(Bajaj_TL_SNo,'Facility Master'!A:A,0))),B9-B8))/DaysInYear,0) -> 0 | R9: =IFERROR(ROUND(MAX(N9+O9-P9,0),6),0) -> 0 | S9: =K9+P9 -> 0 | T9: =L9+Q9 -> 6.0889068 | U9: =S9+T9 -> 6.0889068 | V9: =M9+R9 -> 320.7
A10: 6 | B10: 45838 | C10: Q1 FY26 | D10: 0 | E10: 0 | F10: 0 | G10: 0 | H10: 0 | I10: =IFERROR(MAX(M9,0),0) -> 320.7 | J10: =IFERROR(IF(AND(INDEX('Facility Master'!X:X,MATCH(YBL_TL_SNo,'Facility Master'!A:A,0))>B9,INDEX('Facility Master'!X:X,MATCH(YBL_TL_SNo,'Facility Master'!A:A,0))<=B10),INDEX('Facility Master'!K:K,MATCH(YBL_TL_SNo,'Facility Master'!A:A,0)),0),0) -> 0 | K10: 6.1847 | L10: =IFERROR((I10+J10-K10/2)*INDEX('Facility Master'!R:R,MATCH(YBL_TL_SNo,'Facility Master'!A:A,0))*IF(B10<INDEX('Facility Master'!X:X,MATCH(YBL_TL_SNo,'Facility Master'!A:A,0)),0,IF(I10=0,MAX(0,B10-INDEX('Facility Master'!X:X,MATCH(YBL_TL_SNo,'Facility Master'!A:A,0))),B10-B9))/DaysInYear,0) -> 6.0971967 | M10: =IFERROR(ROUND(MAX(I10+J10-K10,0),6),0) -> 314.5153 | N10: =IFERROR(MAX(R9,0),0) -> 0 | O10: =IFERROR(IF(AND(INDEX('Facility Master'!X:X,MATCH(Bajaj_TL_SNo,'Facility Master'!A:A,0))>B9,INDEX('Facility Master'!X:X,MATCH(Bajaj_TL_SNo,'Facility Master'!A:A,0))<=B10),INDEX('Facility Master'!K:K,MATCH(Bajaj_TL_SNo,'Facility Master'!A:A,0)),0),0) -> 0 | P10: 0 | Q10: =IFERROR((N10+O10-P10/2)*INDEX('Facility Master'!R:R,MATCH(Bajaj_TL_SNo,'Facility Master'!A:A,0))*IF(B10<INDEX('Facility Master'!X:X,MATCH(Bajaj_TL_SNo,'Facility Master'!A:A,0)),0,IF(N10=0,MAX(0,B10-INDEX('Facility Master'!X:X,MATCH(Bajaj_TL_SNo,'Facility Master'!A:A,0))),B10-B9))/DaysInYear,0) -> 0 | R10: =IFERROR(ROUND(MAX(N10+O10-P10,0),6),0) -> 0 | S10: =K10+P10 -> 6.1847 | T10: =L10+Q10 -> 6.0971967 | U10: =S10+T10 -> 12.281897 | V10: =M10+R10 -> 314.5153
A11: 7 | B11: 45930 | C11: Q2 FY26 | D11: 0 | E11: 0 | F11: 0 | G11: 0 | H11: 0 | I11: =IFERROR(MAX(M10,0),0) -> 314.5153 | J11: =IFERROR(IF(AND(INDEX('Facility Master'!X:X,MATCH(YBL_TL_SNo,'Facility Master'!A:A,0))>B10,INDEX('Facility Master'!X:X,MATCH(YBL_TL_SNo,'Facility Master'!A:A,0))<=B11),INDEX('Facility Master'!K:K,MATCH(YBL_TL_SNo,'Facility Master'!A:A,0)),0),0) -> 0 | K11: 6.1847 | L11: =IFERROR((I11+J11-K11/2)*INDEX('Facility Master'!R:R,MATCH(YBL_TL_SNo,'Facility Master'!A:A,0))*IF(B11<INDEX('Facility Master'!X:X,MATCH(YBL_TL_SNo,'Facility Master'!A:A,0)),0,IF(I11=0,MAX(0,B11-INDEX('Facility Master'!X:X,MATCH(YBL_TL_SNo,'Facility Master'!A:A,0))),B11-B10))/DaysInYear,0) -> 6.0441649 | M11: =IFERROR(ROUND(MAX(I11+J11-K11,0),6),0) -> 308.3306 | N11: =IFERROR(MAX(R10,0),0) -> 0 | O11: =IFERROR(IF(AND(INDEX('Facility Master'!X:X,MATCH(Bajaj_TL_SNo,'Facility Master'!A:A,0))>B10,INDEX('Facility Master'!X:X,MATCH(Bajaj_TL_SNo,'Facility Master'!A:A,0))<=B11),INDEX('Facility Master'!K:K,MATCH(Bajaj_TL_SNo,'Facility Master'!A:A,0)),0),0) -> 150 | P11: 0 | Q11: =IFERROR((N11+O11-P11/2)*INDEX('Facility Master'!R:R,MATCH(Bajaj_TL_SNo,'Facility Master'!A:A,0))*IF(B11<INDEX('Facility Master'!X:X,MATCH(Bajaj_TL_SNo,'Facility Master'!A:A,0)),0,IF(N11=0,MAX(0,B11-INDEX('Facility Master'!X:X,MATCH(Bajaj_TL_SNo,'Facility Master'!A:A,0))),B11-B10))/DaysInYear,0) -> 1.2723288 | R11: =IFERROR(ROUND(MAX(N11+O11-P11,0),6),0) -> 150 | S11: =K11+P11 -> 6.1847 | T11: =L11+Q11 -> 7.3164936 | U11: =S11+T11 -> 13.501194 | V11: =M11+R11 -> 458.3306
A12: 8 | B12: 46022 | C12: Q3 FY26 | D12: 0 | E12: 0 | F12: 0 | G12: 0 | H12: 0 | I12: =IFERROR(MAX(M11,0),0) -> 308.3306 | J12: =IFERROR(IF(AND(INDEX('Facility Master'!X:X,MATCH(YBL_TL_SNo,'Facility Master'!A:A,0))>B11,INDEX('Facility Master'!X:X,MATCH(YBL_TL_SNo,'Facility Master'!A:A,0))<=B12),INDEX('Facility Master'!K:K,MATCH(YBL_TL_SNo,'Facility Master'!A:A,0)),0),0) -> 0 | K12: 6.1847 | L12: =IFERROR((I12+J12-K12/2)*INDEX('Facility Master'!R:R,MATCH(YBL_TL_SNo,'Facility Master'!A:A,0))*IF(B12<INDEX('Facility Master'!X:X,MATCH(YBL_TL_SNo,'Facility Master'!A:A,0)),0,IF(I12=0,MAX(0,B12-INDEX('Facility Master'!X:X,MATCH(YBL_TL_SNo,'Facility Master'!A:A,0))),B12-B11))/DaysInYear,0) -> 5.9241309 | M12: =IFERROR(ROUND(MAX(I12+J12-K12,0),6),0) -> 302.1459 | N12: =IFERROR(MAX(R11,0),0) -> 150 | O12: =IFERROR(IF(AND(INDEX('Facility Master'!X:X,MATCH(Bajaj_TL_SNo,'Facility Master'!A:A,0))>B11,INDEX('Facility Master'!X:X,MATCH(Bajaj_TL_SNo,'Facility Master'!A:A,0))<=B12),INDEX('Facility Master'!K:K,MATCH(Bajaj_TL_SNo,'Facility Master'!A:A,0)),0),0) -> 0 | P12: 0 | Q12: =IFERROR((N12+O12-P12/2)*INDEX('Facility Master'!R:R,MATCH(Bajaj_TL_SNo,'Facility Master'!A:A,0))*IF(B12<INDEX('Facility Master'!X:X,MATCH(Bajaj_TL_SNo,'Facility Master'!A:A,0)),0,IF(N12=0,MAX(0,B12-INDEX('Facility Master'!X:X,MATCH(Bajaj_TL_SNo,'Facility Master'!A:A,0))),B12-B11))/DaysInYear,0) -> 3.2515068 | R12: =IFERROR(ROUND(MAX(N12+O12-P12,0),6),0) -> 150 | S12: =K12+P12 -> 6.1847 | T12: =L12+Q12 -> 9.1756377 | U12: =S12+T12 -> 15.360338 | V12: =M12+R12 -> 452.1459
A13: 9 | B13: 46112 | C13: Q4 FY26 | D13: 0 | E13: 0 | F13: 0 | G13: 0 | H13: 0 | I13: =IFERROR(MAX(M12,0),0) -> 302.1459 | J13: =IFERROR(IF(AND(INDEX('Facility Master'!X:X,MATCH(YBL_TL_SNo,'Facility Master'!A:A,0))>B12,INDEX('Facility Master'!X:X,MATCH(YBL_TL_SNo,'Facility Master'!A:A,0))<=B13),INDEX('Facility Master'!K:K,MATCH(YBL_TL_SNo,'Facility Master'!A:A,0)),0),0) -> 0 | K13: 6.1847 | L13: =IFERROR((I13+J13-K13/2)*INDEX('Facility Master'!R:R,MATCH(YBL_TL_SNo,'Facility Master'!A:A,0))*IF(B13<INDEX('Facility Master'!X:X,MATCH(YBL_TL_SNo,'Facility Master'!A:A,0)),0,IF(I13=0,MAX(0,B13-INDEX('Facility Master'!X:X,MATCH(YBL_TL_SNo,'Facility Master'!A:A,0))),B13-B12))/DaysInYear,0) -> 5.6779208 | M13: =IFERROR(ROUND(MAX(I13+J13-K13,0),6),0) -> 295.9612 | N13: =IFERROR(MAX(R12,0),0) -> 150 | O13: =IFERROR(IF(AND(INDEX('Facility Master'!X:X,MATCH(Bajaj_TL_SNo,'Facility Master'!A:A,0))>B12,INDEX('Facility Master'!X:X,MATCH(Bajaj_TL_SNo,'Facility Master'!A:A,0))<=B13),INDEX('Facility Master'!K:K,MATCH(Bajaj_TL_SNo,'Facility Master'!A:A,0)),0),0) -> 0 | P13: 0 | Q13: =IFERROR((N13+O13-P13/2)*INDEX('Facility Master'!R:R,MATCH(Bajaj_TL_SNo,'Facility Master'!A:A,0))*IF(B13<INDEX('Facility Master'!X:X,MATCH(Bajaj_TL_SNo,'Facility Master'!A:A,0)),0,IF(N13=0,MAX(0,B13-INDEX('Facility Master'!X:X,MATCH(Bajaj_TL_SNo,'Facility Master'!A:A,0))),B13-B12))/DaysInYear,0) -> 3.1808219 | R13: =IFERROR(ROUND(MAX(N13+O13-P13,0),6),0) -> 150 | S13: =K13+P13 -> 6.1847 | T13: =L13+Q13 -> 8.8587427 | U13: =S13+T13 -> 15.043443 | V13: =M13+R13 -> 445.9612
A14: 10 | B14: 46203 | C14: Q1 FY27 | D14: 0 | E14: 0 | F14: 0 | G14: 0 | H14: 0 | I14: =IFERROR(MAX(M13,0),0) -> 295.9612 | J14: =IFERROR(IF(AND(INDEX('Facility Master'!X:X,MATCH(YBL_TL_SNo,'Facility Master'!A:A,0))>B13,INDEX('Facility Master'!X:X,MATCH(YBL_TL_SNo,'Facility Master'!A:A,0))<=B14),INDEX('Facility Master'!K:K,MATCH(YBL_TL_SNo,'Facility Master'!A:A,0)),0),0) -> 0 | K14: 6.1847 | L14: =IFERROR((I14+J14-K14/2)*INDEX('Facility Master'!R:R,MATCH(YBL_TL_SNo,'Facility Master'!A:A,0))*IF(B14<INDEX('Facility Master'!X:X,MATCH(YBL_TL_SNo,'Facility Master'!A:A,0)),0,IF(I14=0,MAX(0,B14-INDEX('Facility Master'!X:X,MATCH(YBL_TL_SNo,'Facility Master'!A:A,0))),B14-B13))/DaysInYear,0) -> 5.6222795 | M14: =IFERROR(ROUND(MAX(I14+J14-K14,0),6),0) -> 289.7765 | N14: =IFERROR(MAX(R13,0),0) -> 150 | O14: =IFERROR(IF(AND(INDEX('Facility Master'!X:X,MATCH(Bajaj_TL_SNo,'Facility Master'!A:A,0))>B13,INDEX('Facility Master'!X:X,MATCH(Bajaj_TL_SNo,'Facility Master'!A:A,0))<=B14),INDEX('Facility Master'!K:K,MATCH(Bajaj_TL_SNo,'Facility Master'!A:A,0)),0),0) -> 0 | P14: 0 | Q14: =IFERROR((N14+O14-P14/2)*INDEX('Facility Master'!R:R,MATCH(Bajaj_TL_SNo,'Facility Master'!A:A,0))*IF(B14<INDEX('Facility Master'!X:X,MATCH(Bajaj_TL_SNo,'Facility Master'!A:A,0)),0,IF(N14=0,MAX(0,B14-INDEX('Facility Master'!X:X,MATCH(Bajaj_TL_SNo,'Facility Master'!A:A,0))),B14-B13))/DaysInYear,0) -> 3.2161644 | R14: =IFERROR(ROUND(MAX(N14+O14-P14,0),6),0) -> 150 | S14: =K14+P14 -> 6.1847 | T14: =L14+Q14 -> 8.8384439 | U14: =S14+T14 -> 15.023144 | V14: =M14+R14 -> 439.7765
A15: 11 | B15: 46295 | C15: Q2 FY27 | D15: 0 | E15: 0 | F15: 0 | G15: 0 | H15: 0 | I15: =IFERROR(MAX(M14,0),0) -> 289.7765 | J15: =IFERROR(IF(AND(INDEX('Facility Master'!X:X,MATCH(YBL_TL_SNo,'Facility Master'!A:A,0))>B14,INDEX('Facility Master'!X:X,MATCH(YBL_TL_SNo,'Facility Master'!A:A,0))<=B15),INDEX('Facility Master'!K:K,MATCH(YBL_TL_SNo,'Facility Master'!A:A,0)),0),0) -> 0 | K15: 6.1847 | L15: =IFERROR((I15+J15-K15/2)*INDEX('Facility Master'!R:R,MATCH(YBL_TL_SNo,'Facility Master'!A:A,0))*IF(B15<INDEX('Facility Master'!X:X,MATCH(YBL_TL_SNo,'Facility Master'!A:A,0)),0,IF(I15=0,MAX(0,B15-INDEX('Facility Master'!X:X,MATCH(YBL_TL_SNo,'Facility Master'!A:A,0))),B15-B14))/DaysInYear,0) -> 5.5640288 | M15: =IFERROR(ROUND(MAX(I15+J15-K15,0),6),0) -> 283.5918 | N15: =IFERROR(MAX(R14,0),0) -> 150 | O15: =IFERROR(IF(AND(INDEX('Facility Master'!X:X,MATCH(Bajaj_TL_SNo,'Facility Master'!A:A,0))>B14,INDEX('Facility Master'!X:X,MATCH(Bajaj_TL_SNo,'Facility Master'!A:A,0))<=B15),INDEX('Facility Master'!K:K,MATCH(Bajaj_TL_SNo,'Facility Master'!A:A,0)),0),0) -> 0 | P15: 0 | Q15: =IFERROR((N15+O15-P15/2)*INDEX('Facility Master'!R:R,MATCH(Bajaj_TL_SNo,'Facility Master'!A:A,0))*IF(B15<INDEX('Facility Master'!X:X,MATCH(Bajaj_TL_SNo,'Facility Master'!A:A,0)),0,IF(N15=0,MAX(0,B15-INDEX('Facility Master'!X:X,MATCH(Bajaj_TL_SNo,'Facility Master'!A:A,0))),B15-B14))/DaysInYear,0) -> 3.2515068 | R15: =IFERROR(ROUND(MAX(N15+O15-P15,0),6),0) -> 150 | S15: =K15+P15 -> 6.1847 | T15: =L15+Q15 -> 8.8155357 | U15: =S15+T15 -> 15.000236 | V15: =M15+R15 -> 433.5918
A16: 12 | B16: 46387 | C16: Q3 FY27 | D16: 0 | E16: 0 | F16: 0 | G16: 0 | H16: 0 | I16: =IFERROR(MAX(M15,0),0) -> 283.5918 | J16: =IFERROR(IF(AND(INDEX('Facility Master'!X:X,MATCH(YBL_TL_SNo,'Facility Master'!A:A,0))>B15,INDEX('Facility Master'!X:X,MATCH(YBL_TL_SNo,'Facility Master'!A:A,0))<=B16),INDEX('Facility Master'!K:K,MATCH(YBL_TL_SNo,'Facility Master'!A:A,0)),0),0) -> 0 | K16: 6.1847 | L16: =IFERROR((I16+J16-K16/2)*INDEX('Facility Master'!R:R,MATCH(YBL_TL_SNo,'Facility Master'!A:A,0))*IF(B16<INDEX('Facility Master'!X:X,MATCH(YBL_TL_SNo,'Facility Master'!A:A,0)),0,IF(I16=0,MAX(0,B16-INDEX('Facility Master'!X:X,MATCH(YBL_TL_SNo,'Facility Master'!A:A,0))),B16-B15))/DaysInYear,0) -> 5.4439948 | M16: =IFERROR(ROUND(MAX(I16+J16-K16,0),6),0) -> 277.4071 | N16: =IFERROR(MAX(R15,0),0) -> 150 | O16: =IFERROR(IF(AND(INDEX('Facility Master'!X:X,MATCH(Bajaj_TL_SNo,'Facility Master'!A:A,0))>B15,INDEX('Facility Master'!X:X,MATCH(Bajaj_TL_SNo,'Facility Master'!A:A,0))<=B16),INDEX('Facility Master'!K:K,MATCH(Bajaj_TL_SNo,'Facility Master'!A:A,0)),0),0) -> 0 | P16: 5.3571429 | Q16: =IFERROR((N16+O16-P16/2)*INDEX('Facility Master'!R:R,MATCH(Bajaj_TL_SNo,'Facility Master'!A:A,0))*IF(B16<INDEX('Facility Master'!X:X,MATCH(Bajaj_TL_SNo,'Facility Master'!A:A,0)),0,IF(N16=0,MAX(0,B16-INDEX('Facility Master'!X:X,MATCH(Bajaj_TL_SNo,'Facility Master'!A:A,0))),B16-B15))/DaysInYear,0) -> 3.1934442 | R16: =IFERROR(ROUND(MAX(N16+O16-P16,0),6),0) -> 144.64286 | S16: =K16+P16 -> 11.541843 | T16: =L16+Q16 -> 8.637439 | U16: =S16+T16 -> 20.179282 | V16: =M16+R16 -> 422.04996
A17: 13 | B17: 46477 | C17: Q4 FY27 | D17: 0 | E17: 0 | F17: 0 | G17: 0 | H17: 0 | I17: =IFERROR(MAX(M16,0),0) -> 277.4071 | J17: =IFERROR(IF(AND(INDEX('Facility Master'!X:X,MATCH(YBL_TL_SNo,'Facility Master'!A:A,0))>B16,INDEX('Facility Master'!X:X,MATCH(YBL_TL_SNo,'Facility Master'!A:A,0))<=B17),INDEX('Facility Master'!K:K,MATCH(YBL_TL_SNo,'Facility Master'!A:A,0)),0),0) -> 0 | K17: 6.1847 | L17: =IFERROR((I17+J17-K17/2)*INDEX('Facility Master'!R:R,MATCH(YBL_TL_SNo,'Facility Master'!A:A,0))*IF(B17<INDEX('Facility Master'!X:X,MATCH(YBL_TL_SNo,'Facility Master'!A:A,0)),0,IF(I17=0,MAX(0,B17-INDEX('Facility Master'!X:X,MATCH(YBL_TL_SNo,'Facility Master'!A:A,0))),B17-B16))/DaysInYear,0) -> 5.2082225 | M17: =IFERROR(ROUND(MAX(I17+J17-K17,0),6),0) -> 271.2224 | N17: =IFERROR(MAX(R16,0),0) -> 144.64286 | O17: =IFERROR(IF(AND(INDEX('Facility Master'!X:X,MATCH(Bajaj_TL_SNo,'Facility Master'!A:A,0))>B16,INDEX('Facility Master'!X:X,MATCH(Bajaj_TL_SNo,'Facility Master'!A:A,0))<=B17),INDEX('Facility Master'!K:K,MATCH(Bajaj_TL_SNo,'Facility Master'!A:A,0)),0),0) -> 0 | P17: 5.3571429 | Q17: =IFERROR((N17+O17-P17/2)*INDEX('Facility Master'!R:R,MATCH(Bajaj_TL_SNo,'Facility Master'!A:A,0))*IF(B17<INDEX('Facility Master'!X:X,MATCH(Bajaj_TL_SNo,'Facility Master'!A:A,0)),0,IF(N17=0,MAX(0,B17-INDEX('Facility Master'!X:X,MATCH(Bajaj_TL_SNo,'Facility Master'!A:A,0))),B17-B16))/DaysInYear,0) -> 3.0104207 | R17: =IFERROR(ROUND(MAX(N17+O17-P17,0),6),0) -> 139.28571 | S17: =K17+P17 -> 11.541843 | T17: =L17+Q17 -> 8.2186433 | U17: =S17+T17 -> 19.760486 | V17: =M17+R17 -> 410.50811
... A57: 53 | B57: 50130 | C57: Q4 FY37 | D57: 0 | E57: 0 | F57: 0 | G57: 0 | H57: 0 | I57: =IFERROR(MAX(M56,0),0) -> 0 | J57: =IFERROR(IF(AND(INDEX('Facility Master'!X:X,MATCH(YBL_TL_SNo,'Facility Master'!A:A,0))>B56,INDEX('Facility Master'!X:X,MATCH(YBL_TL_SNo,'Facility Master'!A:A,0))<=B57),INDEX('Facility Master'!K:K,MATCH(YBL_TL_SNo,'Facility Master'!A:A,0)),0),0) -> 0 | K57: 0 | L57: =IFERROR((I57+J57-K57/2)*INDEX('Facility Master'!R:R,MATCH(YBL_TL_SNo,'Facility Master'!A:A,0))*IF(B57<INDEX('Facility Master'!X:X,MATCH(YBL_TL_SNo,'Facility Master'!A:A,0)),0,IF(I57=0,MAX(0,B57-INDEX('Facility Master'!X:X,MATCH(YBL_TL_SNo,'Facility Master'!A:A,0))),B57-B56))/DaysInYear,0) -> 0 | M57: =IFERROR(ROUND(MAX(I57+J57-K57,0),6),0) -> 0 | N57: =IFERROR(MAX(R56,0),0) -> 0 | O57: =IFERROR(IF(AND(INDEX('Facility Master'!X:X,MATCH(Bajaj_TL_SNo,'Facility Master'!A:A,0))>B56,INDEX('Facility Master'!X:X,MATCH(Bajaj_TL_SNo,'Facility Master'!A:A,0))<=B57),INDEX('Facility Master'!K:K,MATCH(Bajaj_TL_SNo,'Facility Master'!A:A,0)),0),0) -> 0 | P57: 0 | Q57: =IFERROR((N57+O57-P57/2)*INDEX('Facility Master'!R:R,MATCH(Bajaj_TL_SNo,'Facility Master'!A:A,0))*IF(B57<INDEX('Facility Master'!X:X,MATCH(Bajaj_TL_SNo,'Facility Master'!A:A,0)),0,IF(N57=0,MAX(0,B57-INDEX('Facility Master'!X:X,MATCH(Bajaj_TL_SNo,'Facility Master'!A:A,0))),B57-B56))/DaysInYear,0) -> 0 | R57: =IFERROR(ROUND(MAX(N57+O57-P57,0),6),0) -> 0 | S57: =K57+P57 -> 0 | T57: =L57+Q57 -> 0 | U57: =S57+T57 -> 0 | V57: =M57+R57 -> 0
A59: TL KPIs (cumulative through As-of Date)
A60: Lender | B60: Sanctioned | C60: Principal Repaid | D60: Principal Outstanding | E60: Interest Paid | F60: Effective Rate
A61: RBL Bank (excluded) | B61: 0 | C61: 0 | D61: 0 | E61: 0 | F61: 0
A62: YES Bank | B62: =IFERROR(INDEX('Facility Master'!K:K,MATCH(YBL_TL_SNo,'Facility Master'!A:A,0)),0) -> 320.7 | C62: =IFERROR(SUMIFS(K5:K57,B5:B57,"<="&AsOfDate),0) -> 24.7388 | D62: =B62-C62 -> 295.9612 | E62: =IFERROR(SUMIFS(L5:L57,B5:B57,"<="&AsOfDate),0) -> 30.847138 | F62: =IFERROR(INDEX('Facility Master'!R:R,MATCH(YBL_TL_SNo,'Facility Master'!A:A,0)),0) -> 0.077
A63: Bajaj Finance | B63: =IFERROR(INDEX('Facility Master'!K:K,MATCH(Bajaj_TL_SNo,'Facility Master'!A:A,0)),0) -> 150 | C63: =IFERROR(SUMIFS(P5:P57,B5:B57,"<="&AsOfDate),0) -> 0 | D63: =B63-C63 -> 150 | E63: =IFERROR(SUMIFS(Q5:Q57,B5:B57,"<="&AsOfDate),0) -> 7.7046575 | F63: =IFERROR(INDEX('Facility Master'!R:R,MATCH(Bajaj_TL_SNo,'Facility Master'!A:A,0)),0) -> 0.086
A64: Total | B64: =SUM(B61:B63) -> 470.7 | C64: =SUM(C61:C63) -> 24.7388 | D64: =SUM(D61:D63) -> 445.9612 | E64: =SUM(E61:E63) -> 38.551795
B246: GRAND TOTAL | E246: =SUM(E193:E245) -> 0 | F246: =SUM(F193:F245) -> 0 | G246: =SUM(G193:G245) -> 0

Sheet Interest Schedule
A1: INTEREST & COMMISSION SCHEDULE
A2: JCL Debt Model | Interest & Commission Run-Rate | May 2026
A3: S.No | B3: Lender | C3: Facility | D3: Category | E3: Bucket | F3: Sanc INR Cr | G3: Eff O/S | H3: Eff Rate | I3: Annual Interest/Comm. ₹Cr | J3: Currency | K3: Remarks
A4: 1 | B4: =IFERROR('Facility Master'!B5,"") -> RBL Bank | C4: =IFERROR('Facility Master'!C5,"") -> Letter of Credit - Main Limit | D4: =IFERROR('Facility Master'!D5,"") -> NFB | E4: =IFERROR('Facility Master'!H5,0) -> 2 | F4: =IFERROR('Facility Master'!K5,0) -> 100 | G4: =IFERROR('Facility Master'!M5,0) -> 100 | H4: =IFERROR('Facility Master'!R5,0) -> 0 | I4: =IFERROR(G4*H4,0) -> 0 | J4: =IFERROR('Facility Master'!I5,"") -> INR | K4: =IFERROR('Facility Master'!AF5,"") -> Pricing 0.45% effective 31-Dec-2025.
A5: 2 | B5: =IFERROR('Facility Master'!B6,"") -> RBL Bank | C5: =IFERROR('Facility Master'!C6,"") -> Bank Guarantee | D5: =IFERROR('Facility Master'!D6,"") -> NFB | E5: =IFERROR('Facility Master'!H6,0) -> 0 | F5: =IFERROR('Facility Master'!K6,0) -> 25 | G5: =IFERROR('Facility Master'!M6,0) -> 25 | H5: =IFERROR('Facility Master'!R6,0) -> 0 | I5: =IFERROR(G5*H5,0) -> 0 | J5: =IFERROR('Facility Master'!I6,"") -> INR | K5: =IFERROR('Facility Master'!AF6,"") -> BG commission 0.50% per 28-Feb-2025 pricing table.
A6: 3 | B6: =IFERROR('Facility Master'!B7,"") -> RBL Bank | C6: =IFERROR('Facility Master'!C7,"") -> Invoice Discounting (PID) | D6: =IFERROR('Facility Master'!D7,"") -> FB | E6: =IFERROR('Facility Master'!H7,0) -> 0 | F6: =IFERROR('Facility Master'!K7,0) -> 100 | G6: =IFERROR('Facility Master'!M7,0) -> 100 | H6: =IFERROR('Facility Master'!R7,0) -> 0.095 | I6: =IFERROR(G6*H6,0) -> 9.5 | J6: =IFERROR('Facility Master'!I7,"") -> INR | K6: =IFERROR('Facility Master'!AF7,"") -> Rate set at availment. Spread of 50 bps over 1Y MCLR is illustrative; rate confirmed at each availment per sanction letter.
A7: 4 | B7: =IFERROR('Facility Master'!B8,"") -> RBL Bank | C7: =IFERROR('Facility Master'!C8,"") -> SBLC | D7: =IFERROR('Facility Master'!D8,"") -> NFB | E7: =IFERROR('Facility Master'!H8,0) -> 0 | F7: =IFERROR('Facility Master'!K8,0) -> 100 | G7: =IFERROR('Facility Master'!M8,0) -> 100 | H7: =IFERROR('Facility Master'!R8,0) -> 0.005 | I7: =IFERROR(G7*H7,0) -> 0.5 | J7: =IFERROR('Facility Master'!I8,"") -> INR | K7: =IFERROR('Facility Master'!AF8,"") -> Sub-limit of LC (Main).
A8: 5 | B8: =IFERROR('Facility Master'!B9,"") -> RBL Bank | C8: =IFERROR('Facility Master'!C9,"") -> Pre-Acceptance LCBD | D8: =IFERROR('Facility Master'!D9,"") -> FB | E8: =IFERROR('Facility Master'!H9,0) -> 0 | F8: =IFERROR('Facility Master'!K9,0) -> 100 | G8: =IFERROR('Facility Master'!M9,0) -> 100 | H8: =IFERROR('Facility Master'!R9,0) -> 0.0975 | I8: =IFERROR(G8*H8,0) -> 9.75 | J8: =IFERROR('Facility Master'!I9,"") -> INR | K8: =IFERROR('Facility Master'!AF9,"") -> Rate set at availment. Spread of 75 bps over 1Y MCLR is illustrative; rate confirmed at each availment per sanction letter.
A9: 6 | B9: =IFERROR('Facility Master'!B10,"") -> RBL Bank | C9: =IFERROR('Facility Master'!C10,"") -> Cash Credit | D9: =IFERROR('Facility Master'!D10,"") -> FB | E9: =IFERROR('Facility Master'!H10,0) -> 0 | F9: =IFERROR('Facility Master'!K10,0) -> 100 | G9: =IFERROR('Facility Master'!M10,0) -> 100 | H9: =IFERROR('Facility Master'!R10,0) -> 0.0905 | I9: =IFERROR(G9*H9,0) -> 9.05 | J9: =IFERROR('Facility Master'!I10,"") -> INR | K9: =IFERROR('Facility Master'!AF10,"") -> 1Y MCLR + 5 bps.
A10: 7 | B10: =IFERROR('Facility Master'!B11,"") -> RBL Bank | C10: =IFERROR('Facility Master'!C11,"") -> Working Capital Demand Loan (WCDL) | D10: =IFERROR('Facility Master'!D11,"") -> FB | E10: =IFERROR('Facility Master'!H11,0) -> 0 | F10: =IFERROR('Facility Master'!K11,0) -> 100 | G10: =IFERROR('Facility Master'!M11,0) -> 100 | H10: =IFERROR('Facility Master'!R11,0) -> 0 | I10: =IFERROR(G10*H10,0) -> 0 | J10: =IFERROR('Facility Master'!I11,"") -> INR | K10: =IFERROR('Facility Master'!AF11,"") -> Rate set at drawdown.
A11: 8 | B11: =IFERROR('Facility Master'!B12,"") -> RBL Bank | C11: =IFERROR('Facility Master'!C12,"") -> Loan Equivalent Risk (LER) | D11: =IFERROR('Facility Master'!D12,"") -> Hedge | E11: =IFERROR('Facility Master'!H12,0) -> 0 | F11: =IFERROR('Facility Master'!K12,0) -> 20 | G11: =IFERROR('Facility Master'!M12,0) -> 20 | H11: =IFERROR('Facility Master'!R12,0) -> 0 | I11: =IFERROR(G11*H11,0) -> 0 | J11: =IFERROR('Facility Master'!I12,"") -> INR | K11: =IFERROR('Facility Master'!AF12,"") -> Notional limit; 75% MTM trigger.
A12: 9 | B12: =IFERROR('Facility Master'!B13,"") -> RBL Bank | C12: =IFERROR('Facility Master'!C13,"") -> Term Loan | D12: =IFERROR('Facility Master'!D13,"") -> FB-Term | E12: =IFERROR('Facility Master'!H13,0) -> 1 | F12: =IFERROR('Facility Master'!K13,0) -> 200 | G12: =IFERROR('Facility Master'!M13,0) -> 0 | H12: =IFERROR('Facility Master'!R13,0) -> 0.0975 | I12: =IFERROR(G12*H12,0) -> 0 | J12: =IFERROR('Facility Master'!I13,"") -> INR | K12: =IFERROR('Facility Master'!AF13,"") -> Indicative 9.75% (1Y MCLR + 75 bps); confirm with RBL at drawdown.
A13: 10 | B13: =IFERROR('Facility Master'!B14,"") -> RBL Bank | C13: =IFERROR('Facility Master'!C14,"") -> SBLC for Buyer's Credit (GIFT City) | D13: =IFERROR('Facility Master'!D14,"") -> NFB | E13: =IFERROR('Facility Master'!H14,0) -> 0 | F13: =IFERROR('Facility Master'!K14,0) -> 190 | G13: =IFERROR('Facility Master'!M14,0) -> 190 | H13: =IFERROR('Facility Master'!R14,0) -> 0.005 | I13: =IFERROR(G13*H13,0) -> 0.95 | J13: =IFERROR('Facility Master'!I14,"") -> INR | K13: =IFERROR('Facility Master'!AF14,"") -> Limit increased 172 → 190 Cr on 31-Dec-2025.
A14: 11 | B14: =IFERROR('Facility Master'!B15,"") -> RBL Bank | C14: =IFERROR('Facility Master'!C15,"") -> Capex LC | D14: =IFERROR('Facility Master'!D15,"") -> NFB | E14: =IFERROR('Facility Master'!H15,0) -> 0 | F14: =IFERROR('Facility Master'!K15,0) -> 25 | G14: =IFERROR('Facility Master'!M15,0) -> 25 | H14: =IFERROR('Facility Master'!R15,0) -> 0.005 | I14: =IFERROR(G14*H14,0) -> 0.125 | J14: =IFERROR('Facility Master'!I15,"") -> INR | K14: =IFERROR('Facility Master'!AF15,"") -> Originally 24-Jan-2024; converted revolving 28-Feb-2025.
A15: 12 | B15: =IFERROR('Facility Master'!B16,"") -> RBL Bank | C15: =IFERROR('Facility Master'!C16,"") -> Overdraft backed by 100% FD (FDOD) | D15: =IFERROR('Facility Master'!D16,"") -> FB-FDbacked | E15: =IFERROR('Facility Master'!H16,0) -> 3 | F15: =IFERROR('Facility Master'!K16,0) -> 100 | G15: =IFERROR('Facility Master'!M16,0) -> 100 | H15: =IFERROR('Facility Master'!R16,0) -> 0.0725 | I15: =IFERROR(G15*H15,0) -> 7.25 | J15: =IFERROR('Facility Master'!I16,"") -> INR | K15: =IFERROR('Facility Master'!AF16,"") -> Excluded from INR 300 Cr overall cap.
... A23: 20 | B23: =IFERROR('Facility Master'!B24,"") -> YES Bank | C23: =IFERROR('Facility Master'!C24,"") -> Working Capital Demand Loan (WCDL) | D23: =IFERROR('Facility Master'!D24,"") -> FB | E23: =IFERROR('Facility Master'!H24,0) -> 0 | F23: =IFERROR('Facility Master'!K24,0) -> 50 | G23: =IFERROR('Facility Master'!M24,0) -> 50 | H23: =IFERROR('Facility Master'!R24,0) -> 0 | I23: =IFERROR(G23*H23,0) -> 0 | J23: =IFERROR('Facility Master'!I24,"") -> INR | K23: =IFERROR('Facility Master'!AF24,"") -> Min utilisation covenant: 40% of YBL limits.
A24: 21 | B24: =IFERROR('Facility Master'!B25,"") -> YES Bank | C24: =IFERROR('Facility Master'!C25,"") -> Term Loan (Refinance Canara) | D24: =IFERROR('Facility Master'!D25,"") -> FB-Term | E24: =IFERROR('Facility Master'!H25,0) -> 1 | F24: =IFERROR('Facility Master'!K25,0) -> 320.7 | G24: =IFERROR('Facility Master'!M25,0) -> 295.9612 | H24: =IFERROR('Facility Master'!R25,0) -> 0.077 | I24: =IFERROR(G24*H24,0) -> 22.789012 | J24: =IFERROR('Facility Master'!I25,"") -> INR | K24: 46 graduated quarterly tranches Jun-2025 to Sep-2036 per actual YBL Final Repayment Schedule (sanction ₹320.7 Cr; ₹295.96 Cr O/S as of 31-Mar-2026).
A25: 22 | B25: =IFERROR('Facility Master'!B26,"") -> Bajaj Finance | C25: =IFERROR('Facility Master'!C26,"") -> Term Loan | D25: =IFERROR('Facility Master'!D26,"") -> FB-Term | E25: =IFERROR('Facility Master'!H26,0) -> 1 | F25: =IFERROR('Facility Master'!K26,0) -> 150 | G25: =IFERROR('Facility Master'!M26,0) -> 150 | H25: =IFERROR('Facility Master'!R26,0) -> 0.086 | I25: =IFERROR(G25*H25,0) -> 12.9 | J25: =IFERROR('Facility Master'!I26,"") -> INR | K25: Drawdown 25-Aug-2025 ₹150 Cr; 96 monthly EMIs (interest monthly, principal quarterly); 28 equal quarterly principal tranches of ₹5.357 Cr from Dec-2026 to Sep-2033; rate 8.6% (BFRR 8.5% + 10 bps).
A26: 23 | B26: =IFERROR('Facility Master'!B27,"") -> ICICI Bank | C26: =IFERROR('Facility Master'!C27,"") -> Cash Credit | D26: =IFERROR('Facility Master'!D27,"") -> FB | E26: =IFERROR('Facility Master'!H27,0) -> 1 | F26: =IFERROR('Facility Master'!K27,0) -> 50 | G26: =IFERROR('Facility Master'!M27,0) -> 50 | H26: =IFERROR('Facility Master'!R27,0) -> 0.0875 | I26: =IFERROR(G26*H26,0) -> 4.375 | J26: =IFERROR('Facility Master'!I27,"") -> INR | K26: =IFERROR('Facility Master'!AF27,"") -> Reset 6 monthly; one-way interchangeability CC→LC.
A27: 24 | B27: =IFERROR('Facility Master'!B28,"") -> ICICI Bank | C27: =IFERROR('Facility Master'!C28,"") -> Working Capital Demand Loan (WCDL) | D27: =IFERROR('Facility Master'!D28,"") -> FB | E27: =IFERROR('Facility Master'!H28,0) -> 0 | F27: =IFERROR('Facility Master'!K28,0) -> 50 | G27: =IFERROR('Facility Master'!M28,0) -> 50 | H27: =IFERROR('Facility Master'!R28,0) -> 0.0525 | I27: =IFERROR(G27*H27,0) -> 2.625 | J27: =IFERROR('Facility Master'!I28,"") -> INR | K27: =IFERROR('Facility Master'!AF28,"") -> Repo reset; spread TBD.
A28: 25 | B28: =IFERROR('Facility Master'!B29,"") -> ICICI Bank | C28: =IFERROR('Facility Master'!C29,"") -> Letter of Credit (Inland/Foreign) | D28: =IFERROR('Facility Master'!D29,"") -> NFB | E28: =IFERROR('Facility Master'!H29,0) -> 2 | F28: =IFERROR('Facility Master'!K29,0) -> 150 | G28: =IFERROR('Facility Master'!M29,0) -> 150 | H28: =IFERROR('Facility Master'!R29,0) -> 0.005 | I28: =IFERROR(G28*H28,0) -> 0.75 | J28: =IFERROR('Facility Master'!I29,"") -> INR | K28: =IFERROR('Facility Master'!AF29,"") -> LC to JSL Global Commodities Pte Ltd capped at INR 25 Cr.
A29: 26 | B29: =IFERROR('Facility Master'!B30,"") -> ICICI Bank | C29: =IFERROR('Facility Master'!C30,"") -> SBLC for Buyers' Credit | D29: =IFERROR('Facility Master'!D30,"") -> NFB | E29: =IFERROR('Facility Master'!H30,0) -> 0 | F29: =IFERROR('Facility Master'!K30,0) -> 150 | G29: =IFERROR('Facility Master'!M30,0) -> 150 | H29: =IFERROR('Facility Master'!R30,0) -> 0.005 | I29: =IFERROR(G29*H29,0) -> 0.75 | J29: =IFERROR('Facility Master'!I30,"") -> INR | K29: =IFERROR('Facility Master'!AF30,"") -> Sub-limit of LC.
A30: 27 | B30: =IFERROR('Facility Master'!B31,"") -> ICICI Bank | C30: =IFERROR('Facility Master'!C31,"") -> Bank Guarantee - Performance | D30: =IFERROR('Facility Master'!D31,"") -> NFB | E30: =IFERROR('Facility Master'!H31,0) -> 0 | F30: =IFERROR('Facility Master'!K31,0) -> 25 | G30: =IFERROR('Facility Master'!M31,0) -> 25 | H30: =IFERROR('Facility Master'!R31,0) -> 0.005 | I30: =IFERROR(G30*H30,0) -> 0.125 | J30: =IFERROR('Facility Master'!I31,"") -> INR | K30: =IFERROR('Facility Master'!AF31,"") -> Sub-limit of LC.
A31: 28 | B31: =IFERROR('Facility Master'!B32,"") -> ICICI Bank | C31: =IFERROR('Facility Master'!C32,"") -> Bank Guarantee - Financial | D31: =IFERROR('Facility Master'!D32,"") -> NFB | E31: =IFERROR('Facility Master'!H32,0) -> 0 | F31: =IFERROR('Facility Master'!K32,0) -> 5 | G31: =IFERROR('Facility Master'!M32,0) -> 5 | H31: =IFERROR('Facility Master'!R32,0) -> 0.006 | I31: =IFERROR(G31*H31,0) -> 0.03 | J31: =IFERROR('Facility Master'!I32,"") -> INR | K31: =IFERROR('Facility Master'!AF32,"") -> Sub-limit of LC.
A32: 29 | B32: =IFERROR('Facility Master'!B33,"") -> South Indian Bank | C32: =IFERROR('Facility Master'!C33,"") -> CCOL (Cash Credit) | D32: =IFERROR('Facility Master'!D33,"") -> FB | E32: =IFERROR('Facility Master'!H33,0) -> 0 | F32: =IFERROR('Facility Master'!K33,0) -> 50 | G32: =IFERROR('Facility Master'!M33,0) -> 50 | H32: =IFERROR('Facility Master'!R33,0) -> 0.102 | I32: =IFERROR(G32*H32,0) -> 5.1 | J32: =IFERROR('Facility Master'!I33,"") -> INR | K32: =IFERROR('Facility Master'!AF33,"") -> Annual reset.
A33: 30 | B33: =IFERROR('Facility Master'!B34,"") -> South Indian Bank | C33: =IFERROR('Facility Master'!C34,"") -> WCL / WCDL | D33: =IFERROR('Facility Master'!D34,"") -> FB | E33: =IFERROR('Facility Master'!H34,0) -> 0 | F33: =IFERROR('Facility Master'!K34,0) -> 50 | G33: =IFERROR('Facility Master'!M34,0) -> 50 | H33: =IFERROR('Facility Master'!R34,0) -> 0 | I33: =IFERROR(G33*H33,0) -> 0 | J33: =IFERROR('Facility Master'!I34,"") -> INR | K33: =IFERROR('Facility Master'!AF34,"") -> Sub-limit of CCOL.
A34: 31 | B34: =IFERROR('Facility Master'!B35,"") -> South Indian Bank | C34: =IFERROR('Facility Master'!C35,"") -> Inland / Import LC | D34: =IFERROR('Facility Master'!D35,"") -> NFB | E34: =IFERROR('Facility Master'!H35,0) -> 2 | F34: =IFERROR('Facility Master'!K35,0) -> 150 | G34: =IFERROR('Facility Master'!M35,0) -> 150 | H34: =IFERROR('Facility Master'!R35,0) -> 0.0065 | I34: =IFERROR(G34*H34,0) -> 0.975 | J34: =IFERROR('Facility Master'!I35,"") -> INR | K34: =IFERROR('Facility Master'!AF35,"") -> Total LC + Capex LC ≤ INR 150 Cr.
A35: 32 | B35: =IFERROR('Facility Master'!B36,"") -> South Indian Bank | C35: =IFERROR('Facility Master'!C36,"") -> Capex LC | D35: =IFERROR('Facility Master'!D36,"") -> NFB | E35: =IFERROR('Facility Master'!H36,0) -> 0 | F35: =IFERROR('Facility Master'!K36,0) -> 50 | G35: =IFERROR('Facility Master'!M36,0) -> 50 | H35: =IFERROR('Facility Master'!R36,0) -> 0.0075 | I35: =IFERROR(G35*H35,0) -> 0.375 | J35: =IFERROR('Facility Master'!I36,"") -> INR | K35: =IFERROR('Facility Master'!AF36,"") -> Combined with Inland/Import LC limit.
A36: 33 | B36: =IFERROR('Facility Master'!B37,"") -> South Indian Bank | C36: =IFERROR('Facility Master'!C37,"") -> SBLC | D36: =IFERROR('Facility Master'!D37,"") -> NFB | E36: =IFERROR('Facility Master'!H37,0) -> 0 | F36: =IFERROR('Facility Master'!K37,0) -> 150 | G36: =IFERROR('Facility Master'!M37,0) -> 150 | H36: =IFERROR('Facility Master'!R37,0) -> 0.0065 | I36: =IFERROR(G36*H36,0) -> 0.975 | J36: =IFERROR('Facility Master'!I37,"") -> INR | K36: =IFERROR('Facility Master'!AF37,"") -> Sub-limit of LC.
A37: 34 | B37: =IFERROR('Facility Master'!B38,"") -> South Indian Bank | C37: =IFERROR('Facility Master'!C38,"") -> Forward Contract Limit | D37: =IFERROR('Facility Master'!D38,"") -> Hedge | E37: =IFERROR('Facility Master'!H38,0) -> 0 | F37: =IFERROR('Facility Master'!K38,0) -> 3 | G37: =IFERROR('Facility Master'!M38,0) -> 3 | H37: =IFERROR('Facility Master'!R38,0) -> 0 | I37: =IFERROR(G37*H37,0) -> 0 | J37: =IFERROR('Facility Master'!I38,"") -> INR | K37: =IFERROR('Facility Master'!AF38,"") -> Notional limit.
A39: Annual Interest & Commission Summary
A40: Total Interest — Sanctioned Debt (Bucket 1) | I40: {=IFERROR(SUMPRODUCT(('Facility Master'!H5:H38=1)*'Facility Master'!M5:M38*'Facility Master'!R5:R38),0)} -> 40.064012
A41: Total Commission — NFB Contingent (Bucket 2) | I41: {=IFERROR(SUMPRODUCT(('Facility Master'!H5:H38=2)*'Facility Master'!M5:M38*'Facility Master'!R5:R38),0)} -> 1.725
A42: Total — Separate Lines (Bucket 3) | I42: {=IFERROR(SUMPRODUCT(('Facility Master'!H5:H38=3)*'Facility Master'!M5:M38*'Facility Master'!R5:R38),0)} -> 7.25
A43: Total Interest + Commission (All Buckets) | I43: =I40+I41+I42 -> 49.039012
A44: Wt. Avg Cost of FB Economic Debt (Bucket 1) | I44: =IFERROR(I40/SUMIFS('Facility Master'!M:M,'Facility Master'!H:H,1),0) -> 0.080780538

Sheet Covenant Tracker
A1: COVENANT TRACKER
A2: JCL Debt Model | Financial Covenant Compliance | May 2026
A3: Lender | B3: Covenant | C3: Operator | D3: Threshold | E3: Actual | F3: Headroom | G3: Status | H3: Risk | I3: Notes
A4: RBL Bank | B4: DSCR | C4: >= | D4: 1.5 | E4: =IFERROR((EBITDA_Active-TaxPaid_Active)/(SchedTLRep_Active+IntExp_Active),0) -> 3.4889653 | F4: =IFERROR(E4-D4,0) -> 1.9889653 | G4: =IFERROR(IF(E4>=D4,IF((E4-D4)/MAX(ABS(D4),1)>0.1,"Compliant","Near Breach"),"Breached"),"Pending Input") -> Compliant | H4: =IFERROR(IF(G4="Breached","Critical",IF(G4="Near Breach","High","Low")),"Low") -> Low | I4: Per RBL TL sanction.
A5: RBL Bank | B5: Total Debt / EBITDA | C5: <= | D5: 4 | E5: =IFERROR(TotalDebt_Active/EBITDA_Active,0) -> 1.5965986 | F5: =IFERROR(D5-E5,0) -> 2.4034014 | G5: =IFERROR(IF(E5<=D5,IF((D5-E5)/MAX(ABS(D5),1)>0.1,"Compliant","Near Breach"),"Breached"),"Pending Input") -> Compliant | H5: =IFERROR(IF(G5="Breached","Critical",IF(G5="Near Breach","High","Low")),"Low") -> Low | I5: Per RBL TL sanction.
A6: RBL Bank | B6: TOL / TNW | C6: <= | D6: 2.5 | E6: =IFERROR(TOL_Active/TNW_Active,0) -> 1.5449853 | F6: =IFERROR(D6-E6,0) -> 0.95501466 | G6: =IFERROR(IF(E6<=D6,IF((D6-E6)/MAX(ABS(D6),1)>0.1,"Compliant","Near Breach"),"Breached"),"Pending Input") -> Compliant | H6: =IFERROR(IF(G6="Breached","Critical",IF(G6="Near Breach","High","Low")),"Low") -> Low | I6: Per RBL TL sanction.
A7: RBL Bank | B7: Term Debt / EBITDA | C7: <= | D7: 3 | E7: =IFERROR(TermDebt_Active/EBITDA_Active,0) -> 1.123242 | F7: =IFERROR(D7-E7,0) -> 1.876758 | G7: =IFERROR(IF(E7<=D7,IF((D7-E7)/MAX(ABS(D7),1)>0.1,"Compliant","Near Breach"),"Breached"),"Pending Input") -> Compliant | H7: =IFERROR(IF(G7="Breached","Critical",IF(G7="Near Breach","High","Low")),"Low") -> Low | I7: Per RBL TL sanction.
A8: RBL Bank | B8: External Rating | C8: rating | D8: BBB+ | E8: =Rating_Active -> CARE A+; Stable / A1 | F8: =IFERROR(IFERROR(VLOOKUP(IFERROR(TRIM(MID(E8,FIND(" ",E8)+1,FIND(";",E8)-FIND(" ",E8)-1)),E8),'Instructions & Assumptions'!$A$61:$B$72,2,FALSE()),0)-IFERROR(VLOOKUP(D8,'Instructions & Assumptions'!$A$61:$B$72,2,FALSE()),0),"N/A") -> 3 | G8: =IF(E8="","Pending Input",IF(IFERROR(VLOOKUP(IFERROR(TRIM(MID(E8,FIND(" ",E8)+1,FIND(";",E8)-FIND(" ",E8)-1)),E8),'Instructions & Assumptions'!$A$61:$B$72,2,FALSE()),0)=0,"Pending Input",IF(F8="N/A","Pending Input",IF(F8>=2,"Compliant",IF(F8>=0,"Near Breach","Breached"))))) -> Compliant | H8: =IFERROR(IF(G8="Breached","Critical",IF(G8="Near Breach","High","Low")),"Low") -> Low | I8: Minimum rating.
A9: RBL Bank | B9: Promoter Shareholding | C9: >= | D9: 0.51 | E9: =PromStake_Active -> 1 | F9: =IFERROR(E9-D9,0) -> 0.49 | G9: =IFERROR(IF(E9>=D9,IF((E9-D9)/MAX(ABS(D9),1)>0.1,"Compliant","Near Breach"),"Breached"),"Pending Input") -> Compliant | H9: =IFERROR(IF(G9="Breached","Critical",IF(G9="Near Breach","High","Low")),"Low") -> Low | I9: Min holding.
A10: YES Bank | B10: DSCR | C10: >= | D10: 1.5 | E10: =IFERROR((EBITDA_Active-TaxPaid_Active)/(SchedTLRep_Active+IntExp_Active),0) -> 3.4889653 | F10: =IFERROR(E10-D10,0) -> 1.9889653 | G10: =IFERROR(IF(E10>=D10,IF((E10-D10)/MAX(ABS(D10),1)>0.1,"Compliant","Near Breach"),"Breached"),"Pending Input") -> Compliant | H10: =IFERROR(IF(G10="Breached","Critical",IF(G10="Near Breach","High","Low")),"Low") -> Low | I10: YBL TL covenant.
A11: YES Bank | B11: Total Debt / EBITDA | C11: <= | D11: 4.5 | E11: =IFERROR(TotalDebt_Active/EBITDA_Active,0) -> 1.5965986 | F11: =IFERROR(D11-E11,0) -> 2.9034014 | G11: =IFERROR(IF(E11<=D11,IF((D11-E11)/MAX(ABS(D11),1)>0.1,"Compliant","Near Breach"),"Breached"),"Pending Input") -> Compliant | H11: =IFERROR(IF(G11="Breached","Critical",IF(G11="Near Breach","High","Low")),"Low") -> Low
A12: YES Bank | B12: TOL / TNW | C12: <= | D12: 2.5 | E12: =IFERROR(TOL_Active/TNW_Active,0) -> 1.5449853 | F12: =IFERROR(D12-E12,0) -> 0.95501466 | G12: =IFERROR(IF(E12<=D12,IF((D12-E12)/MAX(ABS(D12),1)>0.1,"Compliant","Near Breach"),"Breached"),"Pending Input") -> Compliant | H12: =IFERROR(IF(G12="Breached","Critical",IF(G12="Near Breach","High","Low")),"Low") -> Low
A13: YES Bank | B13: ICR | C13: >= | D13: 2 | E13: =IFERROR(EBITDA_Active/IntExp_Active,0) -> 7.8231459 | F13: =IFERROR(E13-D13,0) -> 5.8231459 | G13: =IFERROR(IF(E13>=D13,IF((E13-D13)/MAX(ABS(D13),1)>0.1,"Compliant","Near Breach"),"Breached"),"Pending Input") -> Compliant | H13: =IFERROR(IF(G13="Breached","Critical",IF(G13="Near Breach","High","Low")),"Low") -> Low
A14: YES Bank | B14: Current Ratio | C14: >= | D14: 1.1 | E14: =IFERROR(CA_Active/CL_Active,0) -> 1.3858918 | F14: =IFERROR(E14-D14,0) -> 0.28589181 | G14: =IFERROR(IF(E14>=D14,IF((E14-D14)/MAX(ABS(D14),1)>0.1,"Compliant","Near Breach"),"Breached"),"Pending Input") -> Compliant | H14: =IFERROR(IF(G14="Breached","Critical",IF(G14="Near Breach","High","Low")),"Low") -> Low
A15: YES Bank | B15: FACR | C15: >= | D15: 1.25 | E15: =IFERROR(FA_Active/SecuredDebt_Active,0) -> 2.1742024 | F15: =IFERROR(E15-D15,0) -> 0.92420237 | G15: =IFERROR(IF(E15>=D15,IF((E15-D15)/MAX(ABS(D15),1)>0.1,"Compliant","Near Breach"),"Breached"),"Pending Input") -> Compliant | H15: =IFERROR(IF(G15="Breached","Critical",IF(G15="Near Breach","High","Low")),"Low") -> Low
A16: Bajaj Finance | B16: DSCR | C16: >= | D16: 1.5 | E16: =IFERROR((EBITDA_Active-TaxPaid_Active)/(SchedTLRep_Active+IntExp_Active),0) -> 3.4889653 | F16: =IFERROR(E16-D16,0) -> 1.9889653 | G16: =IFERROR(IF(E16>=D16,IF((E16-D16)/MAX(ABS(D16),1)>0.1,"Compliant","Near Breach"),"Breached"),"Pending Input") -> Compliant | H16: =IFERROR(IF(G16="Breached","Critical",IF(G16="Near Breach","High","Low")),"Low") -> Low | I16: Bajaj TL covenant.
A17: Bajaj Finance | B17: Total Debt / EBITDA | C17: <= | D17: 4 | E17: =IFERROR(TotalDebt_Active/EBITDA_Active,0) -> 1.5965986 | F17: =IFERROR(D17-E17,0) -> 2.4034014 | G17: =IFERROR(IF(E17<=D17,IF((D17-E17)/MAX(ABS(D17),1)>0.1,"Compliant","Near Breach"),"Breached"),"Pending Input") -> Compliant | H17: =IFERROR(IF(G17="Breached","Critical",IF(G17="Near Breach","High","Low")),"Low") -> Low
A18: Bajaj Finance | B18: TOL / TNW | C18: <= | D18: 2.5 | E18: =IFERROR(TOL_Active/TNW_Active,0) -> 1.5449853 | F18: =IFERROR(D18-E18,0) -> 0.95501466 | G18: =IFERROR(IF(E18<=D18,IF((D18-E18)/MAX(ABS(D18),1)>0.1,"Compliant","Near Breach"),"Breached"),"Pending Input") -> Compliant | H18: =IFERROR(IF(G18="Breached","Critical",IF(G18="Near Breach","High","Low")),"Low") -> Low
A19: Bajaj Finance | B19: FACR (MSC 1.25x) | C19: >= | D19: 1.25 | E19: =IFERROR(FA_Active/SecuredDebt_Active,0) -> 2.1742024 | F19: =IFERROR(E19-D19,0) -> 0.92420237 | G19: =IFERROR(IF(E19>=D19,IF((E19-D19)/MAX(ABS(D19),1)>0.1,"Compliant","Near Breach"),"Breached"),"Pending Input") -> Compliant | H19: =IFERROR(IF(G19="Breached","Critical",IF(G19="Near Breach","High","Low")),"Low") -> Low | I19: Min Security Cover.
A20: Bajaj Finance | B20: Debt / Equity | C20: <= | D20: 1.5 | E20: =IFERROR(TotalDebt_Active/TNW_Active,0) -> 0.82827341 | F20: =IFERROR(D20-E20,0) -> 0.67172659 | G20: =IFERROR(IF(E20<=D20,IF((D20-E20)/MAX(ABS(D20),1)>0.1,"Compliant","Near Breach"),"Breached"),"Pending Input") -> Compliant | H20: =IFERROR(IF(G20="Breached","Critical",IF(G20="Near Breach","High","Low")),"Low") -> Low
A21: ICICI Bank | B21: Total Debt / EBITDA | C21: <= | D21: 4 | E21: =IFERROR(TotalDebt_Active/EBITDA_Active,0) -> 1.5965986 | F21: =IFERROR(D21-E21,0) -> 2.4034014 | G21: =IFERROR(IF(E21<=D21,IF((D21-E21)/MAX(ABS(D21),1)>0.1,"Compliant","Near Breach"),"Breached"),"Pending Input") -> Compliant | H21: =IFERROR(IF(G21="Breached","Critical",IF(G21="Near Breach","High","Low")),"Low") -> Low
A22: ICICI Bank | B22: TOL / TNW | C22: <= | D22: 2.5 | E22: =IFERROR(TOL_Active/TNW_Active,0) -> 1.5449853 | F22: =IFERROR(D22-E22,0) -> 0.95501466 | G22: =IFERROR(IF(E22<=D22,IF((D22-E22)/MAX(ABS(D22),1)>0.1,"Compliant","Near Breach"),"Breached"),"Pending Input") -> Compliant | H22: =IFERROR(IF(G22="Breached","Critical",IF(G22="Near Breach","High","Low")),"Low") -> Low
A23: ICICI Bank | B23: Current Ratio | C23: >= | D23: 1.1 | E23: =IFERROR(CA_Active/CL_Active,0) -> 1.3858918 | F23: =IFERROR(E23-D23,0) -> 0.28589181 | G23: =IFERROR(IF(E23>=D23,IF((E23-D23)/MAX(ABS(D23),1)>0.1,"Compliant","Near Breach"),"Breached"),"Pending Input") -> Compliant | H23: =IFERROR(IF(G23="Breached","Critical",IF(G23="Near Breach","High","Low")),"Low") -> Low
A24: ICICI Bank | B24: External Rating | C24: rating | D24: A- | E24: =Rating_Active -> CARE A+; Stable / A1 | F24: =IFERROR(IFERROR(VLOOKUP(IFERROR(TRIM(MID(E24,FIND(" ",E24)+1,FIND(";",E24)-FIND(" ",E24)-1)),E24),'Instructions & Assumptions'!$A$61:$B$72,2,FALSE()),0)-IFERROR(VLOOKUP(D24,'Instructions & Assumptions'!$A$61:$B$72,2,FALSE()),0),"N/A") -> 2 | G24: =IF(E24="","Pending Input",IF(IFERROR(VLOOKUP(IFERROR(TRIM(MID(E24,FIND(" ",E24)+1,FIND(";",E24)-FIND(" ",E24)-1)),E24),'Instructions & Assumptions'!$A$61:$B$72,2,FALSE()),0)=0,"Pending Input",IF(F24="N/A","Pending Input",IF(F24>=2,"Compliant",IF(F24>=0,"Near Breach","Breached"))))) -> Compliant | H24: =IFERROR(IF(G24="Breached","Critical",IF(G24="Near Breach","High","Low")),"Low") -> Low
A25: South Indian Bank | B25: Total Debt / EBITDA | C25: <= | D25: 4.5 | E25: =IFERROR(TotalDebt_Active/EBITDA_Active,0) -> 1.5965986 | F25: =IFERROR(D25-E25,0) -> 2.9034014 | G25: =IFERROR(IF(E25<=D25,IF((D25-E25)/MAX(ABS(D25),1)>0.1,"Compliant","Near Breach"),"Breached"),"Pending Input") -> Compliant | H25: =IFERROR(IF(G25="Breached","Critical",IF(G25="Near Breach","High","Low")),"Low") -> Low
A26: South Indian Bank | B26: TOL / TNW | C26: <= | D26: 2.5 | E26: =IFERROR(TOL_Active/TNW_Active,0) -> 1.5449853 | F26: =IFERROR(D26-E26,0) -> 0.95501466 | G26: =IFERROR(IF(E26<=D26,IF((D26-E26)/MAX(ABS(D26),1)>0.1,"Compliant","Near Breach"),"Breached"),"Pending Input") -> Compliant | H26: =IFERROR(IF(G26="Breached","Critical",IF(G26="Near Breach","High","Low")),"Low") -> Low
A27: South Indian Bank | B27: ICR | C27: >= | D27: 2 | E27: =IFERROR(EBITDA_Active/IntExp_Active,0) -> 7.8231459 | F27: =IFERROR(E27-D27,0) -> 5.8231459 | G27: =IFERROR(IF(E27>=D27,IF((E27-D27)/MAX(ABS(D27),1)>0.1,"Compliant","Near Breach"),"Breached"),"Pending Input") -> Compliant | H27: =IFERROR(IF(G27="Breached","Critical",IF(G27="Near Breach","High","Low")),"Low") -> Low
A29: Covenant Dashboard
A30: Total Covenants | B30: =COUNTA(B4:B27) -> 24
A31: Compliant | B31: =COUNTIF(G4:G27,"Compliant") -> 24
A32: Near Breach | B32: =COUNTIF(G4:G27,"Near Breach") -> 0
A33: Breached | B33: =COUNTIF(G4:G27,"Breached") -> 0
A34: Pending Input | B34: =COUNTIFS(G4:G27,"Pending*") -> 0
A35: Portfolio Compliance % | B35: =IFERROR(B31/B30,0) -> 1
A37: The TOL figure used in TOL/TNW covenants is drawn from JCL's audited balance sheet (Instructions Section C, line item TOL). This figure already incorporates the appropriate accounting treatment of contingent NFB liabilities. The Total Debt figure used in Total Debt/EBITDA, Total Debt/ATNW, and Term Debt/EBITDA covenants is the Gross Outstanding Debt of ₹613.03 Cr (from Instructions B25 — JCL audited financials), NOT the FB Economic Debt of ₹720.7 Cr (Bucket 1) or the Sanctioned Debt of ₹1,320.7 Cr (B1+B2). Covenants standardly test outstanding (drawn) debt rather than sanctioned limits. If the lender's covenant definition specifies sanctioned/committed debt, override TotalDebt_Active to point to a Bucket-1 reference.

Sheet Security & Charge Matrix
A1: SECURITY & CHARGE MATRIX
A2: JCL Debt Model | Collateral & Personal Guarantee Register | May 2026
A3: Lender | B3: # of Facilities | C3: Sanctioned Debt ₹ Cr | D3: Personal Guarantee | E3: Charge Type | F3: Security Description
A4: RBL Bank | B4: =IFERROR(COUNTIFS('Facility Master'!B:B,"RBL Bank",'Facility Master'!A:A,">0"),0) -> 15 | C4: ='Lender Summary'!D5 -> 300 | D4: =IFERROR(IF(COUNTIFS('Facility Master'!B:B,"RBL Bank",'Facility Master'!AD:AD,"*Personal*")>0,"Yes","See note"),"") -> Yes | E4: 1st / 2nd p-p hypothecation + mortgage | F4: 1st p-p on CA; 2nd p-p on FA; 1st p-p mortgage on Faridabad property; Personal guarantee of promoters; FD-collateralised lines exclusive on FD
A5: YES Bank | B5: =IFERROR(COUNTIFS('Facility Master'!B:B,"YES Bank",'Facility Master'!A:A,">0"),0) -> 6 | C5: ='Lender Summary'!D6 -> 520.7 | D5: =IFERROR(IF(COUNTIFS('Facility Master'!B:B,"YES Bank",'Facility Master'!AD:AD,"*Personal*")>0,"Yes","See note"),"") -> Yes | E5: 1st / 2nd p-p hypothecation + mortgage | F5: 1st p-p hypothecation over CA; mortgage on Faridabad property; 2nd p-p on FA; Personal guarantee
A6: Bajaj Finance | B6: =IFERROR(COUNTIFS('Facility Master'!B:B,"Bajaj Finance",'Facility Master'!A:A,">0"),0) -> 1 | C6: ='Lender Summary'!D7 -> 150 | D6: =IFERROR(IF(COUNTIFS('Facility Master'!B:B,"Bajaj Finance",'Facility Master'!AD:AD,"*Personal*")>0,"Yes","See note"),"") -> Yes | E6: 1st / 2nd p-p hypothecation + mortgage | F6: 1st p-p on FA at Coke Plant Khurunti; 2nd p-p on CA; MSC 1.25x; Personal guarantee
A7: ICICI Bank | B7: =IFERROR(COUNTIFS('Facility Master'!B:B,"ICICI Bank",'Facility Master'!A:A,">0"),0) -> 6 | C7: ='Lender Summary'!D8 -> 200 | D7: =IFERROR(IF(COUNTIFS('Facility Master'!B:B,"ICICI Bank",'Facility Master'!AD:AD,"*Personal*")>0,"Yes","See note"),"") -> See note | E7: 1st / 2nd p-p hypothecation + mortgage | F7: 1st p-p on CA; 2nd p-p on FA; 2nd p-p mortgage on Kalinga Nagar property
A8: South Indian Bank | B8: =IFERROR(COUNTIFS('Facility Master'!B:B,"South Indian Bank",'Facility Master'!A:A,">0"),0) -> 6 | C8: ='Lender Summary'!D9 -> 150 | D8: =IFERROR(IF(COUNTIFS('Facility Master'!B:B,"South Indian Bank",'Facility Master'!AD:AD,"*Personal*")>0,"Yes","See note"),"") -> See note | E8: 1st / 2nd p-p hypothecation + mortgage | F8: 1st p-p on CA; 2nd p-p on FA; 2nd p-p mortgage on Kalinga Nagar property

Sheet Utilization Tracker
A1: UTILIZATION TRACKER
A2: JCL Debt Model | Facility Utilisation & Validity Monitor | May 2026
A3: S.No | B3: Lender | C3: Facility | D3: Sanc INR Cr | E3: Eff O/S | F3: Util % | G3: Status | H3: Days to Validity | I3: Review Flag
A4: 1 | B4: =IFERROR('Facility Master'!B5,"") -> RBL Bank | C4: =IFERROR('Facility Master'!C5,"") -> Letter of Credit - Main Limit | D4: =IFERROR('Facility Master'!K5,0) -> 100 | E4: =IFERROR('Facility Master'!M5,0) -> 100 | F4: =IFERROR('Facility Master'!N5,0) -> 1 | G4: =IFERROR(IF(F4>0.9,"High (>90%)",IF(F4>0.75,"Elevated (75-90%)",IF(F4>0,"Normal","Unutilised"))),"") -> High (>90%) | H4: =IFERROR(IF('Facility Master'!D5="FB-Term",IF('Facility Master'!Z5="","-",'Facility Master'!Z5-AsOfDate),IF('Facility Master'!AB5="","-",'Facility Master'!AB5-AsOfDate)),"-") -> 244 | I4: =IFERROR(IF('Facility Master'!D5="FB-Term",IF('Facility Master'!Z5="","No Maturity",IF(H4<=180,"Maturing (<=180d)",IF(H4<=365,"Maturing (<=1yr)","TL — On Schedule"))),IF('Facility Master'!AB5="","No Validity",IF(H4<=30,"Expiring (<=30d)",IF(H4<=60,"Due for Review (<=60d)","OK")))),"") -> OK
A5: 2 | B5: =IFERROR('Facility Master'!B6,"") -> RBL Bank | C5: =IFERROR('Facility Master'!C6,"") -> Bank Guarantee | D5: =IFERROR('Facility Master'!K6,0) -> 25 | E5: =IFERROR('Facility Master'!M6,0) -> 25 | F5: =IFERROR('Facility Master'!N6,0) -> 1 | G5: =IFERROR(IF(F5>0.9,"High (>90%)",IF(F5>0.75,"Elevated (75-90%)",IF(F5>0,"Normal","Unutilised"))),"") -> High (>90%) | H5: =IFERROR(IF('Facility Master'!D6="FB-Term",IF('Facility Master'!Z6="","-",'Facility Master'!Z6-AsOfDate),IF('Facility Master'!AB6="","-",'Facility Master'!AB6-AsOfDate)),"-") -> 244 | I5: =IFERROR(IF('Facility Master'!D6="FB-Term",IF('Facility Master'!Z6="","No Maturity",IF(H5<=180,"Maturing (<=180d)",IF(H5<=365,"Maturing (<=1yr)","TL — On Schedule"))),IF('Facility Master'!AB6="","No Validity",IF(H5<=30,"Expiring (<=30d)",IF(H5<=60,"Due for Review (<=60d)","OK")))),"") -> OK
A6: 3 | B6: =IFERROR('Facility Master'!B7,"") -> RBL Bank | C6: =IFERROR('Facility Master'!C7,"") -> Invoice Discounting (PID) | D6: =IFERROR('Facility Master'!K7,0) -> 100 | E6: =IFERROR('Facility Master'!M7,0) -> 100 | F6: =IFERROR('Facility Master'!N7,0) -> 1 | G6: =IFERROR(IF(F6>0.9,"High (>90%)",IF(F6>0.75,"Elevated (75-90%)",IF(F6>0,"Normal","Unutilised"))),"") -> High (>90%) | H6: =IFERROR(IF('Facility Master'!D7="FB-Term",IF('Facility Master'!Z7="","-",'Facility Master'!Z7-AsOfDate),IF('Facility Master'!AB7="","-",'Facility Master'!AB7-AsOfDate)),"-") -> 244 | I6: =IFERROR(IF('Facility Master'!D7="FB-Term",IF('Facility Master'!Z7="","No Maturity",IF(H6<=180,"Maturing (<=180d)",IF(H6<=365,"Maturing (<=1yr)","TL — On Schedule"))),IF('Facility Master'!AB7="","No Validity",IF(H6<=30,"Expiring (<=30d)",IF(H6<=60,"Due for Review (<=60d)","OK")))),"") -> OK
A7: 4 | B7: =IFERROR('Facility Master'!B8,"") -> RBL Bank | C7: =IFERROR('Facility Master'!C8,"") -> SBLC | D7: =IFERROR('Facility Master'!K8,0) -> 100 | E7: =IFERROR('Facility Master'!M8,0) -> 100 | F7: =IFERROR('Facility Master'!N8,0) -> 1 | G7: =IFERROR(IF(F7>0.9,"High (>90%)",IF(F7>0.75,"Elevated (75-90%)",IF(F7>0,"Normal","Unutilised"))),"") -> High (>90%) | H7: =IFERROR(IF('Facility Master'!D8="FB-Term",IF('Facility Master'!Z8="","-",'Facility Master'!Z8-AsOfDate),IF('Facility Master'!AB8="","-",'Facility Master'!AB8-AsOfDate)),"-") -> 244 | I7: =IFERROR(IF('Facility Master'!D8="FB-Term",IF('Facility Master'!Z8="","No Maturity",IF(H7<=180,"Maturing (<=180d)",IF(H7<=365,"Maturing (<=1yr)","TL — On Schedule"))),IF('Facility Master'!AB8="","No Validity",IF(H7<=30,"Expiring (<=30d)",IF(H7<=60,"Due for Review (<=60d)","OK")))),"") -> OK
A8: 5 | B8: =IFERROR('Facility Master'!B9,"") -> RBL Bank | C8: =IFERROR('Facility Master'!C9,"") -> Pre-Acceptance LCBD | D8: =IFERROR('Facility Master'!K9,0) -> 100 | E8: =IFERROR('Facility Master'!M9,0) -> 100 | F8: =IFERROR('Facility Master'!N9,0) -> 1 | G8: =IFERROR(IF(F8>0.9,"High (>90%)",IF(F8>0.75,"Elevated (75-90%)",IF(F8>0,"Normal","Unutilised"))),"") -> High (>90%) | H8: =IFERROR(IF('Facility Master'!D9="FB-Term",IF('Facility Master'!Z9="","-",'Facility Master'!Z9-AsOfDate),IF('Facility Master'!AB9="","-",'Facility Master'!AB9-AsOfDate)),"-") -> 244 | I8: =IFERROR(IF('Facility Master'!D9="FB-Term",IF('Facility Master'!Z9="","No Maturity",IF(H8<=180,"Maturing (<=180d)",IF(H8<=365,"Maturing (<=1yr)","TL — On Schedule"))),IF('Facility Master'!AB9="","No Validity",IF(H8<=30,"Expiring (<=30d)",IF(H8<=60,"Due for Review (<=60d)","OK")))),"") -> OK
A9: 6 | B9: =IFERROR('Facility Master'!B10,"") -> RBL Bank | C9: =IFERROR('Facility Master'!C10,"") -> Cash Credit | D9: =IFERROR('Facility Master'!K10,0) -> 100 | E9: =IFERROR('Facility Master'!M10,0) -> 100 | F9: =IFERROR('Facility Master'!N10,0) -> 1 | G9: =IFERROR(IF(F9>0.9,"High (>90%)",IF(F9>0.75,"Elevated (75-90%)",IF(F9>0,"Normal","Unutilised"))),"") -> High (>90%) | H9: =IFERROR(IF('Facility Master'!D10="FB-Term",IF('Facility Master'!Z10="","-",'Facility Master'!Z10-AsOfDate),IF('Facility Master'!AB10="","-",'Facility Master'!AB10-AsOfDate)),"-") -> 244 | I9: =IFERROR(IF('Facility Master'!D10="FB-Term",IF('Facility Master'!Z10="","No Maturity",IF(H9<=180,"Maturing (<=180d)",IF(H9<=365,"Maturing (<=1yr)","TL — On Schedule"))),IF('Facility Master'!AB10="","No Validity",IF(H9<=30,"Expiring (<=30d)",IF(H9<=60,"Due for Review (<=60d)","OK")))),"") -> OK
A10: 7 | B10: =IFERROR('Facility Master'!B11,"") -> RBL Bank | C10: =IFERROR('Facility Master'!C11,"") -> Working Capital Demand Loan (WCDL) | D10: =IFERROR('Facility Master'!K11,0) -> 100 | E10: =IFERROR('Facility Master'!M11,0) -> 100 | F10: =IFERROR('Facility Master'!N11,0) -> 1 | G10: =IFERROR(IF(F10>0.9,"High (>90%)",IF(F10>0.75,"Elevated (75-90%)",IF(F10>0,"Normal","Unutilised"))),"") -> High (>90%) | H10: =IFERROR(IF('Facility Master'!D11="FB-Term",IF('Facility Master'!Z11="","-",'Facility Master'!Z11-AsOfDate),IF('Facility Master'!AB11="","-",'Facility Master'!AB11-AsOfDate)),"-") -> 244 | I10: =IFERROR(IF('Facility Master'!D11="FB-Term",IF('Facility Master'!Z11="","No Maturity",IF(H10<=180,"Maturing (<=180d)",IF(H10<=365,"Maturing (<=1yr)","TL — On Schedule"))),IF('Facility Master'!AB11="","No Validity",IF(H10<=30,"Expiring (<=30d)",IF(H10<=60,"Due for Review (<=60d)","OK")))),"") -> OK
A11: 8 | B11: =IFERROR('Facility Master'!B12,"") -> RBL Bank | C11: =IFERROR('Facility Master'!C12,"") -> Loan Equivalent Risk (LER) | D11: =IFERROR('Facility Master'!K12,0) -> 20 | E11: =IFERROR('Facility Master'!M12,0) -> 20 | F11: =IFERROR('Facility Master'!N12,0) -> 1 | G11: =IFERROR(IF(F11>0.9,"High (>90%)",IF(F11>0.75,"Elevated (75-90%)",IF(F11>0,"Normal","Unutilised"))),"") -> High (>90%) | H11: =IFERROR(IF('Facility Master'!D12="FB-Term",IF('Facility Master'!Z12="","-",'Facility Master'!Z12-AsOfDate),IF('Facility Master'!AB12="","-",'Facility Master'!AB12-AsOfDate)),"-") -> 244 | I11: =IFERROR(IF('Facility Master'!D12="FB-Term",IF('Facility Master'!Z12="","No Maturity",IF(H11<=180,"Maturing (<=180d)",IF(H11<=365,"Maturing (<=1yr)","TL — On Schedule"))),IF('Facility Master'!AB12="","No Validity",IF(H11<=30,"Expiring (<=30d)",IF(H11<=60,"Due for Review (<=60d)","OK")))),"") -> OK
A12: 9 | B12: =IFERROR('Facility Master'!B13,"") -> RBL Bank | C12: =IFERROR('Facility Master'!C13,"") -> Term Loan | D12: =IFERROR('Facility Master'!K13,0) -> 200 | E12: =IFERROR('Facility Master'!M13,0) -> 0 | F12: =IFERROR('Facility Master'!N13,0) -> 0 | G12: =IFERROR(IF(F12>0.9,"High (>90%)",IF(F12>0.75,"Elevated (75-90%)",IF(F12>0,"Normal","Unutilised"))),"") -> Unutilised | H12: =IFERROR(IF('Facility Master'!D13="FB-Term",IF('Facility Master'!Z13="","-",'Facility Master'!Z13-AsOfDate),IF('Facility Master'!AB13="","-",'Facility Master'!AB13-AsOfDate)),"-") -> 1096 | I12: =IFERROR(IF('Facility Master'!D13="FB-Term",IF('Facility Master'!Z13="","No Maturity",IF(H12<=180,"Maturing (<=180d)",IF(H12<=365,"Maturing (<=1yr)","TL — On Schedule"))),IF('Facility Master'!AB13="","No Validity",IF(H12<=30,"Expiring (<=30d)",IF(H12<=60,"Due for Review (<=60d)","OK")))),"") -> TL — On Schedule
A13: 10 | B13: =IFERROR('Facility Master'!B14,"") -> RBL Bank | C13: =IFERROR('Facility Master'!C14,"") -> SBLC for Buyer's Credit (GIFT City) | D13: =IFERROR('Facility Master'!K14,0) -> 190 | E13: =IFERROR('Facility Master'!M14,0) -> 190 | F13: =IFERROR('Facility Master'!N14,0) -> 1 | G13: =IFERROR(IF(F13>0.9,"High (>90%)",IF(F13>0.75,"Elevated (75-90%)",IF(F13>0,"Normal","Unutilised"))),"") -> High (>90%) | H13: =IFERROR(IF('Facility Master'!D14="FB-Term",IF('Facility Master'!Z14="","-",'Facility Master'!Z14-AsOfDate),IF('Facility Master'!AB14="","-",'Facility Master'!AB14-AsOfDate)),"-") -> 244 | I13: =IFERROR(IF('Facility Master'!D14="FB-Term",IF('Facility Master'!Z14="","No Maturity",IF(H13<=180,"Maturing (<=180d)",IF(H13<=365,"Maturing (<=1yr)","TL — On Schedule"))),IF('Facility Master'!AB14="","No Validity",IF(H13<=30,"Expiring (<=30d)",IF(H13<=60,"Due for Review (<=60d)","OK")))),"") -> OK
A14: 11 | B14: =IFERROR('Facility Master'!B15,"") -> RBL Bank | C14: =IFERROR('Facility Master'!C15,"") -> Capex LC | D14: =IFERROR('Facility Master'!K15,0) -> 25 | E14: =IFERROR('Facility Master'!M15,0) -> 25 | F14: =IFERROR('Facility Master'!N15,0) -> 1 | G14: =IFERROR(IF(F14>0.9,"High (>90%)",IF(F14>0.75,"Elevated (75-90%)",IF(F14>0,"Normal","Unutilised"))),"") -> High (>90%) | H14: =IFERROR(IF('Facility Master'!D15="FB-Term",IF('Facility Master'!Z15="","-",'Facility Master'!Z15-AsOfDate),IF('Facility Master'!AB15="","-",'Facility Master'!AB15-AsOfDate)),"-") -> 244 | I14: =IFERROR(IF('Facility Master'!D15="FB-Term",IF('Facility Master'!Z15="","No Maturity",IF(H14<=180,"Maturing (<=180d)",IF(H14<=365,"Maturing (<=1yr)","TL — On Schedule"))),IF('Facility Master'!AB15="","No Validity",IF(H14<=30,"Expiring (<=30d)",IF(H14<=60,"Due for Review (<=60d)","OK")))),"") -> OK
A15: 12 | B15: =IFERROR('Facility Master'!B16,"") -> RBL Bank | C15: =IFERROR('Facility Master'!C16,"") -> Overdraft backed by 100% FD (FDOD) | D15: =IFERROR('Facility Master'!K16,0) -> 100 | E15: =IFERROR('Facility Master'!M16,0) -> 100 | F15: =IFERROR('Facility Master'!N16,0) -> 1 | G15: =IFERROR(IF(F15>0.9,"High (>90%)",IF(F15>0.75,"Elevated (75-90%)",IF(F15>0,"Normal","Unutilised"))),"") -> High (>90%) | H15: =IFERROR(IF('Facility Master'!D16="FB-Term",IF('Facility Master'!Z16="","-",'Facility Master'!Z16-AsOfDate),IF('Facility Master'!AB16="","-",'Facility Master'!AB16-AsOfDate)),"-") -> 244 | I15: =IFERROR(IF('Facility Master'!D16="FB-Term",IF('Facility Master'!Z16="","No Maturity",IF(H15<=180,"Maturing (<=180d)",IF(H15<=365,"Maturing (<=1yr)","TL — On Schedule"))),IF('Facility Master'!AB16="","No Validity",IF(H15<=30,"Expiring (<=30d)",IF(H15<=60,"Due for Review (<=60d)","OK")))),"") -> OK
... A37: 34 | B37: =IFERROR('Facility Master'!B38,"") -> South Indian Bank | C37: =IFERROR('Facility Master'!C38,"") -> Forward Contract Limit | D37: =IFERROR('Facility Master'!K38,0) -> 3 | E37: =IFERROR('Facility Master'!M38,0) -> 3 | F37: =IFERROR('Facility Master'!N38,0) -> 1 | G37: =IFERROR(IF(F37>0.9,"High (>90%)",IF(F37>0.75,"Elevated (75-90%)",IF(F37>0,"Normal","Unutilised"))),"") -> High (>90%) | H37: =IFERROR(IF('Facility Master'!D38="FB-Term",IF('Facility Master'!Z38="","-",'Facility Master'!Z38-AsOfDate),IF('Facility Master'!AB38="","-",'Facility Master'!AB38-AsOfDate)),"-") -> 82 | I37: =IFERROR(IF('Facility Master'!D38="FB-Term",IF('Facility Master'!Z38="","No Maturity",IF(H37<=180,"Maturing (<=180d)",IF(H37<=365,"Maturing (<=1yr)","TL — On Schedule"))),IF('Facility Master'!AB38="","No Validity",IF(H37<=30,"Expiring (<=30d)",IF(H37<=60,"Due for Review (<=60d)","OK")))),"") -> OK

Sheet Renewal & Review Calendar
A1: RENEWAL & REVIEW CALENDAR
A2: JCL Debt Model | Sanction Validity & Annual Renewal Schedule | May 2026
A3: S.No | B3: Lender | C3: Facility | D3: Sanction Date | E3: Validity Date | F3: Days to Validity | G3: Status | H3: Action
A4: 1 | B4: =IFERROR('Facility Master'!B5,"") -> RBL Bank | C4: =IFERROR('Facility Master'!C5,"") -> Letter of Credit - Main Limit | D4: =IFERROR('Facility Master'!AA5,"") -> 46022 | E4: =IFERROR(IF('Facility Master'!D5="FB-Term",'Facility Master'!Z5,'Facility Master'!AB5),"") -> 46356 | F4: =IFERROR(IF('Facility Master'!D5="FB-Term",IF('Facility Master'!Z5="","-",'Facility Master'!Z5-AsOfDate),IF('Facility Master'!AB5="","-",'Facility Master'!AB5-AsOfDate)),"-") -> 244 | G4: =IFERROR(IF('Facility Master'!D5="FB-Term",IF('Facility Master'!Z5="","No Maturity",IF(F4<=180,"Maturing <=180d",IF(F4<=365,"Maturing <=1yr","Term Loan — On Schedule"))),IF('Facility Master'!AB5="","No Validity Date",IF('Facility Master'!AB5<AsOfDate,"Annual Renewal — Confirm with Ops",IF(F4<=30,"Expiring <=30d",IF(F4<=60,"Due <=60d","Valid"))))),"") -> Valid | H4: =IF(G4="Annual Renewal — Confirm with Ops","Update validity from RM letter",IF(LEFT(G4,8)="Expiring","Initiate renewal",IF(G4="Maturing <=180d","Plan refinance",IF(G4="Maturing <=1yr","Begin refinance discussion","-")))) -> -
A5: 2 | B5: =IFERROR('Facility Master'!B6,"") -> RBL Bank | C5: =IFERROR('Facility Master'!C6,"") -> Bank Guarantee | D5: =IFERROR('Facility Master'!AA6,"") -> 46022 | E5: =IFERROR(IF('Facility Master'!D6="FB-Term",'Facility Master'!Z6,'Facility Master'!AB6),"") -> 46356 | F5: =IFERROR(IF('Facility Master'!D6="FB-Term",IF('Facility Master'!Z6="","-",'Facility Master'!Z6-AsOfDate),IF('Facility Master'!AB6="","-",'Facility Master'!AB6-AsOfDate)),"-") -> 244 | G5: =IFERROR(IF('Facility Master'!D6="FB-Term",IF('Facility Master'!Z6="","No Maturity",IF(F5<=180,"Maturing <=180d",IF(F5<=365,"Maturing <=1yr","Term Loan — On Schedule"))),IF('Facility Master'!AB6="","No Validity Date",IF('Facility Master'!AB6<AsOfDate,"Annual Renewal — Confirm with Ops",IF(F5<=30,"Expiring <=30d",IF(F5<=60,"Due <=60d","Valid"))))),"") -> Valid | H5: =IF(G5="Annual Renewal — Confirm with Ops","Update validity from RM letter",IF(LEFT(G5,8)="Expiring","Initiate renewal",IF(G5="Maturing <=180d","Plan refinance",IF(G5="Maturing <=1yr","Begin refinance discussion","-")))) -> -
A6: 3 | B6: =IFERROR('Facility Master'!B7,"") -> RBL Bank | C6: =IFERROR('Facility Master'!C7,"") -> Invoice Discounting (PID) | D6: =IFERROR('Facility Master'!AA7,"") -> 46022 | E6: =IFERROR(IF('Facility Master'!D7="FB-Term",'Facility Master'!Z7,'Facility Master'!AB7),"") -> 46356 | F6: =IFERROR(IF('Facility Master'!D7="FB-Term",IF('Facility Master'!Z7="","-",'Facility Master'!Z7-AsOfDate),IF('Facility Master'!AB7="","-",'Facility Master'!AB7-AsOfDate)),"-") -> 244 | G6: =IFERROR(IF('Facility Master'!D7="FB-Term",IF('Facility Master'!Z7="","No Maturity",IF(F6<=180,"Maturing <=180d",IF(F6<=365,"Maturing <=1yr","Term Loan — On Schedule"))),IF('Facility Master'!AB7="","No Validity Date",IF('Facility Master'!AB7<AsOfDate,"Annual Renewal — Confirm with Ops",IF(F6<=30,"Expiring <=30d",IF(F6<=60,"Due <=60d","Valid"))))),"") -> Valid | H6: =IF(G6="Annual Renewal — Confirm with Ops","Update validity from RM letter",IF(LEFT(G6,8)="Expiring","Initiate renewal",IF(G6="Maturing <=180d","Plan refinance",IF(G6="Maturing <=1yr","Begin refinance discussion","-")))) -> -
A7: 4 | B7: =IFERROR('Facility Master'!B8,"") -> RBL Bank | C7: =IFERROR('Facility Master'!C8,"") -> SBLC | D7: =IFERROR('Facility Master'!AA8,"") -> 45729 | E7: =IFERROR(IF('Facility Master'!D8="FB-Term",'Facility Master'!Z8,'Facility Master'!AB8),"") -> 46356 | F7: =IFERROR(IF('Facility Master'!D8="FB-Term",IF('Facility Master'!Z8="","-",'Facility Master'!Z8-AsOfDate),IF('Facility Master'!AB8="","-",'Facility Master'!AB8-AsOfDate)),"-") -> 244 | G7: =IFERROR(IF('Facility Master'!D8="FB-Term",IF('Facility Master'!Z8="","No Maturity",IF(F7<=180,"Maturing <=180d",IF(F7<=365,"Maturing <=1yr","Term Loan — On Schedule"))),IF('Facility Master'!AB8="","No Validity Date",IF('Facility Master'!AB8<AsOfDate,"Annual Renewal — Confirm with Ops",IF(F7<=30,"Expiring <=30d",IF(F7<=60,"Due <=60d","Valid"))))),"") -> Valid | H7: =IF(G7="Annual Renewal — Confirm with Ops","Update validity from RM letter",IF(LEFT(G7,8)="Expiring","Initiate renewal",IF(G7="Maturing <=180d","Plan refinance",IF(G7="Maturing <=1yr","Begin refinance discussion","-")))) -> -
A8: 5 | B8: =IFERROR('Facility Master'!B9,"") -> RBL Bank | C8: =IFERROR('Facility Master'!C9,"") -> Pre-Acceptance LCBD | D8: =IFERROR('Facility Master'!AA9,"") -> 46022 | E8: =IFERROR(IF('Facility Master'!D9="FB-Term",'Facility Master'!Z9,'Facility Master'!AB9),"") -> 46356 | F8: =IFERROR(IF('Facility Master'!D9="FB-Term",IF('Facility Master'!Z9="","-",'Facility Master'!Z9-AsOfDate),IF('Facility Master'!AB9="","-",'Facility Master'!AB9-AsOfDate)),"-") -> 244 | G8: =IFERROR(IF('Facility Master'!D9="FB-Term",IF('Facility Master'!Z9="","No Maturity",IF(F8<=180,"Maturing <=180d",IF(F8<=365,"Maturing <=1yr","Term Loan — On Schedule"))),IF('Facility Master'!AB9="","No Validity Date",IF('Facility Master'!AB9<AsOfDate,"Annual Renewal — Confirm with Ops",IF(F8<=30,"Expiring <=30d",IF(F8<=60,"Due <=60d","Valid"))))),"") -> Valid | H8: =IF(G8="Annual Renewal — Confirm with Ops","Update validity from RM letter",IF(LEFT(G8,8)="Expiring","Initiate renewal",IF(G8="Maturing <=180d","Plan refinance",IF(G8="Maturing <=1yr","Begin refinance discussion","-")))) -> -
A9: 6 | B9: =IFERROR('Facility Master'!B10,"") -> RBL Bank | C9: =IFERROR('Facility Master'!C10,"") -> Cash Credit | D9: =IFERROR('Facility Master'!AA10,"") -> 45716 | E9: =IFERROR(IF('Facility Master'!D10="FB-Term",'Facility Master'!Z10,'Facility Master'!AB10),"") -> 46356 | F9: =IFERROR(IF('Facility Master'!D10="FB-Term",IF('Facility Master'!Z10="","-",'Facility Master'!Z10-AsOfDate),IF('Facility Master'!AB10="","-",'Facility Master'!AB10-AsOfDate)),"-") -> 244 | G9: =IFERROR(IF('Facility Master'!D10="FB-Term",IF('Facility Master'!Z10="","No Maturity",IF(F9<=180,"Maturing <=180d",IF(F9<=365,"Maturing <=1yr","Term Loan — On Schedule"))),IF('Facility Master'!AB10="","No Validity Date",IF('Facility Master'!AB10<AsOfDate,"Annual Renewal — Confirm with Ops",IF(F9<=30,"Expiring <=30d",IF(F9<=60,"Due <=60d","Valid"))))),"") -> Valid | H9: =IF(G9="Annual Renewal — Confirm with Ops","Update validity from RM letter",IF(LEFT(G9,8)="Expiring","Initiate renewal",IF(G9="Maturing <=180d","Plan refinance",IF(G9="Maturing <=1yr","Begin refinance discussion","-")))) -> -
A10: 7 | B10: =IFERROR('Facility Master'!B11,"") -> RBL Bank | C10: =IFERROR('Facility Master'!C11,"") -> Working Capital Demand Loan (WCDL) | D10: =IFERROR('Facility Master'!AA11,"") -> 46022 | E10: =IFERROR(IF('Facility Master'!D11="FB-Term",'Facility Master'!Z11,'Facility Master'!AB11),"") -> 46356 | F10: =IFERROR(IF('Facility Master'!D11="FB-Term",IF('Facility Master'!Z11="","-",'Facility Master'!Z11-AsOfDate),IF('Facility Master'!AB11="","-",'Facility Master'!AB11-AsOfDate)),"-") -> 244 | G10: =IFERROR(IF('Facility Master'!D11="FB-Term",IF('Facility Master'!Z11="","No Maturity",IF(F10<=180,"Maturing <=180d",IF(F10<=365,"Maturing <=1yr","Term Loan — On Schedule"))),IF('Facility Master'!AB11="","No Validity Date",IF('Facility Master'!AB11<AsOfDate,"Annual Renewal — Confirm with Ops",IF(F10<=30,"Expiring <=30d",IF(F10<=60,"Due <=60d","Valid"))))),"") -> Valid | H10: =IF(G10="Annual Renewal — Confirm with Ops","Update validity from RM letter",IF(LEFT(G10,8)="Expiring","Initiate renewal",IF(G10="Maturing <=180d","Plan refinance",IF(G10="Maturing <=1yr","Begin refinance discussion","-")))) -> -
A11: 8 | B11: =IFERROR('Facility Master'!B12,"") -> RBL Bank | C11: =IFERROR('Facility Master'!C12,"") -> Loan Equivalent Risk (LER) | D11: =IFERROR('Facility Master'!AA12,"") -> 46022 | E11: =IFERROR(IF('Facility Master'!D12="FB-Term",'Facility Master'!Z12,'Facility Master'!AB12),"") -> 46356 | F11: =IFERROR(IF('Facility Master'!D12="FB-Term",IF('Facility Master'!Z12="","-",'Facility Master'!Z12-AsOfDate),IF('Facility Master'!AB12="","-",'Facility Master'!AB12-AsOfDate)),"-") -> 244 | G11: =IFERROR(IF('Facility Master'!D12="FB-Term",IF('Facility Master'!Z12="","No Maturity",IF(F11<=180,"Maturing <=180d",IF(F11<=365,"Maturing <=1yr","Term Loan — On Schedule"))),IF('Facility Master'!AB12="","No Validity Date",IF('Facility Master'!AB12<AsOfDate,"Annual Renewal — Confirm with Ops",IF(F11<=30,"Expiring <=30d",IF(F11<=60,"Due <=60d","Valid"))))),"") -> Valid | H11: =IF(G11="Annual Renewal — Confirm with Ops","Update validity from RM letter",IF(LEFT(G11,8)="Expiring","Initiate renewal",IF(G11="Maturing <=180d","Plan refinance",IF(G11="Maturing <=1yr","Begin refinance discussion","-")))) -> -
A12: 9 | B12: =IFERROR('Facility Master'!B13,"") -> RBL Bank | C12: =IFERROR('Facility Master'!C13,"") -> Term Loan | D12: =IFERROR('Facility Master'!AA13,"") -> 45315 | E12: =IFERROR(IF('Facility Master'!D13="FB-Term",'Facility Master'!Z13,'Facility Master'!AB13),"") -> 47208 | F12: =IFERROR(IF('Facility Master'!D13="FB-Term",IF('Facility Master'!Z13="","-",'Facility Master'!Z13-AsOfDate),IF('Facility Master'!AB13="","-",'Facility Master'!AB13-AsOfDate)),"-") -> 1096 | G12: =IFERROR(IF('Facility Master'!D13="FB-Term",IF('Facility Master'!Z13="","No Maturity",IF(F12<=180,"Maturing <=180d",IF(F12<=365,"Maturing <=1yr","Term Loan — On Schedule"))),IF('Facility Master'!AB13="","No Validity Date",IF('Facility Master'!AB13<AsOfDate,"Annual Renewal — Confirm with Ops",IF(F12<=30,"Expiring <=30d",IF(F12<=60,"Due <=60d","Valid"))))),"") -> Term Loan — On Schedule | H12: =IF(G12="Annual Renewal — Confirm with Ops","Update validity from RM letter",IF(LEFT(G12,8)="Expiring","Initiate renewal",IF(G12="Maturing <=180d","Plan refinance",IF(G12="Maturing <=1yr","Begin refinance discussion","-")))) -> -
A13: 10 | B13: =IFERROR('Facility Master'!B14,"") -> RBL Bank | C13: =IFERROR('Facility Master'!C14,"") -> SBLC for Buyer's Credit (GIFT City) | D13: =IFERROR('Facility Master'!AA14,"") -> 46022 | E13: =IFERROR(IF('Facility Master'!D14="FB-Term",'Facility Master'!Z14,'Facility Master'!AB14),"") -> 46356 | F13: =IFERROR(IF('Facility Master'!D14="FB-Term",IF('Facility Master'!Z14="","-",'Facility Master'!Z14-AsOfDate),IF('Facility Master'!AB14="","-",'Facility Master'!AB14-AsOfDate)),"-") -> 244 | G13: =IFERROR(IF('Facility Master'!D14="FB-Term",IF('Facility Master'!Z14="","No Maturity",IF(F13<=180,"Maturing <=180d",IF(F13<=365,"Maturing <=1yr","Term Loan — On Schedule"))),IF('Facility Master'!AB14="","No Validity Date",IF('Facility Master'!AB14<AsOfDate,"Annual Renewal — Confirm with Ops",IF(F13<=30,"Expiring <=30d",IF(F13<=60,"Due <=60d","Valid"))))),"") -> Valid | H13: =IF(G13="Annual Renewal — Confirm with Ops","Update validity from RM letter",IF(LEFT(G13,8)="Expiring","Initiate renewal",IF(G13="Maturing <=180d","Plan refinance",IF(G13="Maturing <=1yr","Begin refinance discussion","-")))) -> -
A14: 11 | B14: =IFERROR('Facility Master'!B15,"") -> RBL Bank | C14: =IFERROR('Facility Master'!C15,"") -> Capex LC | D14: =IFERROR('Facility Master'!AA15,"") -> 46022 | E14: =IFERROR(IF('Facility Master'!D15="FB-Term",'Facility Master'!Z15,'Facility Master'!AB15),"") -> 46356 | F14: =IFERROR(IF('Facility Master'!D15="FB-Term",IF('Facility Master'!Z15="","-",'Facility Master'!Z15-AsOfDate),IF('Facility Master'!AB15="","-",'Facility Master'!AB15-AsOfDate)),"-") -> 244 | G14: =IFERROR(IF('Facility Master'!D15="FB-Term",IF('Facility Master'!Z15="","No Maturity",IF(F14<=180,"Maturing <=180d",IF(F14<=365,"Maturing <=1yr","Term Loan — On Schedule"))),IF('Facility Master'!AB15="","No Validity Date",IF('Facility Master'!AB15<AsOfDate,"Annual Renewal — Confirm with Ops",IF(F14<=30,"Expiring <=30d",IF(F14<=60,"Due <=60d","Valid"))))),"") -> Valid | H14: =IF(G14="Annual Renewal — Confirm with Ops","Update validity from RM letter",IF(LEFT(G14,8)="Expiring","Initiate renewal",IF(G14="Maturing <=180d","Plan refinance",IF(G14="Maturing <=1yr","Begin refinance discussion","-")))) -> -
A15: 12 | B15: =IFERROR('Facility Master'!B16,"") -> RBL Bank | C15: =IFERROR('Facility Master'!C16,"") -> Overdraft backed by 100% FD (FDOD) | D15: =IFERROR('Facility Master'!AA16,"") -> 45315 | E15: =IFERROR(IF('Facility Master'!D16="FB-Term",'Facility Master'!Z16,'Facility Master'!AB16),"") -> 46356 | F15: =IFERROR(IF('Facility Master'!D16="FB-Term",IF('Facility Master'!Z16="","-",'Facility Master'!Z16-AsOfDate),IF('Facility Master'!AB16="","-",'Facility Master'!AB16-AsOfDate)),"-") -> 244 | G15: =IFERROR(IF('Facility Master'!D16="FB-Term",IF('Facility Master'!Z16="","No Maturity",IF(F15<=180,"Maturing <=180d",IF(F15<=365,"Maturing <=1yr","Term Loan — On Schedule"))),IF('Facility Master'!AB16="","No Validity Date",IF('Facility Master'!AB16<AsOfDate,"Annual Renewal — Confirm with Ops",IF(F15<=30,"Expiring <=30d",IF(F15<=60,"Due <=60d","Valid"))))),"") -> Valid | H15: =IF(G15="Annual Renewal — Confirm with Ops","Update validity from RM letter",IF(LEFT(G15,8)="Expiring","Initiate renewal",IF(G15="Maturing <=180d","Plan refinance",IF(G15="Maturing <=1yr","Begin refinance discussion","-")))) -> -
... A37: 34 | B37: =IFERROR('Facility Master'!B38,"") -> South Indian Bank | C37: =IFERROR('Facility Master'!C38,"") -> Forward Contract Limit | D37: =IFERROR('Facility Master'!AA38,"") -> 45829 | E37: =IFERROR(IF('Facility Master'!D38="FB-Term",'Facility Master'!Z38,'Facility Master'!AB38),"") -> 46194 | F37: =IFERROR(IF('Facility Master'!D38="FB-Term",IF('Facility Master'!Z38="","-",'Facility Master'!Z38-AsOfDate),IF('Facility Master'!AB38="","-",'Facility Master'!AB38-AsOfDate)),"-") -> 82 | G37: =IFERROR(IF('Facility Master'!D38="FB-Term",IF('Facility Master'!Z38="","No Maturity",IF(F37<=180,"Maturing <=180d",IF(F37<=365,"Maturing <=1yr","Term Loan — On Schedule"))),IF('Facility Master'!AB38="","No Validity Date",IF('Facility Master'!AB38<AsOfDate,"Annual Renewal — Confirm with Ops",IF(F37<=30,"Expiring <=30d",IF(F37<=60,"Due <=60d","Valid"))))),"") -> Valid | H37: =IF(G37="Annual Renewal — Confirm with Ops","Update validity from RM letter",IF(LEFT(G37,8)="Expiring","Initiate renewal",IF(G37="Maturing <=180d","Plan refinance",IF(G37="Maturing <=1yr","Begin refinance discussion","-")))) -> -
A39: Renewal Dashboard
A40: Valid (incl. TLs on schedule) | B40: =COUNTIF(G4:G37,"Valid")+COUNTIF(G4:G37,"Term Loan — On Schedule") -> 33
A41: Due <=60d | B41: =COUNTIF(G4:G37,"Due*") -> 0
A42: Expiring <=30d | B42: =COUNTIF(G4:G37,"Expiring*") -> 1
A43: Annual Renewal — Confirm | B43: =COUNTIF(G4:G37,"Annual*") -> 0
A44: No Validity Date | B44: =COUNTIF(G4:G37,"No Validity*") -> 0
A45: TLs Maturing (≤1yr) | B45: =COUNTIF(G4:G37,"Maturing <=180d")+COUNTIF(G4:G37,"Maturing <=1yr") -> 0
A46: Working capital facilities operating on annual renewal cycles show their original sanction-letter validity dates. These dates reflect the last formal renewal letter. Update Column AD in the Facility Master with the current validity date from the relationship manager after each renewal. Until updated, the status 'Annual Renewal — Confirm with Ops' is informational and does not indicate an operational breach.

Sheet Scenario Analysis
A1: SCENARIO ANALYSIS — Stress Testing
A2: JCL Debt Model | Rate & Credit Stress Testing | May 2026
A3: Scenario Inputs | C3: Base | D3: Stress | E3: Severe Stress
A4: Rate Shock (parallel +bps) | C4: 0 | D4: 0.01 | E4: 0.02
A5: Spread Increase | C5: 0 | D5: 0.0025 | E5: 0.005
A6: Utilisation Change % | C6: 0 | D6: 0.1 | E6: 0.2
A7: EBITDA Change % | C7: 0 | D7: -0.15 | E7: -0.3
A8: Total Debt Change % | C8: 0 | D8: 0.1 | E8: 0.25
A11: Scenario Outputs | C11: Base | D11: Stress | E11: Severe Stress
A12: Annual Bucket 1 Interest Cost (₹ Cr) | C12: {=IFERROR(SUMPRODUCT(('Facility Master'!H5:H38=1)*'Facility Master'!M5:M38*(1+C6)*('Facility Master'!R5:R38+C4+C5)),0)} -> 40.064012 | D12: {=IFERROR(SUMPRODUCT(('Facility Master'!H5:H38=1)*'Facility Master'!M5:M38*(1+D6)*('Facility Master'!R5:R38+D4+D5)),0)} -> 50.88988 | E12: {=IFERROR(SUMPRODUCT(('Facility Master'!H5:H38=1)*'Facility Master'!M5:M38*(1+E6)*('Facility Master'!R5:R38+E4+E5)),0)} -> 62.955651
A13: DSCR (Stressed) | C13: =IFERROR((EBITDA_Active*(1+C7)-TaxPaid_Active)/(C12+SchedTLRep_Active),0) -> 3.8765797 | D13: =IFERROR((EBITDA_Active*(1+D7)-TaxPaid_Active)/(D12+SchedTLRep_Active),0) -> 2.7941545 | E13: =IFERROR((EBITDA_Active*(1+E7)-TaxPaid_Active)/(E12+SchedTLRep_Active),0) -> 1.9165818
A14: Total Debt / EBITDA (Stressed) | C14: =IFERROR(TotalDebt_Active*(1+C8)/(EBITDA_Active*(1+C7)),0) -> 1.5965986 | D14: =IFERROR(TotalDebt_Active*(1+D8)/(EBITDA_Active*(1+D7)),0) -> 2.0661864 | E14: =IFERROR(TotalDebt_Active*(1+E8)/(EBITDA_Active*(1+E7)),0) -> 2.8510689
A15: ICR (EBITDA / Stressed Interest) | C15: =IFERROR(EBITDA_Active*(1+C7)/C12,0) -> 9.5836632 | D15: =IFERROR(EBITDA_Active*(1+D7)/D12,0) -> 6.4131808 | E15: =IFERROR(EBITDA_Active*(1+E7)/E12,0) -> 4.2692276
A18: STRESS INTERPRETATION
A19: Base case reflects current rate environment, current utilisation, and FY26E financials. Stress applies a +100 bps parallel rate shock, +25 bps spread, +10% utilisation, -15% EBITDA, and +10% debt — testing typical mid-cycle stress. Severe Stress applies +200 bps rate shock, +50 bps spread, +20% utilisation, -30% EBITDA, and +25% debt — testing tail-risk conditions. The DSCR row indicates capacity to meet stressed debt service from operating cash flow; values below 1.25x warrant proactive lender engagement. Note on base values: Scenario uses forward-looking Annual Bucket 1 Interest (₹40.06 Cr from current outstanding × effective rate) so the stress shocks act on the same basis. Covenant Tracker uses TTM Interest Expense (₹49.08 Cr from audited Section C) because most credit agreements test against audited financials. Both are correct for their purpose: Base DSCR here = 3.88x (run-rate basis), Covenant DSCR = 3.49x (TTM basis).
A22: Rate Sensitivity — Annual Interest Impact of +100 bps on each benchmark
A23: Benchmark | B23: Δ Interest @ +100 bps (₹ Cr)
A24: 1Y MCLR (RBL Bank) | B24: {=IFERROR(SUMPRODUCT(('Facility Master'!P5:P38="1Y MCLR (RBL Bank)")*('Facility Master'!H5:H38=1)*'Facility Master'!M5:M38)*0.01,0)} -> 0
A25: 3M T-Bill | B25: {=IFERROR(SUMPRODUCT(('Facility Master'!P5:P38="3M T-Bill")*('Facility Master'!H5:H38=1)*'Facility Master'!M5:M38)*0.01,0)} -> 2.959612
A26: 6M I-MCLR (ICICI) | B26: {=IFERROR(SUMPRODUCT(('Facility Master'!P5:P38="6M I-MCLR (ICICI)")*('Facility Master'!H5:H38=1)*'Facility Master'!M5:M38)*0.01,0)} -> 0.5
A27: 12M MCLR (SIB) | B27: {=IFERROR(SUMPRODUCT(('Facility Master'!P5:P38="12M MCLR (SIB)")*('Facility Master'!H5:H38=1)*'Facility Master'!M5:M38)*0.01,0)} -> 0
A28: BFRR (Bajaj) | B28: {=IFERROR(SUMPRODUCT(('Facility Master'!P5:P38="Bajaj Floating Reference Rate (BFRR)")*('Facility Master'!H5:H38=1)*'Facility Master'!M5:M38)*0.01,0)} -> 1.5
A29: Term SOFR (USD) | B29: {=IFERROR(SUMPRODUCT(('Facility Master'!P5:P38="Term SOFR (USD)")*('Facility Master'!H5:H38=1)*'Facility Master'!M5:M38)*0.01,0)} -> 0

Sheet Debt Pricing Table
A1: DEBT PRICING TABLE
A2: JCL Debt Model | Benchmark Rates, Spreads & Effective Cost | May 2026
A3: # | B3: Lender | C3: Facility | D3: Ccy | E3: Benchmark / Reference Rate | F3: Spread (bps) | G3: Eff. Rate p.a. | H3: Rate Type
A4: 1 | B4: =IFERROR('Facility Master'!B5,"") -> RBL Bank | C4: =IFERROR('Facility Master'!C5,"") -> Letter of Credit - Main Limit | D4: =IFERROR('Facility Master'!I5,"") -> INR | E4: =IFERROR('Facility Master'!P5,"") -> Fixed commission | F4: =IFERROR('Facility Master'!Q5*10000,0) -> 0 | G4: =IFERROR('Facility Master'!R5,0) -> 0 | H4: =IFERROR('Facility Master'!S5,"") -> Fixed
A5: 2 | B5: =IFERROR('Facility Master'!B6,"") -> RBL Bank | C5: =IFERROR('Facility Master'!C6,"") -> Bank Guarantee | D5: =IFERROR('Facility Master'!I6,"") -> INR | E5: =IFERROR('Facility Master'!P6,"") -> Fixed commission | F5: =IFERROR('Facility Master'!Q6*10000,0) -> 0 | G5: =IFERROR('Facility Master'!R6,0) -> 0 | H5: =IFERROR('Facility Master'!S6,"") -> Fixed
A6: 3 | B6: =IFERROR('Facility Master'!B7,"") -> RBL Bank | C6: =IFERROR('Facility Master'!C7,"") -> Invoice Discounting (PID) | D6: =IFERROR('Facility Master'!I7,"") -> INR | E6: =IFERROR('Facility Master'!P7,"") -> 1Y MCLR (RBL Bank) | F6: =IFERROR('Facility Master'!Q7*10000,0) -> 50 | G6: =IFERROR('Facility Master'!R7,0) -> 0.095 | H6: =IFERROR('Facility Master'!S7,"") -> Floating (Indicative)
A7: 4 | B7: =IFERROR('Facility Master'!B8,"") -> RBL Bank | C7: =IFERROR('Facility Master'!C8,"") -> SBLC | D7: =IFERROR('Facility Master'!I8,"") -> INR | E7: =IFERROR('Facility Master'!P8,"") -> To be decided | F7: =IFERROR('Facility Master'!Q8*10000,0) -> 50 | G7: =IFERROR('Facility Master'!R8,0) -> 0.005 | H7: =IFERROR('Facility Master'!S8,"") -> TBD
A8: 5 | B8: =IFERROR('Facility Master'!B9,"") -> RBL Bank | C8: =IFERROR('Facility Master'!C9,"") -> Pre-Acceptance LCBD | D8: =IFERROR('Facility Master'!I9,"") -> INR | E8: =IFERROR('Facility Master'!P9,"") -> 1Y MCLR (RBL Bank) | F8: =IFERROR('Facility Master'!Q9*10000,0) -> 75 | G8: =IFERROR('Facility Master'!R9,0) -> 0.0975 | H8: =IFERROR('Facility Master'!S9,"") -> Floating (Indicative)
A9: 6 | B9: =IFERROR('Facility Master'!B10,"") -> RBL Bank | C9: =IFERROR('Facility Master'!C10,"") -> Cash Credit | D9: =IFERROR('Facility Master'!I10,"") -> INR | E9: =IFERROR('Facility Master'!P10,"") -> 1Y MCLR (RBL Bank) | F9: =IFERROR('Facility Master'!Q10*10000,0) -> 5 | G9: =IFERROR('Facility Master'!R10,0) -> 0.0905 | H9: =IFERROR('Facility Master'!S10,"") -> Floating
A10: 7 | B10: =IFERROR('Facility Master'!B11,"") -> RBL Bank | C10: =IFERROR('Facility Master'!C11,"") -> Working Capital Demand Loan (WCDL) | D10: =IFERROR('Facility Master'!I11,"") -> INR | E10: =IFERROR('Facility Master'!P11,"") -> To be decided | F10: =IFERROR('Facility Master'!Q11*10000,0) -> 0 | G10: =IFERROR('Facility Master'!R11,0) -> 0 | H10: =IFERROR('Facility Master'!S11,"") -> TBD
A11: 8 | B11: =IFERROR('Facility Master'!B12,"") -> RBL Bank | C11: =IFERROR('Facility Master'!C12,"") -> Loan Equivalent Risk (LER) | D11: =IFERROR('Facility Master'!I12,"") -> INR | E11: =IFERROR('Facility Master'!P12,"") -> Bank treasury | F11: =IFERROR('Facility Master'!Q12*10000,0) -> 0 | G11: =IFERROR('Facility Master'!R12,0) -> 0 | H11: =IFERROR('Facility Master'!S12,"") -> Fixed
A12: 9 | B12: =IFERROR('Facility Master'!B13,"") -> RBL Bank | C12: =IFERROR('Facility Master'!C13,"") -> Term Loan | D12: =IFERROR('Facility Master'!I13,"") -> INR | E12: =IFERROR('Facility Master'!P13,"") -> 1Y MCLR (RBL Bank) | F12: =IFERROR('Facility Master'!Q13*10000,0) -> 75 | G12: =IFERROR('Facility Master'!R13,0) -> 0.0975 | H12: =IFERROR('Facility Master'!S13,"") -> Floating (Indicative)
A13: 10 | B13: =IFERROR('Facility Master'!B14,"") -> RBL Bank | C13: =IFERROR('Facility Master'!C14,"") -> SBLC for Buyer's Credit (GIFT City) | D13: =IFERROR('Facility Master'!I14,"") -> INR | E13: =IFERROR('Facility Master'!P14,"") -> Fixed commission | F13: =IFERROR('Facility Master'!Q14*10000,0) -> 50 | G13: =IFERROR('Facility Master'!R14,0) -> 0.005 | H13: =IFERROR('Facility Master'!S14,"") -> Fixed
A14: 11 | B14: =IFERROR('Facility Master'!B15,"") -> RBL Bank | C14: =IFERROR('Facility Master'!C15,"") -> Capex LC | D14: =IFERROR('Facility Master'!I15,"") -> INR | E14: =IFERROR('Facility Master'!P15,"") -> Fixed commission | F14: =IFERROR('Facility Master'!Q15*10000,0) -> 50 | G14: =IFERROR('Facility Master'!R15,0) -> 0.005 | H14: =IFERROR('Facility Master'!S15,"") -> Fixed
A15: 12 | B15: =IFERROR('Facility Master'!B16,"") -> RBL Bank | C15: =IFERROR('Facility Master'!C16,"") -> Overdraft backed by 100% FD (FDOD) | D15: =IFERROR('Facility Master'!I16,"") -> INR | E15: =IFERROR('Facility Master'!P16,"") -> FD rate | F15: =IFERROR('Facility Master'!Q16*10000,0) -> 25 | G15: =IFERROR('Facility Master'!R16,0) -> 0.0725 | H15: =IFERROR('Facility Master'!S16,"") -> Floating
... A37: 34 | B37: =IFERROR('Facility Master'!B38,"") -> South Indian Bank | C37: =IFERROR('Facility Master'!C38,"") -> Forward Contract Limit | D37: =IFERROR('Facility Master'!I38,"") -> INR | E37: =IFERROR('Facility Master'!P38,"") -> N/A | F37: =IFERROR('Facility Master'!Q38*10000,0) -> 0 | G37: =IFERROR('Facility Master'!R38,0) -> 0 | H37: =IFERROR('Facility Master'!S38,"") -> Fixed
A39: PRICING SUMMARY
A40: Fixed | B40: =COUNTIF(H4:H37,"Fixed") -> 15
A41: Floating (firm) | B41: =COUNTIF(H4:H37,"Floating") -> 10
A42: TBD | B42: =COUNTIF(H4:H37,"TBD") -> 6
A43: Floating (Indicative) | B43: =COUNTIF(H4:H37,"Floating (Indicative)") -> 3
A44: Total | B44: =COUNTA(H4:H37) -> 34

Sheet Validation Engine
A1: VALIDATION ENGINE
A2: =IF(B68=0,IF(B67=0,"✓ MODEL INTEGRITY CONFIRMED — ALL CHECKS PASS",B67&" non-critical check(s) for review"),"⚠ CRITICAL: "&B68&" integrity check(s) require attention") -> ✓ MODEL INTEGRITY CONFIRMED — ALL CHECKS PASS
A3: JCL Debt Model | Automated Integrity Checks | May 2026
A4: Integrity Indicator | B4: Status
A5: Bucket totals reconcile | B5: =IF(COUNTIFS(G13:G63,"Bucket",E13:E63,"FAIL")=0,IF(COUNTIFS(G13:G63,"Bucket")>0,"PASS","—"),"FAIL") -> PASS
A6: TL schedules tie out | B6: =IF(COUNTIFS(G13:G63,"TL",E13:E63,"FAIL")=0,IF(COUNTIFS(G13:G63,"TL")>0,"PASS","—"),"FAIL") -> PASS
A7: Covenants populated | B7: =IF(COUNTIFS(G13:G63,"Cov",E13:E63,"FAIL")=0,IF(COUNTIFS(G13:G63,"Cov")>0,"PASS","—"),"FAIL") -> PASS
A8: Inputs set | B8: =IF(COUNTIFS(G13:G63,"Inputs",E13:E63,"FAIL")=0,IF(COUNTIFS(G13:G63,"Inputs")>0,"PASS","—"),"FAIL") -> PASS
A9: Facilities bucketed | B9: =IF(COUNTIFS(G13:G63,"FM",E13:E63,"FAIL")=0,IF(COUNTIFS(G13:G63,"FM")>0,"PASS","—"),"FAIL") -> PASS
A11: Detailed Checks
A12: Check ID | B12: Description | C12: Expected | D12: Actual | E12: Status | F12: Severity | G12: Group
A13: VVE-01 | B13: FM row count = 34 | C13: 34 | D13: =COUNTIF('Facility Master'!A5:A38,">0") -> 34 | E13: =IFERROR(IF(ABS(D13-C13)<0.5,"PASS","FAIL"),"FAIL") -> PASS | F13: Critical | G13: FM
A14: VVE-02 | B14: Sub-limit count | C14: 24 | D14: =COUNTIF('Facility Master'!F5:F38,TRUE()) -> 24 | E14: =IFERROR(IF(ABS(D14-C14)<0.5,"PASS","FAIL"),"FAIL") -> PASS | F14: High | G14: FM
A15: VVE-03 | B15: Bucket 1 (FB Mains) count = 4 | C15: 4 | D15: =COUNTIF('Facility Master'!H5:H38,1) -> 4 | E15: =IFERROR(IF(ABS(D15-C15)<0.5,"PASS","FAIL"),"FAIL") -> PASS | F15: Critical | G15: FM
A16: VVE-04 | B16: Bucket 2 (NFB Mains) count = 4 | C16: 4 | D16: =COUNTIF('Facility Master'!H5:H38,2) -> 4 | E16: =IFERROR(IF(ABS(D16-C16)<0.5,"PASS","FAIL"),"FAIL") -> PASS | F16: Critical | G16: FM
A17: VVE-05 | B17: Bucket 3 (FD-Backed) count = 1 | C17: 1 | D17: =COUNTIF('Facility Master'!H5:H38,3) -> 1 | E17: =IFERROR(IF(ABS(D17-C17)<0.5,"PASS","FAIL"),"FAIL") -> PASS | F17: Critical | G17: FM
A18: VVE-06 | B18: All 5 lenders represented | C18: 5 | D18: {=SUMPRODUCT(1/COUNTIF('Facility Master'!B5:B38,'Facility Master'!B5:B38&""))} -> 5 | E18: =IFERROR(IF(ABS(D18-C18)<0.5,"PASS","FAIL"),"FAIL") -> PASS | F18: Critical | G18: FM
A19: VVE-07 | B19: No outstanding > sanctioned | C19: 0 | D19: {=SUMPRODUCT(('Facility Master'!M5:M38>'Facility Master'!K5:K38)*1)} -> 0 | E19: =IFERROR(IF(ABS(D19-C19)<0.5,"PASS","FAIL"),"FAIL") -> PASS | F19: High | G19: FM
A20: VVE-08 | B20: No TL maturity < drawdown | C20: 0 | D20: {=SUMPRODUCT(('Facility Master'!D5:D38="FB-Term")*('Facility Master'!Z5:Z38<'Facility Master'!X5:X38))} -> 0 | E20: =IFERROR(IF(ABS(D20-C20)<0.5,"PASS","FAIL"),"FAIL") -> PASS | F20: Critical | G20: FM
A21: VVE-09 | B21: Sanctioned Debt (B1+B2) = ₹1,320.7 Cr | C21: 1320.7 | D21: =SanctionedDebt -> 1320.7 | E21: =IFERROR(IF(ABS(D21-C21)<0.5,"PASS","FAIL"),"FAIL") -> PASS | F21: Critical | G21: Bucket
A22: VVE-10 | B22: FB Mains (Bucket 1) = ₹720.7 Cr | C22: 720.7 | D22: =FBMainsTotal -> 720.7 | E22: =IFERROR(IF(ABS(D22-C22)<0.5,"PASS","FAIL"),"FAIL") -> PASS | F22: Critical | G22: Bucket
A23: VVE-11 | B23: NFB Mains (Bucket 2) = ₹600.0 Cr | C23: 600 | D23: =NFBMainsTotal -> 600 | E23: =IFERROR(IF(ABS(D23-C23)<0.5,"PASS","FAIL"),"FAIL") -> PASS | F23: Critical | G23: Bucket
A24: VVE-12 | B24: NFB Contingent = ₹815.0 Cr | C24: 815 | D24: =NFBContingent -> 815 | E24: =IFERROR(IF(ABS(D24-C24)<0.5,"PASS","FAIL"),"FAIL") -> PASS | F24: Critical | G24: Bucket
A25: VVE-13 | B25: FD-Backed (Bucket 3) = ₹100.0 Cr | C25: 100 | D25: =FDBackedTotal -> 100 | E25: =IFERROR(IF(ABS(D25-C25)<0.5,"PASS","FAIL"),"FAIL") -> PASS | F25: Critical | G25: Bucket
A26: VVE-14 | B26: Hedge Notional Memo = ₹23.0 Cr (LER 20 + SIB Forward 3) | C26: 23 | D26: =HedgeNotionalTotal -> 23 | E26: =IFERROR(IF(ABS(D26-C26)<0.5,"PASS","FAIL"),"FAIL") -> PASS | F26: Critical | G26: Bucket
A27: VVE-15 | B27: B1 + B2 + B3 + B0 + Memo = sum of all amounts | C27: 0 | D27: =ABS(SUM('Facility Master'!K5:K38)-(SanctionedDebt+FDBackedTotal+SUMIFS('Facility Master'!K:K,'Facility Master'!H:H,0))) -> 0 | E27: =IF(D27<0.5,"PASS","FAIL") -> PASS | F27: Critical | G27: TL
A28: VVE-16 | B28: YBL TL principal value | C28: 320.7 | D28: {=IFERROR(SUMPRODUCT('Facility Master'!K5:K38*('Facility Master'!A5:A38=YBL_TL_SNo)),0)} -> 320.7 | E28: =IFERROR(IF(ABS(D28-C28)<0.5,"PASS","FAIL"),"FAIL") -> PASS | F28: Critical | G28: TL
A29: VVE-17 | B29: Bajaj TL principal value | C29: 150 | D29: {=IFERROR(SUMPRODUCT('Facility Master'!K5:K38*('Facility Master'!A5:A38=Bajaj_TL_SNo)),0)} -> 150 | E29: =IFERROR(IF(ABS(D29-C29)<0.5,"PASS","FAIL"),"FAIL") -> PASS | F29: Critical | G29: TL
A30: VVE-18 | B30: Repayment schedule sanctioned (YBL+Bajaj only) = ₹470.7 Cr | C30: 470.7 | D30: ='Repayment Schedule'!B64 -> 470.7 | E30: =IFERROR(IF(ABS(D30-C30)<0.5,"PASS","FAIL"),"FAIL") -> PASS | F30: Critical | G30: TL
A31: VVE-19 | B31: Covenant count = 24 | C31: 24 | D31: =CovenantCount -> 24 | E31: =IFERROR(IF(ABS(D31-C31)<0.5,"PASS","FAIL"),"FAIL") -> PASS | F31: Critical | G31: Cov
A32: VVE-20 | B32: EBITDA populated | C32: 1 | D32: =IF(EBITDA_Active>0,1,0) -> 1 | E32: =IFERROR(IF(ABS(D32-C32)<0.5,"PASS","FAIL"),"FAIL") -> PASS | F32: High | G32: Inputs
A33: VVE-21 | B33: TotalDebt populated | C33: 1 | D33: =IF(TotalDebt_Active>0,1,0) -> 1 | E33: =IFERROR(IF(ABS(D33-C33)<0.5,"PASS","FAIL"),"FAIL") -> PASS | F33: High | G33: Inputs
A34: VVE-22 | B34: TNW populated | C34: 1 | D34: =IF(TNW_Active>0,1,0) -> 1 | E34: =IFERROR(IF(ABS(D34-C34)<0.5,"PASS","FAIL"),"FAIL") -> PASS | F34: High | G34: Inputs
A35: VVE-23 | B35: AsOfDate set | C35: 1 | D35: =IF(AsOfDate>0,1,0) -> 1 | E35: =IFERROR(IF(ABS(D35-C35)<0.5,"PASS","FAIL"),"FAIL") -> PASS | F35: Critical | G35: Inputs
